Workbook

Sheet Summary
A1: Impact metric | B1: Immediate roll-out | C1: Six-month roll-out | D1: Waning efficacy | E1: Six-month roll-out + waning efficacy
A2: Cumulative cases averted so far | B2: =Summary[[#TOTALS],[Total cases averted so far (immediate roll-out)]] -> 182661.96 | C2: =Summary[[#TOTALS],[Total cases averted so far (six-month roll-out)]] -> 124515.61 | D2: =Summary[[#TOTALS],[Total cases averted so far (waning efficacy)]] -> 180580.63 | E2: =Summary[[#TOTALS],[Total cases averted so far (six-month roll-out, waning efficacy)]] -> 466871.3
A3: Cumulative lives saved so far | B3: =Summary[[#TOTALS],[Total lives saved so far (immediate roll-out)]] -> 1472324.4 | C3: =Summary[[#TOTALS],[Total lives saved so far (six-month roll-out)]] -> 993520.58 | D3: =Summary[[#TOTALS],[Total lives saved so far (waning efficacy)]] -> 1446310.9 | E3: =Summary[[#TOTALS],[Total lives saved so far (six-month roll-out, waning efficacy)]] -> 978.67686
A5: New cases averted per year | B5: =IFERROR(__xludf.DUMMYFUNCTION("SUM( FILTER( 'Shipments by country'!H2:H1001 * ( INDEX(Countries!S2:S1001, MATCH('Shipments by country'!B2:B1001, Countries!A2:A1001, 0) ) / 1000000 ) * INDEX('Vaccine efficacy curves'!C$2:C1001, MATCH('Shipments by country'!C2:C1001, 'Vaccine e"&"fficacy curves'!A$2:A1001, 0) ), ('Shipments by country'!E2:E1001 < NOW()) * ('Shipments by country'!I2:I1001 > 0) ) ) "),2292774.6125103454) -> 2292774.6 | C5: =IFERROR(__xludf.DUMMYFUNCTION("SUM( FILTER( 'Shipments by country'!H2:H1001 * ( INDEX(Countries!S2:S1001, MATCH('Shipments by country'!B2:B1001, Countries!A2:A1001, 0) ) / 1000000 ) * INDEX('Vaccine efficacy curves'!C$2:C1001, MATCH('Shipments by country'!C2:C1001, 'Vaccine e"&"fficacy curves'!A$2:A1001, 0) ), ('Shipments by country'!E2:E1001 < NOW()) * ('Shipments by country'!I2:I1001 > 0.25) ) ) "),1993636.7970195666) -> 1993636.8 | D5: =IFERROR(__xludf.DUMMYFUNCTION("SUM( FILTER( 'Shipments by country'!H2:H1001 * ( INDEX(Countries!S2:S1001, MATCH('Shipments by country'!B2:B1001, Countries!A2:A1001, 0))/1000000 ) * 'Shipments by country'!J2:J1001, ('Shipments by country'!E2:E1001 < NOW()) * ('Shipments by country'!I2:I"&"1001 > 0) ) )"),2747634.823742303) -> 2747634.8 | E5: =IFERROR(__xludf.DUMMYFUNCTION("SUM( FILTER( 'Shipments by country'!H2:H1001 * ( INDEX(Countries!S2:S1001, MATCH('Shipments by country'!B2:B1001, Countries!A2:A1001, 0))/1000000 ) * 'Shipments by country'!J2:J1001, ('Shipments by country'!E2:E1001 < NOW()) * ('Shipments by country'!I2:I"&"1001 > 0.25) ) )"),2371580.3980284315) -> 2371580.4
A6: New cases averted per day | B6: =B5/365.25 -> 6277.2748 | C6: =C5/365.25 -> 5458.2801 | D6: =D5/365.25 -> 7522.6142 | E6: =E5/365.25 -> 6493.0333
A7: New cases averted per hour | B7: =B6/24 -> 261.55312 | C7: =C6/24 -> 227.42834 | D7: =D6/24 -> 313.44226 | E7: =E6/24 -> 270.54305
A8: New cases averted per minute | B8: =B7/60 -> 4.3592186 | C8: =C7/60 -> 3.7904723 | D8: =D7/60 -> 5.2240376 | E8: =E7/60 -> 4.5090509
A10: New lives saved per year | B10: =IFERROR(__xludf.DUMMYFUNCTION("SUM( FILTER( 'Shipments by country'!H2:H1001 * ( INDEX(Countries!T2:T1001, MATCH('Shipments by country'!B2:B1001, Countries!A2:A1001, 0) ) / 1000000 ) * INDEX('Vaccine efficacy curves'!C$2:C1001, MATCH('Shipments by country'!C2:C1001, 'Vaccine e"&"fficacy curves'!A$2:A1001, 0) ), ('Shipments by country'!E2:E1001 < NOW()) * ('Shipments by country'!I2:I1001 > 0) ) ) "),4548.166149970364) -> 4548.1662 | C10: =IFERROR(__xludf.DUMMYFUNCTION("SUM( FILTER( 'Shipments by country'!H2:H1001 * ( INDEX(Countries!T2:T1001, MATCH('Shipments by country'!B2:B1001, Countries!A2:A1001, 0) ) / 1000000 ) * INDEX('Vaccine efficacy curves'!C$2:C1001, MATCH('Shipments by country'!C2:C1001, 'Vaccine e"&"fficacy curves'!A$2:A1001, 0) ), ('Shipments by country'!E2:E1001 < NOW()) * ('Shipments by country'!I2:I1001 > 0.25) ) ) "),3954.767880830597) -> 3954.7679 | D10: =IFERROR(__xludf.DUMMYFUNCTION("SUM( FILTER( 'Shipments by country'!H2:H1001 * ( INDEX(Countries!T2:T1001, MATCH('Shipments by country'!B2:B1001, Countries!A2:A1001, 0))/1000000 ) * 'Shipments by country'!J2:J1001, ('Shipments by country'!E2:E1001 < NOW()) * ('Shipments by country'!I2:I"&"1001 > 0) ) )"),5450.4701987004155) -> 5450.4702 | E10: =IFERROR(__xludf.DUMMYFUNCTION("SUM( FILTER( 'Shipments by country'!H2:H1001 * ( INDEX(Countries!T2:T1001, MATCH('Shipments by country'!B2:B1001, Countries!A2:A1001, 0))/1000000 ) * 'Shipments by country'!J2:J1001, ('Shipments by country'!E2:E1001 < NOW()) * ('Shipments by country'!I2:I"&"1001 > 0.25) ) )"),4704.492813812281) -> 4704.4928
A11: New lives saved per day | B11: =B10/365.25 -> 12.4522 | C11: =C10/365.25 -> 10.827564 | D11: =D10/365.25 -> 14.922574 | E11: =E10/365.25 -> 12.880199
A13: Cumulative cases expected without vaccines | B13: =MAX( 'Shipments by country'!I2:I1001 ) * SUMPRODUCT( Countries!J2:J1001, Countries!S2:S1001 ) /1000000 -> 4.9560935e+08 | C13: =MAX( 'Shipments by country'!I2:I1001 ) * SUMPRODUCT( Countries!J2:J1001, Countries!S2:S1001 ) /1000000 -> 4.9560935e+08 | D13: =MAX( 'Shipments by country'!I2:I1001 ) * SUMPRODUCT( Countries!J2:J1001, Countries!S2:S1001 ) /1000000 -> 4.9560935e+08 | E13: =MAX( 'Shipments by country'!I2:I1001 ) * SUMPRODUCT( Countries!J2:J1001, Countries!S2:S1001 ) /1000000 -> 4.9560935e+08
A14: Cumulative deaths expected without vaccines | B14: =MAX( 'Shipments by country'!I2:I1001 ) * SUMPRODUCT( Countries!J2:J1001, Countries!T2:T1001 ) /1000000 -> 1144503.1 | C14: =MAX( 'Shipments by country'!I2:I1001 ) * SUMPRODUCT( Countries!J2:J1001, Countries!T2:T1001 ) /1000000 -> 1144503.1 | D14: =MAX( 'Shipments by country'!I2:I1001 ) * SUMPRODUCT( Countries!J2:J1001, Countries!T2:T1001 ) /1000000 -> 1144503.1 | E14: =MAX( 'Shipments by country'!I2:I1001 ) * SUMPRODUCT( Countries!J2:J1001, Countries!T2:T1001 ) /1000000 -> 1144503.1
A16: Fraction of total malaria cases averted by vaccines | B16: =B2/B13 -> 0.00036856036 | C16: =C2/C13 -> 0.0002512374 | D16: =D2/D13 -> 0.00036436081 | E16: =E2/E13 -> 0.00094201472
A17: Fraction of total malaria deaths averted by vaccines | B17: =B3/B14 -> 1.2864312 | C17: =C3/C14 -> 0.86808031 | D17: =D3/D14 -> 1.2637021 | E17: =E3/E14 -> 0.00085511073

Sheet Countries
A1: Country | B1: RTS,S doses delivered | C1: R21 doses delivered | D1: RTS,S + R21 doses delivered | E1: Total RTS,S doses allocated | F1: Total R21 doses allocated | G1: Total RTS,S + R21 doses allocated | H1: Gavi income group | I1: PMI funding, USD (2023) | J1: Population at risk (2023) | K1: Population under five (2023) | L1: Eligible population (2023, 6-60 months) | M1: Eligible population covered | N1: Fraction of eligible population covered (6-60 months) | O1: Eligible population not covered (6-60 months) | P1: Fraction of eligible population not covered (6-60 months) | Q1: Total malaria cases per year (2023) | R1: Total malaria deaths per year (2023) | S1: Malaria cases per million at risk per year | T1: Malaria deaths per million at risk per year | U1: New cases averted per year (immediate roll-out) | V1: Total cases averted so far (immediate roll-out) | W1: New lives saved per year (immediate roll-out) | X1: Total lives saved so far (immediate roll-out) | Y1: New cases averted per year (six-month roll-out) | Z1: Total cases averted so far (six-month roll-out) | AA1: New lives saved per year (six-month roll-out) | AB1: Total lives saved so far (six-month roll-out) | AC1: New cases averted per year (waning efficacy) | AD1: Total cases averted so far (waning efficacy) | AE1: New lives saved per year (waning efficacy) | AF1: Total lives saved so far (waning efficacy) | AG1: New cases averted per year (six-month roll-out, waning efficacy) | AH1: Total cases averted so far (six-month roll-out, waning efficacy) | AI1: New lives saved per year (six-month roll-out, waning efficacy) | AJ1: Total lives saved so far (six-month roll-out, waning efficacy) | AK1: Current stock of further doses required (6-60 months) | AL1: Cost of current stock of further doses required, R21 (6-60 months, USD) | AM1: Share of existing dose costs funded by Gavi | AN1: Years in co-financing phase (as of 2025) | AO1: Co-financing cost of current stock of further doses required, R21 (6-60 months, USD) | AP1: Average GNI per capita (2021-2023) | AQ1: Cost to avert one case, R21 | AR1: Cost to save one life, R21 | AS1: Births per year | AT1: Flow of new vaccines required per year | AU1: Cost of flow of new vaccines required per year | AV1: Eligible population (2023, 5-36 months) | AW1: Fraction of eligible population covered (5-36 months) | AX1: Eligible population not covered (5-36 months) | AY1: Fraction of eligible population not covered (5-36 months) | AZ1: Current stock of further doses required (5-36 months) | BA1: Cost of current stock of further doses required, R21 (5-36 months, USD) | BB1: Co-financing cost of current stock of further doses required, R21 (5-36 months, USD)
A2: Angola | B2: =SUMIFS('Shipments by country'!F:F, 'Shipments by country'!B:B, A2, 'Shipments by country'!C:C, "RTS,S", 'Shipments by country'!G:G, "Delivered") -> 0 | C2: =SUMIFS('Shipments by country'!F:F, 'Shipments by country'!B:B, A2, 'Shipments by country'!C:C, "R21", 'Shipments by country'!G:G, "Delivered") -> 0 | D2: =B2+C2 -> 0 | E2: =SUMIFS('Shipments by country'!F:F, 'Shipments by country'!B:B, A2, 'Shipments by country'!C:C, "RTS,S") -> 0 | F2: =SUMIFS('Shipments by country'!F:F, 'Shipments by country'!B:B, A2, 'Shipments by country'!C:C, "R21") -> 0 | G2: =E2+F2 -> 0 | H2: Fully self-financing | I2: 19000000 | J2: 36749906 | K2: 6219256 | L2: =K2*0.9 -> 5597330.4 | M2: =G2/4 -> 0 | N2: =M2/L2 -> 0 | O2: =L2-M2 -> 5597330.4 | P2: =1-N2 -> 1 | Q2: 8251449 | R2: 16169 | S2: =Q2*1000000/J2 -> 224529.8 | T2: =R2*1000000/J2 -> 439.97391 | U2: =IFERROR(__xludf.DUMMYFUNCTION("IFERROR( SUM( FILTER( 'Shipments by country'!$H$2:$H1023 * ( INDEX(Countries!$S$2:$S1023, MATCH('Shipments by country'!$B$2:$B1023, Countries!$A$2:$A1023, 0) ) / 1000000 ) * INDEX('Vaccine efficacy curves'!$C$2:$C1023, MATCH('Shipments by country'!$C$2:$C"&"1023, 'Vaccine efficacy curves'!$A$2:$A1023, 0) ), ('Shipments by country'!$E$2:$E1023 < NOW()) * ('Shipments by country'!$I$2:$I1023 > 0) * ('Shipments by country'!$B$2:$B1023 = $A2) ) ), 0 )"),0.0) -> 0 | V2: =SUMIF('Shipments by country'!$B:$B,$A2,'Shipments by country'!$K:$K) -> 0 | W2: =IFERROR(__xludf.DUMMYFUNCTION("IFERROR( SUM( FILTER( 'Shipments by country'!$H$2:$H1023 * ( INDEX(Countries!$T$2:$T1023, MATCH('Shipments by country'!$B$2:$B1023, Countries!$A$2:$A1023, 0) ) / 1000000 ) * INDEX('Vaccine efficacy curves'!$C$2:$C1023, MATCH('Shipments by country'!$C$2:$C"&"1023, 'Vaccine efficacy curves'!$A$2:$A1023, 0) ), ('Shipments by country'!$E$2:$E1023 < NOW()) * ('Shipments by country'!$I$2:$I1023 > 0) * ('Shipments by country'!$B$2:$B1023 = $A2) ) ), 0 )"),0.0) -> 0 | X2: =SUMIF('Shipments by country'!$B:$B,$A2,'Shipments by country'!$L:$L) -> 0 | Y2: =IFERROR(__xludf.DUMMYFUNCTION("IFERROR( SUM( FILTER( 'Shipments by country'!$H$2:$H1023 * ( INDEX(Countries!$S$2:$S1023, MATCH('Shipments by country'!$B$2:$B1023, Countries!$A$2:$A1023, 0) ) / 1000000 ) * INDEX('Vaccine efficacy curves'!$C$2:$C1023, MATCH('Shipments by country'!$C$2:$C"&"1023, 'Vaccine efficacy curves'!$A$2:$A1023, 0) ), ('Shipments by country'!$E$2:$E1023 < NOW()) * ('Shipments by country'!$I$2:$I1023 > 0.25) * ('Shipments by country'!$B$2:$B1023 = $A2) ) ), 0 )"),0.0) -> 0 | Z2: =SUMIF('Shipments by country'!$B:$B,$A2,'Shipments by country'!$M:$M) -> 0 | AA2: =IFERROR(__xludf.DUMMYFUNCTION("IFERROR( SUM( FILTER( 'Shipments by country'!$H$2:$H1023 * ( INDEX(Countries!$T$2:$T1023, MATCH('Shipments by country'!$B$2:$B1023, Countries!$A$2:$A1023, 0) ) / 1000000 ) * INDEX('Vaccine efficacy curves'!$C$2:$C1023, MATCH('Shipments by country'!$C$2:$C"&"1023, 'Vaccine efficacy curves'!$A$2:$A1023, 0) ), ('Shipments by country'!$E$2:$E1023 < NOW()) * ('Shipments by country'!$I$2:$I1023 > 0.25) * ('Shipments by country'!$B$2:$B1023 = $A2) ) ), 0 )"),0.0) -> 0 | AB2: =SUMIF('Shipments by country'!$B:$B,$A2,'Shipments by country'!$N:$N) -> 0 | AC2: =IFERROR(__xludf.DUMMYFUNCTION("IFERROR( SUM( FILTER( 'Shipments by country'!$H$2:$H1023 * ( INDEX(Countries!$S$2:$S1023, MATCH('Shipments by country'!$B$2:$B1023, Countries!$A$2:$A1023, 0) ) / 1000000 ) * 'Shipments by country'!$J$2:$J1023, ('Shipments by country'!$E$2:$E1023 < NOW()) "&"* ('Shipments by country'!$I$2:$I1023 > 0) * ('Shipments by country'!$B$2:$B1023 = $A2) ) ), 0 )"),0.0) -> 0 | AD2: =SUMIF('Shipments by country'!$B:$B,$A2,'Shipments by country'!$O:$O) -> 0 | AE2: =IFERROR(__xludf.DUMMYFUNCTION("IFERROR( SUM( FILTER( 'Shipments by country'!$H$2:$H1023 * ( INDEX(Countries!$T$2:$T1023, MATCH('Shipments by country'!$B$2:$B1023, Countries!$A$2:$A1023, 0) ) / 1000000 ) * 'Shipments by country'!$J$2:$J1023, ('Shipments by country'!$E$2:$E1023 < NOW()) "&"* ('Shipments by country'!$I$2:$I1023 > 0) * ('Shipments by country'!$B$2:$B1023 = $A2) ) ), 0 )"),0.0) -> 0 | AF2: =SUMIF('Shipments by country'!$B:$B,$A2,'Shipments by country'!$P:$P) -> 0 | AG2: =IFERROR(__xludf.DUMMYFUNCTION("IFERROR( SUM( FILTER( 'Shipments by country'!$H$2:$H1023 * INDEX(Countries!$S$2:$S1023, MATCH('Shipments by country'!$B$2:$B1023, Countries!$A$2:$A1023, 0) ) / 1000000 "&" * 'Shipments by country'!$J$2:$J1023, ( 'Shipments by country'!$E$2:$E1023 < NOW() ) * ( 'Shipments by country'!$I$2:$I1023 > 0.25 ) * ( 'Shipments by country'!$"&"B$2:$B1023 = $A2 ) ) ), 0 ) "),0.0) -> 0 | AH2: =SUMIF('Shipments by country'!$B:$B,$A2,'Shipments by country'!$Q:$Q) -> 0 | AI2: =IFERROR(__xludf.DUMMYFUNCTION("IFERROR( SUM( FILTER( 'Shipments by country'!$H$2:$H1023 * ( INDEX(Countries!$T$2:$T1023, MATCH('Shipments by country'!$B$2:$B1023, Countries!$A$2:$A1023, 0) ) / 1000000 ) * 'Shipments by country"&"'!$J$2:$J1023, ('Shipments by country'!$E$2:$E1023 < NOW()) * ('Shipments by country'!$I$2:$I1023 > 0.25) * ('Shipments by country'!$B$2:$B1023 = $A2) ) ), 0 ) "),0.0) -> 0 | AJ2: =SUMIF('Shipments by country'!$B:$B,$A2,'Shipments by country'!$R:$R) -> 0 | AK2: =O2*4 -> 22389322 | AL2: =AK2*'Vaccine pricing'!B3 -> 66944072 | AM2: =IF($A2="","", LET( ctry,$A2, ctryCol,'Shipments by country'!$B$2:$B1023, vaccCol,'Shipments by country'!$C$2:$C1023, finCol,'Shipments by country'!$D$2:$D1023, doseCol,'Shipments by country'!$F$2:$F1023, price,IFERROR(VLOOKUP(vaccCol,'Vaccine pricing'!$A$2:$B1023,2,FALSE),0), totCost,SUMPRODUCT((ctryCol=ctry)*doseCol*price), gaviCost,SUMPRODUCT((ctryCol=ctry)*(finCol="Gavi")*doseCol*price), IF(totCost=0,"",gaviCost/totCost) )) | AN2: 8 | AO2: {=IF(AK2:AK46="","",IFS( H2:H46="Initial self-financing",AK2:AK46*0.2, H2:H46="Preparatory transition",AK2:AK46*0.2*POWER(1.15,N(AN2:AN46)-1), H2:H46="Accelerated transition",AK2:AK46*IF(N(AN2:AN46)<9,0.2+0.1*(N(AN2:AN46)-1),1)*'Vaccine pricing'!$B$3, H2:H46="Fully self-financing",AK2:AK46*'Vaccine pricing'!$B$3, TRUE,""))} -> 66944072 | AP2: 1933 | AQ2: ='Vaccine pricing'!$B$3*4/((S2/1000000)*'Vaccine efficacy curves'!$C$3) -> 71.022496 | AR2: ='Vaccine pricing'!$B$3*4/((T2/1000000)*'Vaccine efficacy curves'!$C$3) -> 36244.573 | AS2: =K2/5 -> 1243851.2 | AT2: =AS2*4 -> 4975404.8 | AU2: =AT2*'Vaccine pricing'!B3 -> 14876460 | AV2: =K2*31/60 -> 3213282.3 | AW2: =M2/AV2 -> 0 | AX2: =AV2-M2 -> 3213282.3 | AY2: =1-AW2 -> 1 | AZ2: =AX2*4 -> 12853129 | BA2: =AZ2*'Vaccine pricing'!B3 -> 38430856 | BB2: {=IF(AZ2:AZ46="","",IFS( H2:H46="Initial self-financing",AZ2:AZ46*0.2, H2:H46="Preparatory transition",AZ2:AZ46*0.2*POWER(1.15,N(AN2:AN46)-1), H2:H46="Accelerated transition",AZ2:AZ46*IF(N(AN2:AN46)<9,0.2+0.1*(N(AN2:AN46)-1),1)*'Vaccine pricing'!$B$3, H2:H46="Fully self-financing",AZ2:AZ46*'Vaccine pricing'!$B$3, TRUE,""))} -> 38430856
A3: Benin | B3: =SUMIFS('Shipments by country'!F:F, 'Shipments by country'!B:B, A3, 'Shipments by country'!C:C, "RTS,S", 'Shipments by country'!G:G, "Delivered") -> 976600 | C3: =SUMIFS('Shipments by country'!F:F, 'Shipments by country'!B:B, A3, 'Shipments by country'!C:C, "R21", 'Shipments by country'!G:G, "Delivered") -> 0 | D3: =B3+C3 -> 976600 | E3: =SUMIFS('Shipments by country'!F:F, 'Shipments by country'!B:B, A3, 'Shipments by country'!C:C, "RTS,S") -> 1211800 | F3: =SUMIFS('Shipments by country'!F:F, 'Shipments by country'!B:B, A3, 'Shipments by country'!C:C, "R21") -> 0 | G3: =E3+F3 -> 1211800 | H3: Preparatory transition | I3: 17000000 | J3: 14111034 | K3: 2176442 | L3: =K3*0.9 -> 1958797.8 | M3: =G3/4 -> 302950 | N3: =M3/L3 -> 0.15466119 | O3: =L3-M3 -> 1655847.8 | P3: =1-N3 -> 0.84533881 | Q3: 5127891 | R3: 9928 | S3: =Q3*1000000/J3 -> 363395.84 | T3: =R3*1000000/J3 -> 703.5629 | U3: =IFERROR(__xludf.DUMMYFUNCTION("IFERROR( SUM( FILTER( 'Shipments by country'!$H$2:$H1023 * ( INDEX(Countries!$S$2:$S1023, MATCH('Shipments by country'!$B$2:$B1023, Countries!$A$2:$A1023, 0) ) / 1000000 ) * INDEX('Vaccine efficacy curves'!$C$2:$C1023, MATCH('Shipments by country'!$C$2:$C"&"1023, 'Vaccine efficacy curves'!$A$2:$A1023, 0) ), ('Shipments by country'!$E$2:$E1023 < NOW()) * ('Shipments by country'!$I$2:$I1023 > 0) * ('Shipments by country'!$B$2:$B1023 = $A3) ) ), 0 )"),59970.08980109943) -> 59970.09 | V3: =SUMIF('Shipments by country'!$B:$B,$A3,'Shipments by country'!$K:$K) -> 1677.295 | W3: =IFERROR(__xludf.DUMMYFUNCTION("IFERROR( SUM( FILTER( 'Shipments by country'!$H$2:$H1023 * ( INDEX(Countries!$T$2:$T1023, MATCH('Shipments by country'!$B$2:$B1023, Countries!$A$2:$A1023, 0) ) / 1000000 ) * INDEX('Vaccine efficacy curves'!$C$2:$C1023, MATCH('Shipments by country'!$C$2:$C"&"1023, 'Vaccine efficacy curves'!$A$2:$A1023, 0) ), ('Shipments by country'!$E$2:$E1023 < NOW()) * ('Shipments by country'!$I$2:$I1023 > 0) * ('Shipments by country'!$B$2:$B1023 = $A3) ) ), 0 )"),118.9623833741803) -> 118.96238 | X3: =SUMIF('Shipments by country'!$B:$B,$A3,'Shipments by country'!$L:$L) -> 61394.239 | Y3: =IFERROR(__xludf.DUMMYFUNCTION("IFERROR( SUM( FILTER( 'Shipments by country'!$H$2:$H1023 * ( INDEX(Countries!$S$2:$S1023, MATCH('Shipments by country'!$B$2:$B1023, Countries!$A$2:$A1023, 0) ) / 1000000 ) * INDEX('Vaccine efficacy curves'!$C$2:$C1023, MATCH('Shipments by country'!$C$2:$C"&"1023, 'Vaccine efficacy curves'!$A$2:$A1023, 0) ), ('Shipments by country'!$E$2:$E1023 < NOW()) * ('Shipments by country'!$I$2:$I1023 > 0.25) * ('Shipments by country'!$B$2:$B1023 = $A3) ) ), 0 )"),59321.79125645971) -> 59321.791 | Z3: =SUMIF('Shipments by country'!$B:$B,$A3,'Shipments by country'!$M:$M) -> 1258.5538 | AA3: =IFERROR(__xludf.DUMMYFUNCTION("IFERROR( SUM( FILTER( 'Shipments by country'!$H$2:$H1023 * ( INDEX(Countries!$T$2:$T1023, MATCH('Shipments by country'!$B$2:$B1023, Countries!$A$2:$A1023, 0) ) / 1000000 ) * INDEX('Vaccine efficacy curves'!$C$2:$C1023, MATCH('Shipments by country'!$C$2:$C"&"1023, 'Vaccine efficacy curves'!$A$2:$A1023, 0) ), ('Shipments by country'!$E$2:$E1023 < NOW()) * ('Shipments by country'!$I$2:$I1023 > 0.25) * ('Shipments by country'!$B$2:$B1023 = $A3) ) ), 0 )"),117.67635661877368) -> 117.67636 | AB3: =SUMIF('Shipments by country'!$B:$B,$A3,'Shipments by country'!$N:$N) -> 46067.004 | AC3: =IFERROR(__xludf.DUMMYFUNCTION("IFERROR( SUM( FILTER( 'Shipments by country'!$H$2:$H1023 * ( INDEX(Countries!$S$2:$S1023, MATCH('Shipments by country'!$B$2:$B1023, Countries!$A$2:$A1023, 0) ) / 1000000 ) * 'Shipments by country'!$J$2:$J1023, ('Shipments by country'!$E$2:$E1023 < NOW()) "&"* ('Shipments by country'!$I$2:$I1023 > 0) * ('Shipments by country'!$B$2:$B1023 = $A3) ) ), 0 )"),58204.04753329213) -> 58204.048 | AD3: =SUMIF('Shipments by country'!$B:$B,$A3,'Shipments by country'!$O:$O) -> 1635.9611 | AE3: =IFERROR(__xludf.DUMMYFUNCTION("IFERROR( SUM( FILTER( 'Shipments by country'!$H$2:$H1023 * ( INDEX(Countries!$T$2:$T1023, MATCH('Shipments by country'!$B$2:$B1023, Countries!$A$2:$A1023, 0) ) / 1000000 ) * 'Shipments by country'!$J$2:$J1023, ('Shipments by country'!$E$2:$E1023 < NOW()) "&"* ('Shipments by country'!$I$2:$I1023 > 0) * ('Shipments by country'!$B$2:$B1023 = $A3) ) ), 0 )"),115.45909368402467) -> 115.45909 | AF3: =SUMIF('Shipments by country'!$B:$B,$A3,'Shipments by country'!$P:$P) -> 59881.29 | AG3: =IFERROR(__xludf.DUMMYFUNCTION("IFERROR( SUM( FILTER( 'Shipments by country'!$H$2:$H1023 * INDEX(Countries!$S$2:$S1023, MATCH('Shipments by country'!$B$2:$B1023, Countries!$A$2:$A1023, 0) ) / 1000000 "&" * 'Shipments by country'!$J$2:$J1023, ( 'Shipments by country'!$E$2:$E1023 < NOW() ) * ( 'Shipments by country'!$I$2:$I1023 > 0.25 ) * ( 'Shipments by country'!$"&"B$2:$B1023 = $A3 ) ) ), 0 ) "),57555.74898865242) -> 57555.749 | AH3: =SUMIF('Shipments by country'!$B:$B,$A3,'Shipments by country'!$Q:$Q) -> 14735.416 | AI3: =IFERROR(__xludf.DUMMYFUNCTION("IFERROR( SUM( FILTER( 'Shipments by country'!$H$2:$H1023 * ( INDEX(Countries!$T$2:$T1023, MATCH('Shipments by country'!$B$2:$B1023, Countries!$A$2:$A1023, 0) ) / 1000000 ) * 'Shipments by country"&"'!$J$2:$J1023, ('Shipments by country'!$E$2:$E1023 < NOW()) * ('Shipments by country'!$I$2:$I1023 > 0.25) * ('Shipments by country'!$B$2:$B1023 = $A3) ) ), 0 ) "),114.17306692861804) -> 114.17307 | AJ3: =SUMIF('Shipments by country'!$B:$B,$A3,'Shipments by country'!$R:$R) -> 28.528923 | AK3: =O3*4 -> 6623391.2 | AL3: =AK3*'Vaccine pricing'!B3 -> 19803940 | AM3: =IF($A3="","", LET( ctry,$A3, ctryCol,'Shipments by country'!$B$2:$B1023, vaccCol,'Shipments by country'!$C$2:$C1023, finCol,'Shipments by country'!$D$2:$D1023, doseCol,'Shipments by country'!$F$2:$F1023, price,IFERROR(VLOOKUP(vaccCol,'Vaccine pricing'!$A$2:$B1023,2,FALSE),0), totCost,SUMPRODUCT((ctryCol=ctry)*doseCol*price), gaviCost,SUMPRODUCT((ctryCol=ctry)*(finCol="Gavi")*doseCol*price), IF(totCost=0,"",gaviCost/totCost) )) -> 0.97062221 | AN3: 4 | AO3: 2014670 | AP3: 1403 | AQ3: ='Vaccine pricing'!$B$3*4/((S3/1000000)*'Vaccine efficacy curves'!$C$3) -> 43.882359 | AR3: ='Vaccine pricing'!$B$3*4/((T3/1000000)*'Vaccine efficacy curves'!$C$3) -> 22665.588 | AS3: =K3/5 -> 435288.4 | AT3: =AS3*4 -> 1741153.6 | AU3: =AT3*'Vaccine pricing'!B3 -> 5206049.3 | AV3: =K3*31/60 -> 1124495 | AW3: =M3/AV3 -> 0.26940982 | AX3: =AV3-M3 -> 821545.03 | AY3: =1-AW3 -> 0.73059018 | AZ3: =AX3*4 -> 3286180.1 | BA3: =AZ3*'Vaccine pricing'!B3 -> 9825678.6 | BB3: 999573.84
A4: Botswana | B4: =SUMIFS('Shipments by country'!F:F, 'Shipments by country'!B:B, A4, 'Shipments by country'!C:C, "RTS,S", 'Shipments by country'!G:G, "Delivered") -> 0 | C4: =SUMIFS('Shipments by country'!F:F, 'Shipments by country'!B:B, A4, 'Shipments by country'!C:C, "R21", 'Shipments by country'!G:G, "Delivered") -> 0 | D4: =B4+C4 -> 0 | E4: =SUMIFS('Shipments by country'!F:F, 'Shipments by country'!B:B, A4, 'Shipments by country'!C:C, "RTS,S") -> 0 | F4: =SUMIFS('Shipments by country'!F:F, 'Shipments by country'!B:B, A4, 'Shipments by country'!C:C, "R21") -> 0 | G4: =E4+F4 -> 0 | H4: N/A | I4: 0 | J4: 1644352 | K4: 293659 | L4: =K4*0.9 -> 264293.1 | M4: =G4/4 -> 0 | N4: =M4/L4 -> 0 | O4: =L4-M4 -> 264293.1 | P4: =1-N4 -> 1 | Q4: 778 | R4: 4 | S4: =Q4*1000000/J4 -> 473.13471 | T4: =R4*1000000/J4 -> 2.4325692 | U4: =IFERROR(__xludf.DUMMYFUNCTION("IFERROR( SUM( FILTER( 'Shipments by country'!$H$2:$H1023 * ( INDEX(Countries!$S$2:$S1023, MATCH('Shipments by country'!$B$2:$B1023, Countries!$A$2:$A1023, 0) ) / 1000000 ) * INDEX('Vaccine efficacy curves'!$C$2:$C1023, MATCH('Shipments by country'!$C$2:$C"&"1023, 'Vaccine efficacy curves'!$A$2:$A1023, 0) ), ('Shipments by country'!$E$2:$E1023 < NOW()) * ('Shipments by country'!$I$2:$I1023 > 0) * ('Shipments by country'!$B$2:$B1023 = $A4) ) ), 0 )"),0.0) -> 0 | V4: =SUMIF('Shipments by country'!$B:$B,$A4,'Shipments by country'!$K:$K) -> 0 | W4: =IFERROR(__xludf.DUMMYFUNCTION("IFERROR( SUM( FILTER( 'Shipments by country'!$H$2:$H1023 * ( INDEX(Countries!$T$2:$T1023, MATCH('Shipments by country'!$B$2:$B1023, Countries!$A$2:$A1023, 0) ) / 1000000 ) * INDEX('Vaccine efficacy curves'!$C$2:$C1023, MATCH('Shipments by country'!$C$2:$C"&"1023, 'Vaccine efficacy curves'!$A$2:$A1023, 0) ), ('Shipments by country'!$E$2:$E1023 < NOW()) * ('Shipments by country'!$I$2:$I1023 > 0) * ('Shipments by country'!$B$2:$B1023 = $A4) ) ), 0 )"),0.0) -> 0 | X4: =SUMIF('Shipments by country'!$B:$B,$A4,'Shipments by country'!$L:$L) -> 0 | Y4: =IFERROR(__xludf.DUMMYFUNCTION("IFERROR( SUM( FILTER( 'Shipments by country'!$H$2:$H1023 * ( INDEX(Countries!$S$2:$S1023, MATCH('Shipments by country'!$B$2:$B1023, Countries!$A$2:$A1023, 0) ) / 1000000 ) * INDEX('Vaccine efficacy curves'!$C$2:$C1023, MATCH('Shipments by country'!$C$2:$C"&"1023, 'Vaccine efficacy curves'!$A$2:$A1023, 0) ), ('Shipments by country'!$E$2:$E1023 < NOW()) * ('Shipments by country'!$I$2:$I1023 > 0.25) * ('Shipments by country'!$B$2:$B1023 = $A4) ) ), 0 )"),0.0) -> 0 | Z4: =SUMIF('Shipments by country'!$B:$B,$A4,'Shipments by country'!$M:$M) -> 0 | AA4: =IFERROR(__xludf.DUMMYFUNCTION("IFERROR( SUM( FILTER( 'Shipments by country'!$H$2:$H1023 * ( INDEX(Countries!$T$2:$T1023, MATCH('Shipments by country'!$B$2:$B1023, Countries!$A$2:$A1023, 0) ) / 1000000 ) * INDEX('Vaccine efficacy curves'!$C$2:$C1023, MATCH('Shipments by country'!$C$2:$C"&"1023, 'Vaccine efficacy curves'!$A$2:$A1023, 0) ), ('Shipments by country'!$E$2:$E1023 < NOW()) * ('Shipments by country'!$I$2:$I1023 > 0.25) * ('Shipments by country'!$B$2:$B1023 = $A4) ) ), 0 )"),0.0) -> 0 | AB4: =SUMIF('Shipments by country'!$B:$B,$A4,'Shipments by country'!$N:$N) -> 0 | AC4: =IFERROR(__xludf.DUMMYFUNCTION("IFERROR( SUM( FILTER( 'Shipments by country'!$H$2:$H1023 * ( INDEX(Countries!$S$2:$S1023, MATCH('Shipments by country'!$B$2:$B1023, Countries!$A$2:$A1023, 0) ) / 1000000 ) * 'Shipments by country'!$J$2:$J1023, ('Shipments by country'!$E$2:$E1023 < NOW()) "&"* ('Shipments by country'!$I$2:$I1023 > 0) * ('Shipments by country'!$B$2:$B1023 = $A4) ) ), 0 )"),0.0) -> 0 | AD4: =SUMIF('Shipments by country'!$B:$B,$A4,'Shipments by country'!$O:$O) -> 0 | AE4: =IFERROR(__xludf.DUMMYFUNCTION("IFERROR( SUM( FILTER( 'Shipments by country'!$H$2:$H1023 * ( INDEX(Countries!$T$2:$T1023, MATCH('Shipments by country'!$B$2:$B1023, Countries!$A$2:$A1023, 0) ) / 1000000 ) * 'Shipments by country'!$J$2:$J1023, ('Shipments by country'!$E$2:$E1023 < NOW()) "&"* ('Shipments by country'!$I$2:$I1023 > 0) * ('Shipments by country'!$B$2:$B1023 = $A4) ) ), 0 )"),0.0) -> 0 | AF4: =SUMIF('Shipments by country'!$B:$B,$A4,'Shipments by country'!$P:$P) -> 0 | AG4: =IFERROR(__xludf.DUMMYFUNCTION("IFERROR( SUM( FILTER( 'Shipments by country'!$H$2:$H1023 * INDEX(Countries!$S$2:$S1023, MATCH('Shipments by country'!$B$2:$B1023, Countries!$A$2:$A1023, 0) ) / 1000000 "&" * 'Shipments by country'!$J$2:$J1023, ( 'Shipments by country'!$E$2:$E1023 < NOW() ) * ( 'Shipments by country'!$I$2:$I1023 > 0.25 ) * ( 'Shipments by country'!$"&"B$2:$B1023 = $A4 ) ) ), 0 ) "),0.0) -> 0 | AH4: =SUMIF('Shipments by country'!$B:$B,$A4,'Shipments by country'!$Q:$Q) -> 0 | AI4: =IFERROR(__xludf.DUMMYFUNCTION("IFERROR( SUM( FILTER( 'Shipments by country'!$H$2:$H1023 * ( INDEX(Countries!$T$2:$T1023, MATCH('Shipments by country'!$B$2:$B1023, Countries!$A$2:$A1023, 0) ) / 1000000 ) * 'Shipments by country"&"'!$J$2:$J1023, ('Shipments by country'!$E$2:$E1023 < NOW()) * ('Shipments by country'!$I$2:$I1023 > 0.25) * ('Shipments by country'!$B$2:$B1023 = $A4) ) ), 0 ) "),0.0) -> 0 | AJ4: =SUMIF('Shipments by country'!$B:$B,$A4,'Shipments by country'!$R:$R) -> 0 | AK4: =O4*4 -> 1057172.4 | AL4: =AK4*'Vaccine pricing'!B3 -> 3160945.5 | AM4: =IF($A4="","", LET( ctry,$A4, ctryCol,'Shipments by country'!$B$2:$B1023, vaccCol,'Shipments by country'!$C$2:$C1023, finCol,'Shipments by country'!$D$2:$D1023, doseCol,'Shipments by country'!$F$2:$F1023, price,IFERROR(VLOOKUP(vaccCol,'Vaccine pricing'!$A$2:$B1023,2,FALSE),0), totCost,SUMPRODUCT((ctryCol=ctry)*doseCol*price), gaviCost,SUMPRODUCT((ctryCol=ctry)*(finCol="Gavi")*doseCol*price), IF(totCost=0,"",gaviCost/totCost) )) | AN4: - | AP4: - | AQ4: ='Vaccine pricing'!$B$3*4/((S4/1000000)*'Vaccine efficacy curves'!$C$3) -> 33704.284 | AR4: ='Vaccine pricing'!$B$3*4/((T4/1000000)*'Vaccine efficacy curves'!$C$3) -> 6555483.3 | AS4: =K4/5 -> 58731.8 | AT4: =AS4*4 -> 234927.2 | AU4: =AT4*'Vaccine pricing'!B3 -> 702432.33 | AV4: =K4*31/60 -> 151723.82 | AW4: =M4/AV4 -> 0 | AX4: =AV4-M4 -> 151723.82 | AY4: =1-AW4 -> 1 | AZ4: =AX4*4 -> 606895.27 | BA4: =AZ4*'Vaccine pricing'!B3 -> 1814616.8
A5: Burkina Faso | B5: =SUMIFS('Shipments by country'!F:F, 'Shipments by country'!B:B, A5, 'Shipments by country'!C:C, "RTS,S", 'Shipments by country'!G:G, "Delivered") -> 1374600 | C5: =SUMIFS('Shipments by country'!F:F, 'Shipments by country'!B:B, A5, 'Shipments by country'!C:C, "R21", 'Shipments by country'!G:G, "Delivered") -> 800000 | D5: =B5+C5 -> 2174600 | E5: =SUMIFS('Shipments by country'!F:F, 'Shipments by country'!B:B, A5, 'Shipments by country'!C:C, "RTS,S") -> 1374600 | F5: =SUMIFS('Shipments by country'!F:F, 'Shipments by country'!B:B, A5, 'Shipments by country'!C:C, "R21") -> 2209800 | G5: =E5+F5 -> 3584400 | H5: Initial self-financing | I5: 26000000 | J5: 23025776 | K5: 3351139 | L5: =K5*0.9 -> 3016025.1 | M5: =G5/4 -> 896100 | N5: =M5/L5 -> 0.29711291 | O5: =L5-M5 -> 2119925.1 | P5: =1-N5 -> 0.70288709 | Q5: 8139355 | R5: 16146 | S5: =Q5*1000000/J5 -> 353488.85 | T5: =R5*1000000/J5 -> 701.21415 | U5: =IFERROR(__xludf.DUMMYFUNCTION("IFERROR( SUM( FILTER( 'Shipments by country'!$H$2:$H1023 * ( INDEX(Countries!$S$2:$S1023, MATCH('Shipments by country'!$B$2:$B1023, Countries!$A$2:$A1023, 0) ) / 1000000 ) * INDEX('Vaccine efficacy curves'!$C$2:$C1023, MATCH('Shipments by country'!$C$2:$C"&"1023, 'Vaccine efficacy curves'!$A$2:$A1023, 0) ), ('Shipments by country'!$E$2:$E1023 < NOW()) * ('Shipments by country'!$I$2:$I1023 > 0) * ('Shipments by country'!$B$2:$B1023 = $A5) ) ), 0 )"),152558.00943212508) -> 152558.01 | V5: =SUMIF('Shipments by country'!$B:$B,$A5,'Shipments by country'!$K:$K) -> 5310.2456 | W5: =IFERROR(__xludf.DUMMYFUNCTION("IFERROR( SUM( FILTER( 'Shipments by country'!$H$2:$H1023 * ( INDEX(Countries!$T$2:$T1023, MATCH('Shipments by country'!$B$2:$B1023, Countries!$A$2:$A1023, 0) ) / 1000000 ) * INDEX('Vaccine efficacy curves'!$C$2:$C1023, MATCH('Shipments by country'!$C$2:$C"&"1023, 'Vaccine efficacy curves'!$A$2:$A1023, 0) ), ('Shipments by country'!$E$2:$E1023 < NOW()) * ('Shipments by country'!$I$2:$I1023 > 0) * ('Shipments by country'!$B$2:$B1023 = $A5) ) ), 0 )"),302.6286014421404) -> 302.6286 | X5: =SUMIF('Shipments by country'!$B:$B,$A5,'Shipments by country'!$L:$L) -> 116258.68 | Y5: =IFERROR(__xludf.DUMMYFUNCTION("IFERROR( SUM( FILTER( 'Shipments by country'!$H$2:$H1023 * ( INDEX(Countries!$S$2:$S1023, MATCH('Shipments by country'!$B$2:$B1023, Countries!$A$2:$A1023, 0) ) / 1000000 ) * INDEX('Vaccine efficacy curves'!$C$2:$C1023, MATCH('Shipments by country'!$C$2:$C"&"1023, 'Vaccine efficacy curves'!$A$2:$A1023, 0) ), ('Shipments by country'!$E$2:$E1023 < NOW()) * ('Shipments by country'!$I$2:$I1023 > 0.25) * ('Shipments by country'!$B$2:$B1023 = $A5) ) ), 0 )"),107617.55841019211) -> 107617.56 | Z5: =SUMIF('Shipments by country'!$B:$B,$A5,'Shipments by country'!$M:$M) -> 3621.0306 | AA5: =IFERROR(__xludf.DUMMYFUNCTION("IFERROR( SUM( FILTER( 'Shipments by country'!$H$2:$H1023 * ( INDEX(Countries!$T$2:$T1023, MATCH('Shipments by country'!$B$2:$B1023, Countries!$A$2:$A1023, 0) ) / 1000000 ) * INDEX('Vaccine efficacy curves'!$C$2:$C1023, MATCH('Shipments by country'!$C$2:$C"&"1023, 'Vaccine efficacy curves'!$A$2:$A1023, 0) ), ('Shipments by country'!$E$2:$E1023 < NOW()) * ('Shipments by country'!$I$2:$I1023 > 0.25) * ('Shipments by country'!$B$2:$B1023 = $A5) ) ), 0 )"),213.4804413975017) -> 213.48044 | AB5: =SUMIF('Shipments by country'!$B:$B,$A5,'Shipments by country'!$N:$N) -> 79276.226 | AC5: =IFERROR(__xludf.DUMMYFUNCTION("IFERROR( SUM( FILTER( 'Shipments by country'!$H$2:$H1023 * ( INDEX(Countries!$S$2:$S1023, MATCH('Shipments by country'!$B$2:$B1023, Countries!$A$2:$A1023, 0) ) / 1000000 ) * 'Shipments by country'!$J$2:$J1023, ('Shipments by country'!$E$2:$E1023 < NOW()) "&"* ('Shipments by country'!$I$2:$I1023 > 0) * ('Shipments by country'!$B$2:$B1023 = $A5) ) ), 0 )"),176361.47787601806) -> 176361.48 | AD5: =SUMIF('Shipments by country'!$B:$B,$A5,'Shipments by country'!$O:$O) -> 5124.6193 | AE5: =IFERROR(__xludf.DUMMYFUNCTION("IFERROR( SUM( FILTER( 'Shipments by country'!$H$2:$H1023 * ( INDEX(Countries!$T$2:$T1023, MATCH('Shipments by country'!$B$2:$B1023, Countries!$A$2:$A1023, 0) ) / 1000000 ) * 'Shipments by country'!$J$2:$J1023, ('Shipments by country'!$E$2:$E1023 < NOW()) "&"* ('Shipments by country'!$I$2:$I1023 > 0) * ('Shipments by country'!$B$2:$B1023 = $A5) ) ), 0 )"),349.8474291619162) -> 349.84743 | AF5: =SUMIF('Shipments by country'!$B:$B,$A5,'Shipments by country'!$P:$P) -> 112194.71 | AG5: =IFERROR(__xludf.DUMMYFUNCTION("IFERROR( SUM( FILTER( 'Shipments by country'!$H$2:$H1023 * INDEX(Countries!$S$2:$S1023, MATCH('Shipments by country'!$B$2:$B1023, Countries!$A$2:$A1023, 0) ) / 1000000 "&" * 'Shipments by country'!$J$2:$J1023, ( 'Shipments by country'!$E$2:$E1023 < NOW() ) * ( 'Shipments by country'!$I$2:$I1023 > 0.25 ) * ( 'Shipments by country'!$"&"B$2:$B1023 = $A5 ) ) ), 0 ) "),116173.37382878644) -> 116173.37 | AH5: =SUMIF('Shipments by country'!$B:$B,$A5,'Shipments by country'!$Q:$Q) -> 35818.456 | AI5: =IFERROR(__xludf.DUMMYFUNCTION("IFERROR( SUM( FILTER( 'Shipments by country'!$H$2:$H1023 * ( INDEX(Countries!$T$2:$T1023, MATCH('Shipments by country'!$B$2:$B1023, Countries!$A$2:$A1023, 0) ) / 1000000 ) * 'Shipments by country"&"'!$J$2:$J1023, ('Shipments by country'!$E$2:$E1023 < NOW()) * ('Shipments by country'!$I$2:$I1023 > 0.25) * ('Shipments by country'!$B$2:$B1023 = $A5) ) ), 0 ) "),230.4525719592751) -> 230.45257 | AJ5: =SUMIF('Shipments by country'!$B:$B,$A5,'Shipments by country'!$R:$R) -> 71.052902 | AK5: =O5*4 -> 8479700.4 | AL5: =AK5*'Vaccine pricing'!B3 -> 25354304 | AM5: =IF($A5="","", LET( ctry,$A5, ctryCol,'Shipments by country'!$B$2:$B1023, vaccCol,'Shipments by country'!$C$2:$C1023, finCol,'Shipments by country'!$D$2:$D1023, doseCol,'Shipments by country'!$F$2:$F1023, price,IFERROR(VLOOKUP(vaccCol,'Vaccine pricing'!$A$2:$B1023,2,FALSE),0), totCost,SUMPRODUCT((ctryCol=ctry)*doseCol*price), gaviCost,SUMPRODUCT((ctryCol=ctry)*(finCol="Gavi")*doseCol*price), IF(totCost=0,"",gaviCost/totCost) )) -> 0.9621415 | AN5: 11 | AO5: 1695940.1 | AP5: 850 | AQ5: ='Vaccine pricing'!$B$3*4/((S5/1000000)*'Vaccine efficacy curves'!$C$3) -> 45.11222 | AR5: ='Vaccine pricing'!$B$3*4/((T5/1000000)*'Vaccine efficacy curves'!$C$3) -> 22741.507 | AS5: =K5/5 -> 670227.8 | AT5: =AS5*4 -> 2680911.2 | AU5: =AT5*'Vaccine pricing'!B3 -> 8015924.5 | AV5: =K5*31/60 -> 1731421.8 | AW5: =M5/AV5 -> 0.51755152 | AX5: =AV5-M5 -> 835321.82 | AY5: =1-AW5 -> 0.48244848 | AZ5: =AX5*4 -> 3341287.3 | BA5: =AZ5*'Vaccine pricing'!B3 -> 9990448.9 | BB5: 668257.45
A6: Burundi | B6: =SUMIFS('Shipments by country'!F:F, 'Shipments by country'!B:B, A6, 'Shipments by country'!C:C, "RTS,S", 'Shipments by country'!G:G, "Delivered") -> 1426250 | C6: =SUMIFS('Shipments by country'!F:F, 'Shipments by country'!B:B, A6, 'Shipments by country'!C:C, "R21", 'Shipments by country'!G:G, "Delivered") -> 0 | D6: =B6+C6 -> 1426250 | E6: =SUMIFS('Shipments by country'!F:F, 'Shipments by country'!B:B, A6, 'Shipments by country'!C:C, "RTS,S") -> 1445550 | F6: =SUMIFS('Shipments by country'!F:F, 'Shipments by country'!B:B, A6, 'Shipments by country'!C:C, "R21") -> 0 | G6: =E6+F6 -> 1445550 | H6: Initial self-financing | I6: 15000000 | J6: 13689449 | K6: 2167233 | L6: =K6*0.9 -> 1950509.7 | M6: =G6/4 -> 361387.5 | N6: =M6/L6 -> 0.18527849 | O6: =L6-M6 -> 1589122.2 | P6: =1-N6 -> 0.81472151 | Q6: 3354726 | R6: 6302 | S6: =Q6*1000000/J6 -> 245059.24 | T6: =R6*1000000/J6 -> 460.35454 | U6: =IFERROR(__xludf.DUMMYFUNCTION("IFERROR( SUM( FILTER( 'Shipments by country'!$H$2:$H1023 * ( INDEX(Countries!$S$2:$S1023, MATCH('Shipments by country'!$B$2:$B1023, Countries!$A$2:$A1023, 0) ) / 1000000 ) * INDEX('Vaccine efficacy curves'!$C$2:$C1023, MATCH('Shipments by country'!$C$2:$C"&"1023, 'Vaccine efficacy curves'!$A$2:$A1023, 0) ), ('Shipments by country'!$E$2:$E1023 < NOW()) * ('Shipments by country'!$I$2:$I1023 > 0) * ('Shipments by country'!$B$2:$B1023 = $A6) ) ), 0 )"),71538.0123056439) -> 71538.012 | V6: =SUMIF('Shipments by country'!$B:$B,$A6,'Shipments by country'!$K:$K) -> 620.4038 | W6: =IFERROR(__xludf.DUMMYFUNCTION("IFERROR( SUM( FILTER( 'Shipments by country'!$H$2:$H1023 * ( INDEX(Countries!$T$2:$T1023, MATCH('Shipments by country'!$B$2:$B1023, Countries!$A$2:$A1023, 0) ) / 1000000 ) * INDEX('Vaccine efficacy curves'!$C$2:$C1023, MATCH('Shipments by country'!$C$2:$C"&"1023, 'Vaccine efficacy curves'!$A$2:$A1023, 0) ), ('Shipments by country'!$E$2:$E1023 < NOW()) * ('Shipments by country'!$I$2:$I1023 > 0) * ('Shipments by country'!$B$2:$B1023 = $A6) ) ), 0 )"),141.90961650977584) -> 141.90962 | X6: =SUMIF('Shipments by country'!$B:$B,$A6,'Shipments by country'!$L:$L) -> 24124.99 | Y6: =IFERROR(__xludf.DUMMYFUNCTION("IFERROR( SUM( FILTER( 'Shipments by country'!$H$2:$H1023 * ( INDEX(Countries!$S$2:$S1023, MATCH('Shipments by country'!$B$2:$B1023, Countries!$A$2:$A1023, 0) ) / 1000000 ) * INDEX('Vaccine efficacy curves'!$C$2:$C1023, MATCH('Shipments by country'!$C$2:$C"&"1023, 'Vaccine efficacy curves'!$A$2:$A1023, 0) ), ('Shipments by country'!$E$2:$E1023 < NOW()) * ('Shipments by country'!$I$2:$I1023 > 0.25) * ('Shipments by country'!$B$2:$B1023 = $A6) ) ), 0 )"),48748.58636620977) -> 48748.586 | Z6: =SUMIF('Shipments by country'!$B:$B,$A6,'Shipments by country'!$M:$M) -> 331.28419 | AA6: =IFERROR(__xludf.DUMMYFUNCTION("IFERROR( SUM( FILTER( 'Shipments by country'!$H$2:$H1023 * ( INDEX(Countries!$T$2:$T1023, MATCH('Shipments by country'!$B$2:$B1023, Countries!$A$2:$A1023, 0) ) / 1000000 ) * INDEX('Vaccine efficacy curves'!$C$2:$C1023, MATCH('Shipments by country'!$C$2:$C"&"1023, 'Vaccine efficacy curves'!$A$2:$A1023, 0) ), ('Shipments by country'!$E$2:$E1023 < NOW()) * ('Shipments by country'!$I$2:$I1023 > 0.25) * ('Shipments by country'!$B$2:$B1023 = $A6) ) ), 0 )"),96.70234010788607) -> 96.70234 | AB6: =SUMIF('Shipments by country'!$B:$B,$A6,'Shipments by country'!$N:$N) -> 12882.3 | AC6: =IFERROR(__xludf.DUMMYFUNCTION("IFERROR( SUM( FILTER( 'Shipments by country'!$H$2:$H1023 * ( INDEX(Countries!$S$2:$S1023, MATCH('Shipments by country'!$B$2:$B1023, Countries!$A$2:$A1023, 0) ) / 1000000 ) * 'Shipments by country'!$J$2:$J1023, ('Shipments by country'!$E$2:$E1023 < NOW()) "&"* ('Shipments by country'!$I$2:$I1023 > 0) * ('Shipments by country'!$B$2:$B1023 = $A6) ) ), 0 )"),71538.0123056439) -> 71538.012 | AD6: =SUMIF('Shipments by country'!$B:$B,$A6,'Shipments by country'!$O:$O) -> 620.4038 | AE6: =IFERROR(__xludf.DUMMYFUNCTION("IFERROR( SUM( FILTER( 'Shipments by country'!$H$2:$H1023 * ( INDEX(Countries!$T$2:$T1023, MATCH('Shipments by country'!$B$2:$B1023, Countries!$A$2:$A1023, 0) ) / 1000000 ) * 'Shipments by country'!$J$2:$J1023, ('Shipments by country'!$E$2:$E1023 < NOW()) "&"* ('Shipments by country'!$I$2:$I1023 > 0) * ('Shipments by country'!$B$2:$B1023 = $A6) ) ), 0 )"),141.90961650977584) -> 141.90962 | AF6: =SUMIF('Shipments by country'!$B:$B,$A6,'Shipments by country'!$P:$P) -> 24124.99 | AG6: =IFERROR(__xludf.DUMMYFUNCTION("IFERROR( SUM( FILTER( 'Shipments by country'!$H$2:$H1023 * INDEX(Countries!$S$2:$S1023, MATCH('Shipments by country'!$B$2:$B1023, Countries!$A$2:$A1023, 0) ) / 1000000 "&" * 'Shipments by country'!$J$2:$J1023, ( 'Shipments by country'!$E$2:$E1023 < NOW() ) * ( 'Shipments by country'!$I$2:$I1023 > 0.25 ) * ( 'Shipments by country'!$"&"B$2:$B1023 = $A6 ) ) ), 0 ) "),48748.58636620977) -> 48748.586 | AH6: =SUMIF('Shipments by country'!$B:$B,$A6,'Shipments by country'!$Q:$Q) -> 11242.69 | AI6: =IFERROR(__xludf.DUMMYFUNCTION("IFERROR( SUM( FILTER( 'Shipments by country'!$H$2:$H1023 * ( INDEX(Countries!$T$2:$T1023, MATCH('Shipments by country'!$B$2:$B1023, Countries!$A$2:$A1023, 0) ) / 1000000 ) * 'Shipments by country"&"'!$J$2:$J1023, ('Shipments by country'!$E$2:$E1023 < NOW()) * ('Shipments by country'!$I$2:$I1023 > 0.25) * ('Shipments by country'!$B$2:$B1023 = $A6) ) ), 0 ) "),96.70234010788607) -> 96.70234 | AJ6: =SUMIF('Shipments by country'!$B:$B,$A6,'Shipments by country'!$R:$R) -> 21.119887 | AK6: =O6*4 -> 6356488.8 | AL6: =AK6*'Vaccine pricing'!B3 -> 19005902 | AM6: =IF($A6="","", LET( ctry,$A6, ctryCol,'Shipments by country'!$B$2:$B1023, vaccCol,'Shipments by country'!$C$2:$C1023, finCol,'Shipments by country'!$D$2:$D1023, doseCol,'Shipments by country'!$F$2:$F1023, price,IFERROR(VLOOKUP(vaccCol,'Vaccine pricing'!$A$2:$B1023,2,FALSE),0), totCost,SUMPRODUCT((ctryCol=ctry)*doseCol*price), gaviCost,SUMPRODUCT((ctryCol=ctry)*(finCol="Gavi")*doseCol*price), IF(totCost=0,"",gaviCost/totCost) )) -> 0.97858946 | AN6: 11 | AO6: 1271297.8 | AP6: 237 | AQ6: ='Vaccine pricing'!$B$3*4/((S6/1000000)*'Vaccine efficacy curves'!$C$3) -> 65.0727 | AR6: ='Vaccine pricing'!$B$3*4/((T6/1000000)*'Vaccine efficacy curves'!$C$3) -> 34639.968 | AS6: =K6/5 -> 433446.6 | AT6: =AS6*4 -> 1733786.4 | AU6: =AT6*'Vaccine pricing'!B3 -> 5184021.3 | AV6: =K6*31/60 -> 1119737.1 | AW6: =M6/AV6 -> 0.32274318 | AX6: =AV6-M6 -> 758349.55 | AY6: =1-AW6 -> 0.67725682 | AZ6: =AX6*4 -> 3033398.2 | BA6: =AZ6*'Vaccine pricing'!B3 -> 9069860.6 | BB6: 606679.64
A7: Cameroon | B7: =SUMIFS('Shipments by country'!F:F, 'Shipments by country'!B:B, A7, 'Shipments by country'!C:C, "RTS,S", 'Shipments by country'!G:G, "Delivered") -> 961800 | C7: =SUMIFS('Shipments by country'!F:F, 'Shipments by country'!B:B, A7, 'Shipments by country'!C:C, "R21", 'Shipments by country'!G:G, "Delivered") -> 0 | D7: =B7+C7 -> 961800 | E7: =SUMIFS('Shipments by country'!F:F, 'Shipments by country'!B:B, A7, 'Shipments by country'!C:C, "RTS,S") -> 1387900 | F7: =SUMIFS('Shipments by country'!F:F, 'Shipments by country'!B:B, A7, 'Shipments by country'!C:C, "R21") -> 0 | G7: =E7+F7 -> 1387900 | H7: Preparatory transition | I7: 23500000 | J7: 28372687 | K7: 4393101 | L7: =K7*0.9 -> 3953790.9 | M7: =G7/4 -> 346975 | N7: =M7/L7 -> 0.087757549 | O7: =L7-M7 -> 3606815.9 | P7: =1-N7 -> 0.91224245 | Q7: 7343057 | R7: 11602 | S7: =Q7*1000000/J7 -> 258807.25 | T7: =R7*1000000/J7 -> 408.91439 | U7: =IFERROR(__xludf.DUMMYFUNCTION("IFERROR( SUM( FILTER( 'Shipments by country'!$H$2:$H1023 * ( INDEX(Countries!$S$2:$S1023, MATCH('Shipments by country'!$B$2:$B1023, Countries!$A$2:$A1023, 0) ) / 1000000 ) * INDEX('Vaccine efficacy curves'!$C$2:$C1023, MATCH('Shipments by country'!$C$2:$C"&"1023, 'Vaccine efficacy curves'!$A$2:$A1023, 0) ), ('Shipments by country'!$E$2:$E1023 < NOW()) * ('Shipments by country'!$I$2:$I1023 > 0) * ('Shipments by country'!$B$2:$B1023 = $A7) ) ), 0 )"),67804.1096191503) -> 67804.11 | V7: =SUMIF('Shipments by country'!$B:$B,$A7,'Shipments by country'!$K:$K) -> 2559.4899 | W7: =IFERROR(__xludf.DUMMYFUNCTION("IFERROR( SUM( FILTER( 'Shipments by country'!$H$2:$H1023 * ( INDEX(Countries!$T$2:$T1023, MATCH('Shipments by country'!$B$2:$B1023, Countries!$A$2:$A1023, 0) ) / 1000000 ) * INDEX('Vaccine efficacy curves'!$C$2:$C1023, MATCH('Shipments by country'!$C$2:$C"&"1023, 'Vaccine efficacy curves'!$A$2:$A1023, 0) ), ('Shipments by country'!$E$2:$E1023 < NOW()) * ('Shipments by country'!$I$2:$I1023 > 0) * ('Shipments by country'!$B$2:$B1023 = $A7) ) ), 0 )"),134.50269141852158) -> 134.50269 | X7: =SUMIF('Shipments by country'!$B:$B,$A7,'Shipments by country'!$L:$L) -> 57094.857 | Y7: =IFERROR(__xludf.DUMMYFUNCTION("IFERROR( SUM( FILTER( 'Shipments by country'!$H$2:$H1023 * ( INDEX(Countries!$S$2:$S1023, MATCH('Shipments by country'!$B$2:$B1023, Countries!$A$2:$A1023, 0) ) / 1000000 ) * INDEX('Vaccine efficacy curves'!$C$2:$C1023, MATCH('Shipments by country'!$C$2:$C"&"1023, 'Vaccine efficacy curves'!$A$2:$A1023, 0) ), ('Shipments by country'!$E$2:$E1023 < NOW()) * ('Shipments by country'!$I$2:$I1023 > 0.25) * ('Shipments by country'!$B$2:$B1023 = $A7) ) ), 0 )"),67804.1096191503) -> 67804.11 | Z7: =SUMIF('Shipments by country'!$B:$B,$A7,'Shipments by country'!$M:$M) -> 2003.1334 | AA7: =IFERROR(__xludf.DUMMYFUNCTION("IFERROR( SUM( FILTER( 'Shipments by country'!$H$2:$H1023 * ( INDEX(Countries!$T$2:$T1023, MATCH('Shipments by country'!$B$2:$B1023, Countries!$A$2:$A1023, 0) ) / 1000000 ) * INDEX('Vaccine efficacy curves'!$C$2:$C1023, MATCH('Shipments by country'!$C$2:$C"&"1023, 'Vaccine efficacy curves'!$A$2:$A1023, 0) ), ('Shipments by country'!$E$2:$E1023 < NOW()) * ('Shipments by country'!$I$2:$I1023 > 0.25) * ('Shipments by country'!$B$2:$B1023 = $A7) ) ), 0 )"),134.50269141852158) -> 134.50269 | AB7: =SUMIF('Shipments by country'!$B:$B,$A7,'Shipments by country'!$N:$N) -> 44684.143 | AC7: =IFERROR(__xludf.DUMMYFUNCTION("IFERROR( SUM( FILTER( 'Shipments by country'!$H$2:$H1023 * ( INDEX(Countries!$S$2:$S1023, MATCH('Shipments by country'!$B$2:$B1023, Countries!$A$2:$A1023, 0) ) / 1000000 ) * 'Shipments by country'!$J$2:$J1023, ('Shipments by country'!$E$2:$E1023 < NOW()) "&"* ('Shipments by country'!$I$2:$I1023 > 0) * ('Shipments by country'!$B$2:$B1023 = $A7) ) ), 0 )"),64537.07067391035) -> 64537.071 | AD7: =SUMIF('Shipments by country'!$B:$B,$A7,'Shipments by country'!$O:$O) -> 2470.1325 | AE7: =IFERROR(__xludf.DUMMYFUNCTION("IFERROR( SUM( FILTER( 'Shipments by country'!$H$2:$H1023 * ( INDEX(Countries!$T$2:$T1023, MATCH('Shipments by country'!$B$2:$B1023, Countries!$A$2:$A1023, 0) ) / 1000000 ) * 'Shipments by country'!$J$2:$J1023, ('Shipments by country'!$E$2:$E1023 < NOW()) "&"* ('Shipments by country'!$I$2:$I1023 > 0) * ('Shipments by country'!$B$2:$B1023 = $A7) ) ), 0 )"),128.02188172170358) -> 128.02188 | AF7: =SUMIF('Shipments by country'!$B:$B,$A7,'Shipments by country'!$P:$P) -> 55101.551 | AG7: =IFERROR(__xludf.DUMMYFUNCTION("IFERROR( SUM( FILTER( 'Shipments by country'!$H$2:$H1023 * INDEX(Countries!$S$2:$S1023, MATCH('Shipments by country'!$B$2:$B1023, Countries!$A$2:$A1023, 0) ) / 1000000 "&" * 'Shipments by country'!$J$2:$J1023, ( 'Shipments by country'!$E$2:$E1023 < NOW() ) * ( 'Shipments by country'!$I$2:$I1023 > 0.25 ) * ( 'Shipments by country'!$"&"B$2:$B1023 = $A7 ) ) ), 0 ) "),64537.07067391035) -> 64537.071 | AH7: =SUMIF('Shipments by country'!$B:$B,$A7,'Shipments by country'!$Q:$Q) -> 11782.006 | AI7: =IFERROR(__xludf.DUMMYFUNCTION("IFERROR( SUM( FILTER( 'Shipments by country'!$H$2:$H1023 * ( INDEX(Countries!$T$2:$T1023, MATCH('Shipments by country'!$B$2:$B1023, Countries!$A$2:$A1023, 0) ) / 1000000 ) * 'Shipments by country"&"'!$J$2:$J1023, ('Shipments by country'!$E$2:$E1023 < NOW()) * ('Shipments by country'!$I$2:$I1023 > 0.25) * ('Shipments by country'!$B$2:$B1023 = $A7) ) ), 0 ) "),128.02188172170358) -> 128.02188 | AJ7: =SUMIF('Shipments by country'!$B:$B,$A7,'Shipments by country'!$R:$R) -> 18.615521 | AK7: =O7*4 -> 14427264 | AL7: =AK7*'Vaccine pricing'!B3 -> 43137518 | AM7: =IF($A7="","", LET( ctry,$A7, ctryCol,'Shipments by country'!$B$2:$B1023, vaccCol,'Shipments by country'!$C$2:$C1023, finCol,'Shipments by country'!$D$2:$D1023, doseCol,'Shipments by country'!$F$2:$F1023, price,IFERROR(VLOOKUP(vaccCol,'Vaccine pricing'!$A$2:$B1023,2,FALSE),0), totCost,SUMPRODUCT((ctryCol=ctry)*doseCol*price), gaviCost,SUMPRODUCT((ctryCol=ctry)*(finCol="Gavi")*doseCol*price), IF(totCost=0,"",gaviCost/totCost) )) -> 0.97708769 | AN7: 11 | AO7: 11673266 | AP7: 1633 | AQ7: ='Vaccine pricing'!$B$3*4/((S7/1000000)*'Vaccine efficacy curves'!$C$3) -> 61.615998 | AR7: ='Vaccine pricing'!$B$3*4/((T7/1000000)*'Vaccine efficacy curves'!$C$3) -> 38997.568 | AS7: =K7/5 -> 878620.2 | AT7: =AS7*4 -> 3514480.8 | AU7: =AT7*'Vaccine pricing'!B3 -> 10508298 | AV7: =K7*31/60 -> 2269768.9 | AW7: =M7/AV7 -> 0.15286799 | AX7: =AV7-M7 -> 1922793.9 | AY7: =1-AW7 -> 0.84713201 | AZ7: =AX7*4 -> 7691175.4 | BA7: =AZ7*'Vaccine pricing'!B3 -> 22996614 | BB7: 6223018.8
A8: Central African Republic | B8: =SUMIFS('Shipments by country'!F:F, 'Shipments by country'!B:B, A8, 'Shipments by country'!C:C, "RTS,S", 'Shipments by country'!G:G, "Delivered") -> 0 | C8: =SUMIFS('Shipments by country'!F:F, 'Shipments by country'!B:B, A8, 'Shipments by country'!C:C, "R21", 'Shipments by country'!G:G, "Delivered") -> 430400 | D8: =B8+C8 -> 430400 | E8: =SUMIFS('Shipments by country'!F:F, 'Shipments by country'!B:B, A8, 'Shipments by country'!C:C, "RTS,S") -> 0 | F8: =SUMIFS('Shipments by country'!F:F, 'Shipments by country'!B:B, A8, 'Shipments by country'!C:C, "R21") -> 452200 | G8: =E8+F8 -> 452200 | H8: Initial self-financing | I8: 0 | J8: 5152420 | K8: 940906 | L8: =K8*0.9 -> 846815.4 | M8: =G8/4 -> 113050 | N8: =M8/L8 -> 0.13350017 | O8: =L8-M8 -> 733765.4 | P8: =1-N8 -> 0.86649983 | Q8: 1574284 | R8: 5052 | S8: =Q8*1000000/J8 -> 305542.64 | T8: =R8*1000000/J8 -> 980.51013 | U8: =IFERROR(__xludf.DUMMYFUNCTION("IFERROR( SUM( FILTER( 'Shipments by country'!$H$2:$H1023 * ( INDEX(Countries!$S$2:$S1023, MATCH('Shipments by country'!$B$2:$B1023, Countries!$A$2:$A1023, 0) ) / 1000000 ) * INDEX('Vaccine efficacy curves'!$C$2:$C1023, MATCH('Shipments by country'!$C$2:$C"&"1023, 'Vaccine efficacy curves'!$A$2:$A1023, 0) ), ('Shipments by country'!$E$2:$E1023 < NOW()) * ('Shipments by country'!$I$2:$I1023 > 0) * ('Shipments by country'!$B$2:$B1023 = $A8) ) ), 0 )"),21299.823939918464) -> 21299.824 | V8: =SUMIF('Shipments by country'!$B:$B,$A8,'Shipments by country'!$K:$K) -> 354.63856 | W8: =IFERROR(__xludf.DUMMYFUNCTION("IFERROR( SUM( FILTER( 'Shipments by country'!$H$2:$H1023 * ( INDEX(Countries!$T$2:$T1023, MATCH('Shipments by country'!$B$2:$B1023, Countries!$A$2:$A1023, 0) ) / 1000000 ) * INDEX('Vaccine efficacy curves'!$C$2:$C1023, MATCH('Shipments by country'!$C$2:$C"&"1023, 'Vaccine efficacy curves'!$A$2:$A1023, 0) ), ('Shipments by country'!$E$2:$E1023 < NOW()) * ('Shipments by country'!$I$2:$I1023 > 0) * ('Shipments by country'!$B$2:$B1023 = $A8) ) ), 0 )"),42.252359963894385) -> 42.25236 | X8: =SUMIF('Shipments by country'!$B:$B,$A8,'Shipments by country'!$L:$L) -> 21448.377 | Y8: =IFERROR(__xludf.DUMMYFUNCTION("IFERROR( SUM( FILTER( 'Shipments by country'!$H$2:$H1023 * ( INDEX(Countries!$S$2:$S1023, MATCH('Shipments by country'!$B$2:$B1023, Countries!$A$2:$A1023, 0) ) / 1000000 ) * INDEX('Vaccine efficacy curves'!$C$2:$C1023, MATCH('Shipments by country'!$C$2:$C"&"1023, 'Vaccine efficacy curves'!$A$2:$A1023, 0) ), ('Shipments by country'!$E$2:$E1023 < NOW()) * ('Shipments by country'!$I$2:$I1023 > 0.25) * ('Shipments by country'!$B$2:$B1023 = $A8) ) ), 0 )"),21299.823939918464) -> 21299.824 | Z8: =SUMIF('Shipments by country'!$B:$B,$A8,'Shipments by country'!$M:$M) -> 252.71446 | AA8: =IFERROR(__xludf.DUMMYFUNCTION("IFERROR( SUM( FILTER( 'Shipments by country'!$H$2:$H1023 * ( INDEX(Countries!$T$2:$T1023, MATCH('Shipments by country'!$B$2:$B1023, Countries!$A$2:$A1023, 0) ) / 1000000 ) * INDEX('Vaccine efficacy curves'!$C$2:$C1023, MATCH('Shipments by country'!$C$2:$C"&"1023, 'Vaccine efficacy curves'!$A$2:$A1023, 0) ), ('Shipments by country'!$E$2:$E1023 < NOW()) * ('Shipments by country'!$I$2:$I1023 > 0.25) * ('Shipments by country'!$B$2:$B1023 = $A8) ) ), 0 )"),42.252359963894385) -> 42.25236 | AB8: =SUMIF('Shipments by country'!$B:$B,$A8,'Shipments by country'!$N:$N) -> 15284.055 | AC8: =IFERROR(__xludf.DUMMYFUNCTION("IFERROR( SUM( FILTER( 'Shipments by country'!$H$2:$H1023 * ( INDEX(Countries!$S$2:$S1023, MATCH('Shipments by country'!$B$2:$B1023, Countries!$A$2:$A1023, 0) ) / 1000000 ) * 'Shipments by country'!$J$2:$J1023, ('Shipments by country'!$E$2:$E1023 < NOW()) "&"* ('Shipments by country'!$I$2:$I1023 > 0) * ('Shipments by country'!$B$2:$B1023 = $A8) ) ), 0 )"),27860.751378014094) -> 27860.751 | AD8: =SUMIF('Shipments by country'!$B:$B,$A8,'Shipments by country'!$O:$O) -> 346.709 | AE8: =IFERROR(__xludf.DUMMYFUNCTION("IFERROR( SUM( FILTER( 'Shipments by country'!$H$2:$H1023 * ( INDEX(Countries!$T$2:$T1023, MATCH('Shipments by country'!$B$2:$B1023, Countries!$A$2:$A1023, 0) ) / 1000000 ) * 'Shipments by country'!$J$2:$J1023, ('Shipments by country'!$E$2:$E1023 < NOW()) "&"* ('Shipments by country'!$I$2:$I1023 > 0) * ('Shipments by country'!$B$2:$B1023 = $A8) ) ), 0 )"),55.26724067809006) -> 55.267241 | AF8: =SUMIF('Shipments by country'!$B:$B,$A8,'Shipments by country'!$P:$P) -> 20968.801 | AG8: =IFERROR(__xludf.DUMMYFUNCTION("IFERROR( SUM( FILTER( 'Shipments by country'!$H$2:$H1023 * INDEX(Countries!$S$2:$S1023, MATCH('Shipments by country'!$B$2:$B1023, Countries!$A$2:$A1023, 0) ) / 1000000 "&" * 'Shipments by country'!$J$2:$J1023, ( 'Shipments by country'!$E$2:$E1023 < NOW() ) * ( 'Shipments by country'!$I$2:$I1023 > 0.25 ) * ( 'Shipments by country'!$"&"B$2:$B1023 = $A8 ) ) ), 0 ) "),27860.751378014094) -> 27860.751 | AH8: =SUMIF('Shipments by country'!$B:$B,$A8,'Shipments by country'!$Q:$Q) -> 5912.9662 | AI8: =IFERROR(__xludf.DUMMYFUNCTION("IFERROR( SUM( FILTER( 'Shipments by country'!$H$2:$H1023 * ( INDEX(Countries!$T$2:$T1023, MATCH('Shipments by country'!$B$2:$B1023, Countries!$A$2:$A1023, 0) ) / 1000000 ) * 'Shipments by country"&"'!$J$2:$J1023, ('Shipments by country'!$E$2:$E1023 < NOW()) * ('Shipments by country'!$I$2:$I1023 > 0.25) * ('Shipments by country'!$B$2:$B1023 = $A8) ) ), 0 ) "),55.26724067809006) -> 55.267241 | AJ8: =SUMIF('Shipments by country'!$B:$B,$A8,'Shipments by country'!$R:$R) -> 18.975169 | AK8: =O8*4 -> 2935061.6 | AL8: =AK8*'Vaccine pricing'!B3 -> 8775834.2 | AM8: =IF($A8="","", LET( ctry,$A8, ctryCol,'Shipments by country'!$B$2:$B1023, vaccCol,'Shipments by country'!$C$2:$C1023, finCol,'Shipments by country'!$D$2:$D1023, doseCol,'Shipments by country'!$F$2:$F1023, price,IFERROR(VLOOKUP(vaccCol,'Vaccine pricing'!$A$2:$B1023,2,FALSE),0), totCost,SUMPRODUCT((ctryCol=ctry)*doseCol*price), gaviCost,SUMPRODUCT((ctryCol=ctry)*(finCol="Gavi")*doseCol*price), IF(totCost=0,"",gaviCost/totCost) )) -> 0.95179124 | AN8: 11 | AO8: 587012.32 | AP8: 493 | AQ8: ='Vaccine pricing'!$B$3*4/((S8/1000000)*'Vaccine efficacy curves'!$C$3) -> 52.191297 | AR8: ='Vaccine pricing'!$B$3*4/((T8/1000000)*'Vaccine efficacy curves'!$C$3) -> 16263.643 | AS8: =K8/5 -> 188181.2 | AT8: =AS8*4 -> 752724.8 | AU8: =AT8*'Vaccine pricing'!B3 -> 2250647.2 | AV8: =K8*31/60 -> 486134.77 | AW8: =M8/AV8 -> 0.23254868 | AX8: =AV8-M8 -> 373084.77 | AY8: =1-AW8 -> 0.76745132 | AZ8: =AX8*4 -> 1492339.1 | BA8: =AZ8*'Vaccine pricing'!B3 -> 4462093.8 | BB8: 298467.81
A9: Chad | B9: =SUMIFS('Shipments by country'!F:F, 'Shipments by country'!B:B, A9, 'Shipments by country'!C:C, "RTS,S", 'Shipments by country'!G:G, "Delivered") -> 0 | C9: =SUMIFS('Shipments by country'!F:F, 'Shipments by country'!B:B, A9, 'Shipments by country'!C:C, "R21", 'Shipments by country'!G:G, "Delivered") -> 553500 | D9: =B9+C9 -> 553500 | E9: =SUMIFS('Shipments by country'!F:F, 'Shipments by country'!B:B, A9, 'Shipments by country'!C:C, "RTS,S") -> 0 | F9: =SUMIFS('Shipments by country'!F:F, 'Shipments by country'!B:B, A9, 'Shipments by country'!C:C, "R21") -> 553500 | G9: =E9+F9 -> 553500 | H9: Initial self-financing | I9: 0 | J9: 19319064 | K9: 3546917 | L9: =K9*0.9 -> 3192225.3 | M9: =G9/4 -> 138375 | N9: =M9/L9 -> 0.043347504 | O9: =L9-M9 -> 3053850.3 | P9: =1-N9 -> 0.9566525 | Q9: 3946418 | R9: 13707 | S9: =Q9*1000000/J9 -> 204275.84 | T9: =R9*1000000/J9 -> 709.50642 | U9: =IFERROR(__xludf.DUMMYFUNCTION("IFERROR( SUM( FILTER( 'Shipments by country'!$H$2:$H1023 * ( INDEX(Countries!$S$2:$S1023, MATCH('Shipments by country'!$B$2:$B1023, Countries!$A$2:$A1023, 0) ) / 1000000 ) * INDEX('Vaccine efficacy curves'!$C$2:$C1023, MATCH('Shipments by country'!$C$2:$C"&"1023, 'Vaccine efficacy curves'!$A$2:$A1023, 0) ), ('Shipments by country'!$E$2:$E1023 < NOW()) * ('Shipments by country'!$I$2:$I1023 > 0) * ('Shipments by country'!$B$2:$B1023 = $A9) ) ), 0 )"),27391.850721990868) -> 27391.851 | V9: =SUMIF('Shipments by country'!$B:$B,$A9,'Shipments by country'!$K:$K) -> 1384.1015 | W9: =IFERROR(__xludf.DUMMYFUNCTION("IFERROR( SUM( FILTER( 'Shipments by country'!$H$2:$H1023 * ( INDEX(Countries!$T$2:$T1023, MATCH('Shipments by country'!$B$2:$B1023, Countries!$A$2:$A1023, 0) ) / 1000000 ) * INDEX('Vaccine efficacy curves'!$C$2:$C1023, MATCH('Shipments by country'!$C$2:$C"&"1023, 'Vaccine efficacy curves'!$A$2:$A1023, 0) ), ('Shipments by country'!$E$2:$E1023 < NOW()) * ('Shipments by country'!$I$2:$I1023 > 0) * ('Shipments by country'!$B$2:$B1023 = $A9) ) ), 0 )"),54.33708466546362) -> 54.337085 | X9: =SUMIF('Shipments by country'!$B:$B,$A9,'Shipments by country'!$L:$L) -> 20627.306 | Y9: =IFERROR(__xludf.DUMMYFUNCTION("IFERROR( SUM( FILTER( 'Shipments by country'!$H$2:$H1023 * ( INDEX(Countries!$S$2:$S1023, MATCH('Shipments by country'!$B$2:$B1023, Countries!$A$2:$A1023, 0) ) / 1000000 ) * INDEX('Vaccine efficacy curves'!$C$2:$C1023, MATCH('Shipments by country'!$C$2:$C"&"1023, 'Vaccine efficacy curves'!$A$2:$A1023, 0) ), ('Shipments by country'!$E$2:$E1023 < NOW()) * ('Shipments by country'!$I$2:$I1023 > 0.25) * ('Shipments by country'!$B$2:$B1023 = $A9) ) ), 0 )"),27391.850721990868) -> 27391.851 | Z9: =SUMIF('Shipments by country'!$B:$B,$A9,'Shipments by country'!$M:$M) -> 1028.4691 | AA9: =IFERROR(__xludf.DUMMYFUNCTION("IFERROR( SUM( FILTER( 'Shipments by country'!$H$2:$H1023 * ( INDEX(Countries!$T$2:$T1023, MATCH('Shipments by country'!$B$2:$B1023, Countries!$A$2:$A1023, 0) ) / 1000000 ) * INDEX('Vaccine efficacy curves'!$C$2:$C1023, MATCH('Shipments by country'!$C$2:$C"&"1023, 'Vaccine efficacy curves'!$A$2:$A1023, 0) ), ('Shipments by country'!$E$2:$E1023 < NOW()) * ('Shipments by country'!$I$2:$I1023 > 0.25) * ('Shipments by country'!$B$2:$B1023 = $A9) ) ), 0 )"),54.33708466546362) -> 54.337085 | AB9: =SUMIF('Shipments by country'!$B:$B,$A9,'Shipments by country'!$N:$N) -> 15327.306 | AC9: =IFERROR(__xludf.DUMMYFUNCTION("IFERROR( SUM( FILTER( 'Shipments by country'!$H$2:$H1023 * ( INDEX(Countries!$S$2:$S1023, MATCH('Shipments by country'!$B$2:$B1023, Countries!$A$2:$A1023, 0) ) / 1000000 ) * 'Shipments by country'!$J$2:$J1023, ('Shipments by country'!$E$2:$E1023 < NOW()) "&"* ('Shipments by country'!$I$2:$I1023 > 0) * ('Shipments by country'!$B$2:$B1023 = $A9) ) ), 0 )"),36161.49383898846) -> 36161.494 | AD9: =SUMIF('Shipments by country'!$B:$B,$A9,'Shipments by country'!$O:$O) -> 1367.1685 | AE9: =IFERROR(__xludf.DUMMYFUNCTION("IFERROR( SUM( FILTER( 'Shipments by country'!$H$2:$H1023 * ( INDEX(Countries!$T$2:$T1023, MATCH('Shipments by country'!$B$2:$B1023, Countries!$A$2:$A1023, 0) ) / 1000000 ) * 'Shipments by country'!$J$2:$J1023, ('Shipments by country'!$E$2:$E1023 < NOW()) "&"* ('Shipments by country'!$I$2:$I1023 > 0) * ('Shipments by country'!$B$2:$B1023 = $A9) ) ), 0 )"),71.73338422077767) -> 71.733384 | AF9: =SUMIF('Shipments by country'!$B:$B,$A9,'Shipments by country'!$P:$P) -> 20374.953 | AG9: =IFERROR(__xludf.DUMMYFUNCTION("IFERROR( SUM( FILTER( 'Shipments by country'!$H$2:$H1023 * INDEX(Countries!$S$2:$S1023, MATCH('Shipments by country'!$B$2:$B1023, Countries!$A$2:$A1023, 0) ) / 1000000 "&" * 'Shipments by country'!$J$2:$J1023, ( 'Shipments by country'!$E$2:$E1023 < NOW() ) * ( 'Shipments by country'!$I$2:$I1023 > 0.25 ) * ( 'Shipments by country'!$"&"B$2:$B1023 = $A9 ) ) ), 0 ) "),36161.49383898846) -> 36161.494 | AH9: =SUMIF('Shipments by country'!$B:$B,$A9,'Shipments by country'!$Q:$Q) -> 5136.1873 | AI9: =IFERROR(__xludf.DUMMYFUNCTION("IFERROR( SUM( FILTER( 'Shipments by country'!$H$2:$H1023 * ( INDEX(Countries!$T$2:$T1023, MATCH('Shipments by country'!$B$2:$B1023, Countries!$A$2:$A1023, 0) ) / 1000000 ) * 'Shipments by country"&"'!$J$2:$J1023, ('Shipments by country'!$E$2:$E1023 < NOW()) * ('Shipments by country'!$I$2:$I1023 > 0.25) * ('Shipments by country'!$B$2:$B1023 = $A9) ) ), 0 ) "),71.73338422077767) -> 71.733384 | AJ9: =SUMIF('Shipments by country'!$B:$B,$A9,'Shipments by country'!$R:$R) -> 17.839397 | AK9: =O9*4 -> 12215401 | AL9: =AK9*'Vaccine pricing'!B3 -> 36524050 | AM9: =IF($A9="","", LET( ctry,$A9, ctryCol,'Shipments by country'!$B$2:$B1023, vaccCol,'Shipments by country'!$C$2:$C1023, finCol,'Shipments by country'!$D$2:$D1023, doseCol,'Shipments by country'!$F$2:$F1023, price,IFERROR(VLOOKUP(vaccCol,'Vaccine pricing'!$A$2:$B1023,2,FALSE),0), totCost,SUMPRODUCT((ctryCol=ctry)*doseCol*price), gaviCost,SUMPRODUCT((ctryCol=ctry)*(finCol="Gavi")*doseCol*price), IF(totCost=0,"",gaviCost/totCost) )) -> 0.95212285 | AN9: 11 | AO9: 2443080.2 | AP9: 683 | AQ9: ='Vaccine pricing'!$B$3*4/((S9/1000000)*'Vaccine efficacy curves'!$C$3) -> 78.06438 | AR9: ='Vaccine pricing'!$B$3*4/((T9/1000000)*'Vaccine efficacy curves'!$C$3) -> 22475.719 | AS9: =K9/5 -> 709383.4 | AT9: =AS9*4 -> 2837533.6 | AU9: =AT9*'Vaccine pricing'!B3 -> 8484225.5 | AV9: =K9*31/60 -> 1832573.8 | AW9: =M9/AV9 -> 0.075508556 | AX9: =AV9-M9 -> 1694198.8 | AY9: =1-AW9 -> 0.92449144 | AZ9: =AX9*4 -> 6776795.1 | BA9: =AZ9*'Vaccine pricing'!B3 -> 20262617 | BB9: 1355359
A10: Comoros | B10: =SUMIFS('Shipments by country'!F:F, 'Shipments by country'!B:B, A10, 'Shipments by country'!C:C, "RTS,S", 'Shipments by country'!G:G, "Delivered") -> 0 | C10: =SUMIFS('Shipments by country'!F:F, 'Shipments by country'!B:B, A10, 'Shipments by country'!C:C, "R21", 'Shipments by country'!G:G, "Delivered") -> 0 | D10: =B10+C10 -> 0 | E10: =SUMIFS('Shipments by country'!F:F, 'Shipments by country'!B:B, A10, 'Shipments by country'!C:C, "RTS,S") -> 0 | F10: =SUMIFS('Shipments by country'!F:F, 'Shipments by country'!B:B, A10, 'Shipments by country'!C:C, "R21") -> 0 | G10: =E10+F10 -> 0 | H10: Preparatory transition | I10: 0 | J10: 850387 | K10: 114145 | L10: =K10*0.9 -> 102730.5 | M10: =G10/4 -> 0 | N10: =M10/L10 -> 0 | O10: =L10-M10 -> 102730.5 | P10: =1-N10 -> 1 | Q10: 21049 | R10: 53 | S10: =Q10*1000000/J10 -> 24752.26 | T10: =R10*1000000/J10 -> 62.324565 | U10: =IFERROR(__xludf.DUMMYFUNCTION("IFERROR( SUM( FILTER( 'Shipments by country'!$H$2:$H1023 * ( INDEX(Countries!$S$2:$S1023, MATCH('Shipments by country'!$B$2:$B1023, Countries!$A$2:$A1023, 0) ) / 1000000 ) * INDEX('Vaccine efficacy curves'!$C$2:$C1023, MATCH('Shipments by country'!$C$2:$C"&"1023, 'Vaccine efficacy curves'!$A$2:$A1023, 0) ), ('Shipments by country'!$E$2:$E1023 < NOW()) * ('Shipments by country'!$I$2:$I1023 > 0) * ('Shipments by country'!$B$2:$B1023 = $A10) ) ), 0 )"),0.0) -> 0 | V10: =SUMIF('Shipments by country'!$B:$B,$A10,'Shipments by country'!$K:$K) -> 0 | W10: =IFERROR(__xludf.DUMMYFUNCTION("IFERROR( SUM( FILTER( 'Shipments by country'!$H$2:$H1023 * ( INDEX(Countries!$T$2:$T1023, MATCH('Shipments by country'!$B$2:$B1023, Countries!$A$2:$A1023, 0) ) / 1000000 ) * INDEX('Vaccine efficacy curves'!$C$2:$C1023, MATCH('Shipments by country'!$C$2:$C"&"1023, 'Vaccine efficacy curves'!$A$2:$A1023, 0) ), ('Shipments by country'!$E$2:$E1023 < NOW()) * ('Shipments by country'!$I$2:$I1023 > 0) * ('Shipments by country'!$B$2:$B1023 = $A10) ) ), 0 )"),0.0) -> 0 | X10: =SUMIF('Shipments by country'!$B:$B,$A10,'Shipments by country'!$L:$L) -> 0 | Y10: =IFERROR(__xludf.DUMMYFUNCTION("IFERROR( SUM( FILTER( 'Shipments by country'!$H$2:$H1023 * ( INDEX(Countries!$S$2:$S1023, MATCH('Shipments by country'!$B$2:$B1023, Countries!$A$2:$A1023, 0) ) / 1000000 ) * INDEX('Vaccine efficacy curves'!$C$2:$C1023, MATCH('Shipments by country'!$C$2:$C"&"1023, 'Vaccine efficacy curves'!$A$2:$A1023, 0) ), ('Shipments by country'!$E$2:$E1023 < NOW()) * ('Shipments by country'!$I$2:$I1023 > 0.25) * ('Shipments by country'!$B$2:$B1023 = $A10) ) ), 0 )"),0.0) -> 0 | Z10: =SUMIF('Shipments by country'!$B:$B,$A10,'Shipments by country'!$M:$M) -> 0 | AA10: =IFERROR(__xludf.DUMMYFUNCTION("IFERROR( SUM( FILTER( 'Shipments by country'!$H$2:$H1023 * ( INDEX(Countries!$T$2:$T1023, MATCH('Shipments by country'!$B$2:$B1023, Countries!$A$2:$A1023, 0) ) / 1000000 ) * INDEX('Vaccine efficacy curves'!$C$2:$C1023, MATCH('Shipments by country'!$C$2:$C"&"1023, 'Vaccine efficacy curves'!$A$2:$A1023, 0) ), ('Shipments by country'!$E$2:$E1023 < NOW()) * ('Shipments by country'!$I$2:$I1023 > 0.25) * ('Shipments by country'!$B$2:$B1023 = $A10) ) ), 0 )"),0.0) -> 0 | AB10: =SUMIF('Shipments by country'!$B:$B,$A10,'Shipments by country'!$N:$N) -> 0 | AC10: =IFERROR(__xludf.DUMMYFUNCTION("IFERROR( SUM( FILTER( 'Shipments by country'!$H$2:$H1023 * ( INDEX(Countries!$S$2:$S1023, MATCH('Shipments by country'!$B$2:$B1023, Countries!$A$2:$A1023, 0) ) / 1000000 ) * 'Shipments by country'!$J$2:$J1023, ('Shipments by country'!$E$2:$E1023 < NOW()) "&"* ('Shipments by country'!$I$2:$I1023 > 0) * ('Shipments by country'!$B$2:$B1023 = $A10) ) ), 0 )"),0.0) -> 0 | AD10: =SUMIF('Shipments by country'!$B:$B,$A10,'Shipments by country'!$O:$O) -> 0 | AE10: =IFERROR(__xludf.DUMMYFUNCTION("IFERROR( SUM( FILTER( 'Shipments by country'!$H$2:$H1023 * ( INDEX(Countries!$T$2:$T1023, MATCH('Shipments by country'!$B$2:$B1023, Countries!$A$2:$A1023, 0) ) / 1000000 ) * 'Shipments by country'!$J$2:$J1023, ('Shipments by country'!$E$2:$E1023 < NOW()) "&"* ('Shipments by country'!$I$2:$I1023 > 0) * ('Shipments by country'!$B$2:$B1023 = $A10) ) ), 0 )"),0.0) -> 0 | AF10: =SUMIF('Shipments by country'!$B:$B,$A10,'Shipments by country'!$P:$P) -> 0 | AG10: =IFERROR(__xludf.DUMMYFUNCTION("IFERROR( SUM( FILTER( 'Shipments by country'!$H$2:$H1023 * INDEX(Countries!$S$2:$S1023, MATCH('Shipments by country'!$B$2:$B1023, Countries!$A$2:$A1023, 0) ) / 1000000 "&" * 'Shipments by country'!$J$2:$J1023, ( 'Shipments by country'!$E$2:$E1023 < NOW() ) * ( 'Shipments by country'!$I$2:$I1023 > 0.25 ) * ( 'Shipments by country'!$"&"B$2:$B1023 = $A10 ) ) ), 0 ) "),0.0) -> 0 | AH10: =SUMIF('Shipments by country'!$B:$B,$A10,'Shipments by country'!$Q:$Q) -> 0 | AI10: =IFERROR(__xludf.DUMMYFUNCTION("IFERROR( SUM( FILTER( 'Shipments by country'!$H$2:$H1023 * ( INDEX(Countries!$T$2:$T1023, MATCH('Shipments by country'!$B$2:$B1023, Countries!$A$2:$A1023, 0) ) / 1000000 ) * 'Shipments by country"&"'!$J$2:$J1023, ('Shipments by country'!$E$2:$E1023 < NOW()) * ('Shipments by country'!$I$2:$I1023 > 0.25) * ('Shipments by country'!$B$2:$B1023 = $A10) ) ), 0 ) "),0.0) -> 0 | AJ10: =SUMIF('Shipments by country'!$B:$B,$A10,'Shipments by country'!$R:$R) -> 0 | AK10: =O10*4 -> 410922 | AL10: =AK10*'Vaccine pricing'!B3 -> 1228656.8 | AM10: =IF($A10="","", LET( ctry,$A10, ctryCol,'Shipments by country'!$B$2:$B1023, vaccCol,'Shipments by country'!$C$2:$C1023, finCol,'Shipments by country'!$D$2:$D1023, doseCol,'Shipments by country'!$F$2:$F1023, price,IFERROR(VLOOKUP(vaccCol,'Vaccine pricing'!$A$2:$B1023,2,FALSE),0), totCost,SUMPRODUCT((ctryCol=ctry)*doseCol*price), gaviCost,SUMPRODUCT((ctryCol=ctry)*(finCol="Gavi")*doseCol*price), IF(totCost=0,"",gaviCost/totCost) )) | AN10: 6 | AO10: 165302.18 | AP10: 1557 | AQ10: ='Vaccine pricing'!$B$3*4/((S10/1000000)*'Vaccine efficacy curves'!$C$3) -> 644.25094 | AR10: ='Vaccine pricing'!$B$3*4/((T10/1000000)*'Vaccine efficacy curves'!$C$3) -> 255864.87 | AS10: =K10/5 -> 22829 | AT10: =AS10*4 -> 91316 | AU10: =AT10*'Vaccine pricing'!B3 -> 273034.84 | AV10: =K10*31/60 -> 58974.917 | AW10: =M10/AV10 -> 0 | AX10: =AV10-M10 -> 58974.917 | AY10: =1-AW10 -> 1 | AZ10: =AX10*4 -> 235899.67 | BA10: =AZ10*'Vaccine pricing'!B3 -> 705340 | BB10: 94895.698
A11: Congo-Brazzaville | B11: =SUMIFS('Shipments by country'!F:F, 'Shipments by country'!B:B, A11, 'Shipments by country'!C:C, "RTS,S", 'Shipments by country'!G:G, "Delivered") -> 0 | C11: =SUMIFS('Shipments by country'!F:F, 'Shipments by country'!B:B, A11, 'Shipments by country'!C:C, "R21", 'Shipments by country'!G:G, "Delivered") -> 0 | D11: =B11+C11 -> 0 | E11: =SUMIFS('Shipments by country'!F:F, 'Shipments by country'!B:B, A11, 'Shipments by country'!C:C, "RTS,S") -> 0 | F11: =SUMIFS('Shipments by country'!F:F, 'Shipments by country'!B:B, A11, 'Shipments by country'!C:C, "R21") -> 0 | G11: =E11+F11 -> 0 | H11: Accelerated transition | I11: 0 | J11: 6182885 | K11: 885681 | L11: =K11*0.9 -> 797112.9 | M11: =G11/4 -> 0 | N11: =M11/L11 -> 0 | O11: =L11-M11 -> 797112.9 | P11: =1-N11 -> 1 | Q11: 1327964 | R11: 2244 | S11: =Q11*1000000/J11 -> 214780.64 | T11: =R11*1000000/J11 -> 362.93737 | U11: =IFERROR(__xludf.DUMMYFUNCTION("IFERROR( SUM( FILTER( 'Shipments by country'!$H$2:$H1023 * ( INDEX(Countries!$S$2:$S1023, MATCH('Shipments by country'!$B$2:$B1023, Countries!$A$2:$A1023, 0) ) / 1000000 ) * INDEX('Vaccine efficacy curves'!$C$2:$C1023, MATCH('Shipments by country'!$C$2:$C"&"1023, 'Vaccine efficacy curves'!$A$2:$A1023, 0) ), ('Shipments by country'!$E$2:$E1023 < NOW()) * ('Shipments by country'!$I$2:$I1023 > 0) * ('Shipments by country'!$B$2:$B1023 = $A11) ) ), 0 )"),0.0) -> 0 | V11: =SUMIF('Shipments by country'!$B:$B,$A11,'Shipments by country'!$K:$K) -> 0 | W11: =IFERROR(__xludf.DUMMYFUNCTION("IFERROR( SUM( FILTER( 'Shipments by country'!$H$2:$H1023 * ( INDEX(Countries!$T$2:$T1023, MATCH('Shipments by country'!$B$2:$B1023, Countries!$A$2:$A1023, 0) ) / 1000000 ) * INDEX('Vaccine efficacy curves'!$C$2:$C1023, MATCH('Shipments by country'!$C$2:$C"&"1023, 'Vaccine efficacy curves'!$A$2:$A1023, 0) ), ('Shipments by country'!$E$2:$E1023 < NOW()) * ('Shipments by country'!$I$2:$I1023 > 0) * ('Shipments by country'!$B$2:$B1023 = $A11) ) ), 0 )"),0.0) -> 0 | X11: =SUMIF('Shipments by country'!$B:$B,$A11,'Shipments by country'!$L:$L) -> 0 | Y11: =IFERROR(__xludf.DUMMYFUNCTION("IFERROR( SUM( FILTER( 'Shipments by country'!$H$2:$H1023 * ( INDEX(Countries!$S$2:$S1023, MATCH('Shipments by country'!$B$2:$B1023, Countries!$A$2:$A1023, 0) ) / 1000000 ) * INDEX('Vaccine efficacy curves'!$C$2:$C1023, MATCH('Shipments by country'!$C$2:$C"&"1023, 'Vaccine efficacy curves'!$A$2:$A1023, 0) ), ('Shipments by country'!$E$2:$E1023 < NOW()) * ('Shipments by country'!$I$2:$I1023 > 0.25) * ('Shipments by country'!$B$2:$B1023 = $A11) ) ), 0 )"),0.0) -> 0 | Z11: =SUMIF('Shipments by country'!$B:$B,$A11,'Shipments by country'!$M:$M) -> 0 | AA11: =IFERROR(__xludf.DUMMYFUNCTION("IFERROR( SUM( FILTER( 'Shipments by country'!$H$2:$H1023 * ( INDEX(Countries!$T$2:$T1023, MATCH('Shipments by country'!$B$2:$B1023, Countries!$A$2:$A1023, 0) ) / 1000000 ) * INDEX('Vaccine efficacy curves'!$C$2:$C1023, MATCH('Shipments by country'!$C$2:$C"&"1023, 'Vaccine efficacy curves'!$A$2:$A1023, 0) ), ('Shipments by country'!$E$2:$E1023 < NOW()) * ('Shipments by country'!$I$2:$I1023 > 0.25) * ('Shipments by country'!$B$2:$B1023 = $A11) ) ), 0 )"),0.0) -> 0 | AB11: =SUMIF('Shipments by country'!$B:$B,$A11,'Shipments by country'!$N:$N) -> 0 | AC11: =IFERROR(__xludf.DUMMYFUNCTION("IFERROR( SUM( FILTER( 'Shipments by country'!$H$2:$H1023 * ( INDEX(Countries!$S$2:$S1023, MATCH('Shipments by country'!$B$2:$B1023, Countries!$A$2:$A1023, 0) ) / 1000000 ) * 'Shipments by country'!$J$2:$J1023, ('Shipments by country'!$E$2:$E1023 < NOW()) "&"* ('Shipments by country'!$I$2:$I1023 > 0) * ('Shipments by country'!$B$2:$B1023 = $A11) ) ), 0 )"),0.0) -> 0 | AD11: =SUMIF('Shipments by country'!$B:$B,$A11,'Shipments by country'!$O:$O) -> 0 | AE11: =IFERROR(__xludf.DUMMYFUNCTION("IFERROR( SUM( FILTER( 'Shipments by country'!$H$2:$H1023 * ( INDEX(Countries!$T$2:$T1023, MATCH('Shipments by country'!$B$2:$B1023, Countries!$A$2:$A1023, 0) ) / 1000000 ) * 'Shipments by country'!$J$2:$J1023, ('Shipments by country'!$E$2:$E1023 < NOW()) "&"* ('Shipments by country'!$I$2:$I1023 > 0) * ('Shipments by country'!$B$2:$B1023 = $A11) ) ), 0 )"),0.0) -> 0 | AF11: =SUMIF('Shipments by country'!$B:$B,$A11,'Shipments by country'!$P:$P) -> 0 | AG11: =IFERROR(__xludf.DUMMYFUNCTION("IFERROR( SUM( FILTER( 'Shipments by country'!$H$2:$H1023 * INDEX(Countries!$S$2:$S1023, MATCH('Shipments by country'!$B$2:$B1023, Countries!$A$2:$A1023, 0) ) / 1000000 "&" * 'Shipments by country'!$J$2:$J1023, ( 'Shipments by country'!$E$2:$E1023 < NOW() ) * ( 'Shipments by country'!$I$2:$I1023 > 0.25 ) * ( 'Shipments by country'!$"&"B$2:$B1023 = $A11 ) ) ), 0 ) "),0.0) -> 0 | AH11: =SUMIF('Shipments by country'!$B:$B,$A11,'Shipments by country'!$Q:$Q) -> 0 | AI11: =IFERROR(__xludf.DUMMYFUNCTION("IFERROR( SUM( FILTER( 'Shipments by country'!$H$2:$H1023 * ( INDEX(Countries!$T$2:$T1023, MATCH('Shipments by country'!$B$2:$B1023, Countries!$A$2:$A1023, 0) ) / 1000000 ) * 'Shipments by country"&"'!$J$2:$J1023, ('Shipments by country'!$E$2:$E1023 < NOW()) * ('Shipments by country'!$I$2:$I1023 > 0.25) * ('Shipments by country'!$B$2:$B1023 = $A11) ) ), 0 ) "),0.0) -> 0 | AJ11: =SUMIF('Shipments by country'!$B:$B,$A11,'Shipments by country'!$R:$R) -> 0 | AK11: =O11*4 -> 3188451.6 | AL11: =AK11*'Vaccine pricing'!B3 -> 9533470.3 | AM11: =IF($A11="","", LET( ctry,$A11, ctryCol,'Shipments by country'!$B$2:$B1023, vaccCol,'Shipments by country'!$C$2:$C1023, finCol,'Shipments by country'!$D$2:$D1023, doseCol,'Shipments by country'!$F$2:$F1023, price,IFERROR(VLOOKUP(vaccCol,'Vaccine pricing'!$A$2:$B1023,2,FALSE),0), totCost,SUMPRODUCT((ctryCol=ctry)*doseCol*price), gaviCost,SUMPRODUCT((ctryCol=ctry)*(finCol="Gavi")*doseCol*price), IF(totCost=0,"",gaviCost/totCost) )) | AN11: 2 | AO11: 2860041.1 | AP11: 2053 | AQ11: ='Vaccine pricing'!$B$3*4/((S11/1000000)*'Vaccine efficacy curves'!$C$3) -> 74.246294 | AR11: ='Vaccine pricing'!$B$3*4/((T11/1000000)*'Vaccine efficacy curves'!$C$3) -> 43937.792 | AS11: =K11/5 -> 177136.2 | AT11: =AS11*4 -> 708544.8 | AU11: =AT11*'Vaccine pricing'!B3 -> 2118549 | AV11: =K11*31/60 -> 457601.85 | AW11: =M11/AV11 -> 0 | AX11: =AV11-M11 -> 457601.85 | AY11: =1-AW11 -> 1 | AZ11: =AX11*4 -> 1830407.4 | BA11: =AZ11*'Vaccine pricing'!B3 -> 5472918.1 | BB11: 1641875.4
A12: Côte d'Ivoire | B12: =SUMIFS('Shipments by country'!F:F, 'Shipments by country'!B:B, A12, 'Shipments by country'!C:C, "RTS,S", 'Shipments by country'!G:G, "Delivered") -> 0 | C12: =SUMIFS('Shipments by country'!F:F, 'Shipments by country'!B:B, A12, 'Shipments by country'!C:C, "R21", 'Shipments by country'!G:G, "Delivered") -> 2263100 | D12: =B12+C12 -> 2263100 | E12: =SUMIFS('Shipments by country'!F:F, 'Shipments by country'!B:B, A12, 'Shipments by country'!C:C, "RTS,S") -> 0 | F12: =SUMIFS('Shipments by country'!F:F, 'Shipments by country'!B:B, A12, 'Shipments by country'!C:C, "R21") -> 2758800 | G12: =E12+F12 -> 2758800 | H12: Accelerated transition | I12: 25000000 | J12: 31165654 | K12: 4593840 | L12: =K12*0.9 -> 4134456 | M12: =G12/4 -> 689700 | N12: =M12/L12 -> 0.16681759 | O12: =L12-M12 -> 3444756 | P12: =1-N12 -> 0.83318241 | Q12: 7835921 | R12: 10771 | S12: =Q12*1000000/J12 -> 251428.09 | T12: =R12*1000000/J12 -> 345.60481 | U12: =IFERROR(__xludf.DUMMYFUNCTION("IFERROR( SUM( FILTER( 'Shipments by country'!$H$2:$H1023 * ( INDEX(Countries!$S$2:$S1023, MATCH('Shipments by country'!$B$2:$B1023, Countries!$A$2:$A1023, 0) ) / 1000000 ) * INDEX('Vaccine efficacy curves'!$C$2:$C1023, MATCH('Shipments by country'!$C$2:$C"&"1023, 'Vaccine efficacy curves'!$A$2:$A1023, 0) ), ('Shipments by country'!$E$2:$E1023 < NOW()) * ('Shipments by country'!$I$2:$I1023 > 0) * ('Shipments by country'!$B$2:$B1023 = $A12) ) ), 0 )"),136528.70419481193) -> 136528.7 | V12: =SUMIF('Shipments by country'!$B:$B,$A12,'Shipments by country'!$K:$K) -> 3432.9809 | W12: =IFERROR(__xludf.DUMMYFUNCTION("IFERROR( SUM( FILTER( 'Shipments by country'!$H$2:$H1023 * ( INDEX(Countries!$T$2:$T1023, MATCH('Shipments by country'!$B$2:$B1023, Countries!$A$2:$A1023, 0) ) / 1000000 ) * INDEX('Vaccine efficacy curves'!$C$2:$C1023, MATCH('Shipments by country'!$C$2:$C"&"1023, 'Vaccine efficacy curves'!$A$2:$A1023, 0) ), ('Shipments by country'!$E$2:$E1023 < NOW()) * ('Shipments by country'!$I$2:$I1023 > 0) * ('Shipments by country'!$B$2:$B1023 = $A12) ) ), 0 )"),270.83134448975795) -> 270.83134 | X12: =SUMIF('Shipments by country'!$B:$B,$A12,'Shipments by country'!$L:$L) -> 80136.278 | Y12: =IFERROR(__xludf.DUMMYFUNCTION("IFERROR( SUM( FILTER( 'Shipments by country'!$H$2:$H1023 * ( INDEX(Countries!$S$2:$S1023, MATCH('Shipments by country'!$B$2:$B1023, Countries!$A$2:$A1023, 0) ) / 1000000 ) * INDEX('Vaccine efficacy curves'!$C$2:$C1023, MATCH('Shipments by country'!$C$2:$C"&"1023, 'Vaccine efficacy curves'!$A$2:$A1023, 0) ), ('Shipments by country'!$E$2:$E1023 < NOW()) * ('Shipments by country'!$I$2:$I1023 > 0.25) * ('Shipments by country'!$B$2:$B1023 = $A12) ) ), 0 )"),111997.28521939933) -> 111997.29 | Z12: =SUMIF('Shipments by country'!$B:$B,$A12,'Shipments by country'!$M:$M) -> 2253.444 | AA12: =IFERROR(__xludf.DUMMYFUNCTION("IFERROR( SUM( FILTER( 'Shipments by country'!$H$2:$H1023 * ( INDEX(Countries!$T$2:$T1023, MATCH('Shipments by country'!$B$2:$B1023, Countries!$A$2:$A1023, 0) ) / 1000000 ) * INDEX('Vaccine efficacy curves'!$C$2:$C1023, MATCH('Shipments by country'!$C$2:$C"&"1023, 'Vaccine efficacy curves'!$A$2:$A1023, 0) ), ('Shipments by country'!$E$2:$E1023 < NOW()) * ('Shipments by country'!$I$2:$I1023 > 0.25) * ('Shipments by country'!$B$2:$B1023 = $A12) ) ), 0 )"),222.16848474509612) -> 222.16848 | AB12: =SUMIF('Shipments by country'!$B:$B,$A12,'Shipments by country'!$N:$N) -> 52602.277 | AC12: =IFERROR(__xludf.DUMMYFUNCTION("IFERROR( SUM( FILTER( 'Shipments by country'!$H$2:$H1023 * ( INDEX(Countries!$S$2:$S1023, MATCH('Shipments by country'!$B$2:$B1023, Countries!$A$2:$A1023, 0) ) / 1000000 ) * 'Shipments by country'!$J$2:$J1023, ('Shipments by country'!$E$2:$E1023 < NOW()) "&"* ('Shipments by country'!$I$2:$I1023 > 0) * ('Shipments by country'!$B$2:$B1023 = $A12) ) ), 0 )"),180422.14853678868) -> 180422.15 | AD12: =SUMIF('Shipments by country'!$B:$B,$A12,'Shipments by country'!$O:$O) -> 3371.3087 | AE12: =IFERROR(__xludf.DUMMYFUNCTION("IFERROR( SUM( FILTER( 'Shipments by country'!$H$2:$H1023 * ( INDEX(Countries!$T$2:$T1023, MATCH('Shipments by country'!$B$2:$B1023, Countries!$A$2:$A1023, 0) ) / 1000000 ) * 'Shipments by country'!$J$2:$J1023, ('Shipments by country'!$E$2:$E1023 < NOW()) "&"* ('Shipments by country'!$I$2:$I1023 > 0) * ('Shipments by country'!$B$2:$B1023 = $A12) ) ), 0 )"),357.9025623375551) -> 357.90256 | AF12: =SUMIF('Shipments by country'!$B:$B,$A12,'Shipments by country'!$P:$P) -> 78696.659 | AG12: =IFERROR(__xludf.DUMMYFUNCTION("IFERROR( SUM( FILTER( 'Shipments by country'!$H$2:$H1023 * INDEX(Countries!$S$2:$S1023, MATCH('Shipments by country'!$B$2:$B1023, Countries!$A$2:$A1023, 0) ) / 1000000 "&" * 'Shipments by country'!$J$2:$J1023, ( 'Shipments by country'!$E$2:$E1023 < NOW() ) * ( 'Shipments by country'!$I$2:$I1023 > 0.25 ) * ( 'Shipments by country'!$"&"B$2:$B1023 = $A12 ) ) ), 0 ) "),147567.5695518611) -> 147567.57 | AH12: =SUMIF('Shipments by country'!$B:$B,$A12,'Shipments by country'!$Q:$Q) -> 26546.854 | AI12: =IFERROR(__xludf.DUMMYFUNCTION("IFERROR( SUM( FILTER( 'Shipments by country'!$H$2:$H1023 * ( INDEX(Countries!$T$2:$T1023, MATCH('Shipments by country'!$B$2:$B1023, Countries!$A$2:$A1023, 0) ) / 1000000 ) * 'Shipments by country"&"'!$J$2:$J1023, ('Shipments by country'!$E$2:$E1023 < NOW()) * ('Shipments by country'!$I$2:$I1023 > 0.25) * ('Shipments by country'!$B$2:$B1023 = $A12) ) ), 0 ) "),292.7290894652401) -> 292.72909 | AJ12: =SUMIF('Shipments by country'!$B:$B,$A12,'Shipments by country'!$R:$R) -> 36.490435 | AK12: =O12*4 -> 13779024 | AL12: =AK12*'Vaccine pricing'!B3 -> 41199282 | AM12: =IF($A12="","", LET( ctry,$A12, ctryCol,'Shipments by country'!$B$2:$B1023, vaccCol,'Shipments by country'!$C$2:$C1023, finCol,'Shipments by country'!$D$2:$D1023, doseCol,'Shipments by country'!$F$2:$F1023, price,IFERROR(VLOOKUP(vaccCol,'Vaccine pricing'!$A$2:$B1023,2,FALSE),0), totCost,SUMPRODUCT((ctryCol=ctry)*doseCol*price), gaviCost,SUMPRODUCT((ctryCol=ctry)*(finCol="Gavi")*doseCol*price), IF(totCost=0,"",gaviCost/totCost) )) -> 0.74735392 | AN12: 4 | AO12: 20599641 | AP12: 2580 | AQ12: ='Vaccine pricing'!$B$3*4/((S12/1000000)*'Vaccine efficacy curves'!$C$3) -> 63.424363 | AR12: ='Vaccine pricing'!$B$3*4/((T12/1000000)*'Vaccine efficacy curves'!$C$3) -> 46141.333 | AS12: =K12/5 -> 918768 | AT12: =AS12*4 -> 3675072 | AU12: =AT12*'Vaccine pricing'!B3 -> 10988465 | AV12: =K12*31/60 -> 2373484 | AW12: =M12/AV12 -> 0.29058549 | AX12: =AV12-M12 -> 1683784 | AY12: =1-AW12 -> 0.70941451 | AZ12: =AX12*4 -> 6735136 | BA12: =AZ12*'Vaccine pricing'!B3 -> 20138057 | BB12: 10069028
A13: Djibouti | B13: =SUMIFS('Shipments by country'!F:F, 'Shipments by country'!B:B, A13, 'Shipments by country'!C:C, "RTS,S", 'Shipments by country'!G:G, "Delivered") -> 0 | C13: =SUMIFS('Shipments by country'!F:F, 'Shipments by country'!B:B, A13, 'Shipments by country'!C:C, "R21", 'Shipments by country'!G:G, "Delivered") -> 0 | D13: =B13+C13 -> 0 | E13: =SUMIFS('Shipments by country'!F:F, 'Shipments by country'!B:B, A13, 'Shipments by country'!C:C, "RTS,S") -> 0 | F13: =SUMIFS('Shipments by country'!F:F, 'Shipments by country'!B:B, A13, 'Shipments by country'!C:C, "R21") -> 0 | G13: =E13+F13 -> 0 | H13: Accelerated transition | I13: 0 | J13: 864614 | K13: 114506 | L13: =K13*0.9 -> 103055.4 | M13: =G13/4 -> 0 | N13: =M13/L13 -> 0 | O13: =L13-M13 -> 103055.4 | P13: =1-N13 -> 1 | Q13: 38944 | R13: 80 | S13: =Q13*1000000/J13 -> 45042.065 | T13: =R13*1000000/J13 -> 92.526839 | U13: =IFERROR(__xludf.DUMMYFUNCTION("IFERROR( SUM( FILTER( 'Shipments by country'!$H$2:$H1023 * ( INDEX(Countries!$S$2:$S1023, MATCH('Shipments by country'!$B$2:$B1023, Countries!$A$2:$A1023, 0) ) / 1000000 ) * INDEX('Vaccine efficacy curves'!$C$2:$C1023, MATCH('Shipments by country'!$C$2:$C"&"1023, 'Vaccine efficacy curves'!$A$2:$A1023, 0) ), ('Shipments by country'!$E$2:$E1023 < NOW()) * ('Shipments by country'!$I$2:$I1023 > 0) * ('Shipments by country'!$B$2:$B1023 = $A13) ) ), 0 )"),0.0) -> 0 | V13: =SUMIF('Shipments by country'!$B:$B,$A13,'Shipments by country'!$K:$K) -> 0 | W13: =IFERROR(__xludf.DUMMYFUNCTION("IFERROR( SUM( FILTER( 'Shipments by country'!$H$2:$H1023 * ( INDEX(Countries!$T$2:$T1023, MATCH('Shipments by country'!$B$2:$B1023, Countries!$A$2:$A1023, 0) ) / 1000000 ) * INDEX('Vaccine efficacy curves'!$C$2:$C1023, MATCH('Shipments by country'!$C$2:$C"&"1023, 'Vaccine efficacy curves'!$A$2:$A1023, 0) ), ('Shipments by country'!$E$2:$E1023 < NOW()) * ('Shipments by country'!$I$2:$I1023 > 0) * ('Shipments by country'!$B$2:$B1023 = $A13) ) ), 0 )"),0.0) -> 0 | X13: =SUMIF('Shipments by country'!$B:$B,$A13,'Shipments by country'!$L:$L) -> 0 | Y13: =IFERROR(__xludf.DUMMYFUNCTION("IFERROR( SUM( FILTER( 'Shipments by country'!$H$2:$H1023 * ( INDEX(Countries!$S$2:$S1023, MATCH('Shipments by country'!$B$2:$B1023, Countries!$A$2:$A1023, 0) ) / 1000000 ) * INDEX('Vaccine efficacy curves'!$C$2:$C1023, MATCH('Shipments by country'!$C$2:$C"&"1023, 'Vaccine efficacy curves'!$A$2:$A1023, 0) ), ('Shipments by country'!$E$2:$E1023 < NOW()) * ('Shipments by country'!$I$2:$I1023 > 0.25) * ('Shipments by country'!$B$2:$B1023 = $A13) ) ), 0 )"),0.0) -> 0 | Z13: =SUMIF('Shipments by country'!$B:$B,$A13,'Shipments by country'!$M:$M) -> 0 | AA13: =IFERROR(__xludf.DUMMYFUNCTION("IFERROR( SUM( FILTER( 'Shipments by country'!$H$2:$H1023 * ( INDEX(Countries!$T$2:$T1023, MATCH('Shipments by country'!$B$2:$B1023, Countries!$A$2:$A1023, 0) ) / 1000000 ) * INDEX('Vaccine efficacy curves'!$C$2:$C1023, MATCH('Shipments by country'!$C$2:$C"&"1023, 'Vaccine efficacy curves'!$A$2:$A1023, 0) ), ('Shipments by country'!$E$2:$E1023 < NOW()) * ('Shipments by country'!$I$2:$I1023 > 0.25) * ('Shipments by country'!$B$2:$B1023 = $A13) ) ), 0 )"),0.0) -> 0 | AB13: =SUMIF('Shipments by country'!$B:$B,$A13,'Shipments by country'!$N:$N) -> 0 | AC13: =IFERROR(__xludf.DUMMYFUNCTION("IFERROR( SUM( FILTER( 'Shipments by country'!$H$2:$H1023 * ( INDEX(Countries!$S$2:$S1023, MATCH('Shipments by country'!$B$2:$B1023, Countries!$A$2:$A1023, 0) ) / 1000000 ) * 'Shipments by country'!$J$2:$J1023, ('Shipments by country'!$E$2:$E1023 < NOW()) "&"* ('Shipments by country'!$I$2:$I1023 > 0) * ('Shipments by country'!$B$2:$B1023 = $A13) ) ), 0 )"),0.0) -> 0 | AD13: =SUMIF('Shipments by country'!$B:$B,$A13,'Shipments by country'!$O:$O) -> 0 | AE13: =IFERROR(__xludf.DUMMYFUNCTION("IFERROR( SUM( FILTER( 'Shipments by country'!$H$2:$H1023 * ( INDEX(Countries!$T$2:$T1023, MATCH('Shipments by country'!$B$2:$B1023, Countries!$A$2:$A1023, 0) ) / 1000000 ) * 'Shipments by country'!$J$2:$J1023, ('Shipments by country'!$E$2:$E1023 < NOW()) "&"* ('Shipments by country'!$I$2:$I1023 > 0) * ('Shipments by country'!$B$2:$B1023 = $A13) ) ), 0 )"),0.0) -> 0 | AF13: =SUMIF('Shipments by country'!$B:$B,$A13,'Shipments by country'!$P:$P) -> 0 | AG13: =IFERROR(__xludf.DUMMYFUNCTION("IFERROR( SUM( FILTER( 'Shipments by country'!$H$2:$H1023 * INDEX(Countries!$S$2:$S1023, MATCH('Shipments by country'!$B$2:$B1023, Countries!$A$2:$A1023, 0) ) / 1000000 "&" * 'Shipments by country'!$J$2:$J1023, ( 'Shipments by country'!$E$2:$E1023 < NOW() ) * ( 'Shipments by country'!$I$2:$I1023 > 0.25 ) * ( 'Shipments by country'!$"&"B$2:$B1023 = $A13 ) ) ), 0 ) "),0.0) -> 0 | AH13: =SUMIF('Shipments by country'!$B:$B,$A13,'Shipments by country'!$Q:$Q) -> 0 | AI13: =IFERROR(__xludf.DUMMYFUNCTION("IFERROR( SUM( FILTER( 'Shipments by country'!$H$2:$H1023 * ( INDEX(Countries!$T$2:$T1023, MATCH('Shipments by country'!$B$2:$B1023, Countries!$A$2:$A1023, 0) ) / 1000000 ) * 'Shipments by country"&"'!$J$2:$J1023, ('Shipments by country'!$E$2:$E1023 < NOW()) * ('Shipments by country'!$I$2:$I1023 > 0.25) * ('Shipments by country'!$B$2:$B1023 = $A13) ) ), 0 ) "),0.0) -> 0 | AJ13: =SUMIF('Shipments by country'!$B:$B,$A13,'Shipments by country'!$R:$R) -> 0 | AK13: =O13*4 -> 412221.6 | AL13: =AK13*'Vaccine pricing'!B3 -> 1232542.6 | AM13: =IF($A13="","", LET( ctry,$A13, ctryCol,'Shipments by country'!$B$2:$B1023, vaccCol,'Shipments by country'!$C$2:$C1023, finCol,'Shipments by country'!$D$2:$D1023, doseCol,'Shipments by country'!$F$2:$F1023, price,IFERROR(VLOOKUP(vaccCol,'Vaccine pricing'!$A$2:$B1023,2,FALSE),0), totCost,SUMPRODUCT((ctryCol=ctry)*doseCol*price), gaviCost,SUMPRODUCT((ctryCol=ctry)*(finCol="Gavi")*doseCol*price), IF(totCost=0,"",gaviCost/totCost) )) | AN13: 4 | AO13: 616271.29 | AP13: 3310 | AQ13: ='Vaccine pricing'!$B$3*4/((S13/1000000)*'Vaccine efficacy curves'!$C$3) -> 354.03942 | AR13: ='Vaccine pricing'!$B$3*4/((T13/1000000)*'Vaccine efficacy curves'!$C$3) -> 172346.39 | AS13: =K13/5 -> 22901.2 | AT13: =AS13*4 -> 91604.8 | AU13: =AT13*'Vaccine pricing'!B3 -> 273898.35 | AV13: =K13*31/60 -> 59161.433 | AW13: =M13/AV13 -> 0 | AX13: =AV13-M13 -> 59161.433 | AY13: =1-AW13 -> 1 | AZ13: =AX13*4 -> 236645.73 | BA13: =AZ13*'Vaccine pricing'!B3 -> 707570.74 | BB13: 353785.37
A14: DRC | B14: =SUMIFS('Shipments by country'!F:F, 'Shipments by country'!B:B, A14, 'Shipments by country'!C:C, "RTS,S", 'Shipments by country'!G:G, "Delivered") -> 0 | C14: =SUMIFS('Shipments by country'!F:F, 'Shipments by country'!B:B, A14, 'Shipments by country'!C:C, "R21", 'Shipments by country'!G:G, "Delivered") -> 5137800 | D14: =B14+C14 -> 5137800 | E14: =SUMIFS('Shipments by country'!F:F, 'Shipments by country'!B:B, A14, 'Shipments by country'!C:C, "RTS,S") -> 0 | F14: =SUMIFS('Shipments by country'!F:F, 'Shipments by country'!B:B, A14, 'Shipments by country'!C:C, "R21") -> 10000500 | G14: =E14+F14 -> 10000500 | H14: Initial self-financing | I14: 54500000 | J14: 105789731 | K14: 19275876 | L14: =K14*0.9 -> 17348288 | M14: =G14/4 -> 2500125 | N14: =M14/L14 -> 0.14411364 | O14: =L14-M14 -> 14848163 | P14: =1-N14 -> 0.85588636 | Q14: 33140568 | R14: 67464 | S14: =Q14*1000000/J14 -> 313268.29 | T14: =R14*1000000/J14 -> 637.71785 | U14: =IFERROR(__xludf.DUMMYFUNCTION("IFERROR( SUM( FILTER( 'Shipments by country'!$H$2:$H1023 * ( INDEX(Countries!$S$2:$S1023, MATCH('Shipments by country'!$B$2:$B1023, Countries!$A$2:$A1023, 0) ) / 1000000 ) * INDEX('Vaccine efficacy curves'!$C$2:$C1023, MATCH('Shipments by country'!$C$2:$C"&"1023, 'Vaccine efficacy curves'!$A$2:$A1023, 0) ), ('Shipments by country'!$E$2:$E1023 < NOW()) * ('Shipments by country'!$I$2:$I1023 > 0) * ('Shipments by country'!$B$2:$B1023 = $A14) ) ), 0 )"),353238.5764831552) -> 353238.58 | V14: =SUMIF('Shipments by country'!$B:$B,$A14,'Shipments by country'!$K:$K) -> 57401.409 | W14: =IFERROR(__xludf.DUMMYFUNCTION("IFERROR( SUM( FILTER( 'Shipments by country'!$H$2:$H1023 * ( INDEX(Countries!$T$2:$T1023, MATCH('Shipments by country'!$B$2:$B1023, Countries!$A$2:$A1023, 0) ) / 1000000 ) * INDEX('Vaccine efficacy curves'!$C$2:$C1023, MATCH('Shipments by country'!$C$2:$C"&"1023, 'Vaccine efficacy curves'!$A$2:$A1023, 0) ), ('Shipments by country'!$E$2:$E1023 < NOW()) * ('Shipments by country'!$I$2:$I1023 > 0) * ('Shipments by country'!$B$2:$B1023 = $A14) ) ), 0 )"),700.7176927283581) -> 700.71769 | X14: =SUMIF('Shipments by country'!$B:$B,$A14,'Shipments by country'!$L:$L) -> 266542.76 | Y14: =IFERROR(__xludf.DUMMYFUNCTION("IFERROR( SUM( FILTER( 'Shipments by country'!$H$2:$H1023 * ( INDEX(Countries!$S$2:$S1023, MATCH('Shipments by country'!$B$2:$B1023, Countries!$A$2:$A1023, 0) ) / 1000000 ) * INDEX('Vaccine efficacy curves'!$C$2:$C1023, MATCH('Shipments by country'!$C$2:$C"&"1023, 'Vaccine efficacy curves'!$A$2:$A1023, 0) ), ('Shipments by country'!$E$2:$E1023 < NOW()) * ('Shipments by country'!$I$2:$I1023 > 0.25) * ('Shipments by country'!$B$2:$B1023 = $A14) ) ), 0 )"),254261.6994389244) -> 254261.7 | Z14: =SUMIF('Shipments by country'!$B:$B,$A14,'Shipments by country'!$M:$M) -> 38073.557 | AA14: =IFERROR(__xludf.DUMMYFUNCTION("IFERROR( SUM( FILTER( 'Shipments by country'!$H$2:$H1023 * ( INDEX(Countries!$T$2:$T1023, MATCH('Shipments by country'!$B$2:$B1023, Countries!$A$2:$A1023, 0) ) / 1000000 ) * INDEX('Vaccine efficacy curves'!$C$2:$C1023, MATCH('Shipments by country'!$C$2:$C"&"1023, 'Vaccine efficacy curves'!$A$2:$A1023, 0) ), ('Shipments by country'!$E$2:$E1023 < NOW()) * ('Shipments by country'!$I$2:$I1023 > 0.25) * ('Shipments by country'!$B$2:$B1023 = $A14) ) ), 0 )"),504.3777300708563) -> 504.37773 | AB14: =SUMIF('Shipments by country'!$B:$B,$A14,'Shipments by country'!$N:$N) -> 176794.11 | AC14: =IFERROR(__xludf.DUMMYFUNCTION("IFERROR( SUM( FILTER( 'Shipments by country'!$H$2:$H1023 * ( INDEX(Countries!$S$2:$S1023, MATCH('Shipments by country'!$B$2:$B1023, Countries!$A$2:$A1023, 0) ) / 1000000 ) * 'Shipments by country'!$J$2:$J1023, ('Shipments by country'!$E$2:$E1023 < NOW()) "&"* ('Shipments by country'!$I$2:$I1023 > 0) * ('Shipments by country'!$B$2:$B1023 = $A14) ) ), 0 )"),470592.1062723384) -> 470592.11 | AD14: =SUMIF('Shipments by country'!$B:$B,$A14,'Shipments by country'!$O:$O) -> 57004.553 | AE14: =IFERROR(__xludf.DUMMYFUNCTION("IFERROR( SUM( FILTER( 'Shipments by country'!$H$2:$H1023 * ( INDEX(Countries!$T$2:$T1023, MATCH('Shipments by country'!$B$2:$B1023, Countries!$A$2:$A1023, 0) ) / 1000000 ) * 'Shipments by country'!$J$2:$J1023, ('Shipments by country'!$E$2:$E1023 < NOW()) "&"* ('Shipments by country'!$I$2:$I1023 > 0) * ('Shipments by country'!$B$2:$B1023 = $A14) ) ), 0 )"),933.5113344820537) -> 933.51133 | AF14: =SUMIF('Shipments by country'!$B:$B,$A14,'Shipments by country'!$P:$P) -> 264699.97 | AG14: =IFERROR(__xludf.DUMMYFUNCTION("IFERROR( SUM( FILTER( 'Shipments by country'!$H$2:$H1023 * INDEX(Countries!$S$2:$S1023, MATCH('Shipments by country'!$B$2:$B1023, Countries!$A$2:$A1023, 0) ) / 1000000 "&" * 'Shipments by country'!$J$2:$J1023, ( 'Shipments by country'!$E$2:$E1023 < NOW() ) * ( 'Shipments by country'!$I$2:$I1023 > 0.25 ) * ( 'Shipments by country'!$"&"B$2:$B1023 = $A14 ) ) ), 0 ) "),338033.7888023865) -> 338033.79 | AH14: =SUMIF('Shipments by country'!$B:$B,$A14,'Shipments by country'!$Q:$Q) -> 88657.543 | AI14: =IFERROR(__xludf.DUMMYFUNCTION("IFERROR( SUM( FILTER( 'Shipments by country'!$H$2:$H1023 * ( INDEX(Countries!$T$2:$T1023, MATCH('Shipments by country'!$B$2:$B1023, Countries!$A$2:$A1023, 0) ) / 1000000 ) * 'Shipments by country"&"'!$J$2:$J1023, ('Shipments by country'!$E$2:$E1023 < NOW()) * ('Shipments by country'!$I$2:$I1023 > 0.25) * ('Shipments by country'!$B$2:$B1023 = $A14) ) ), 0 ) "),670.556027351471) -> 670.55603 | AJ14: =SUMIF('Shipments by country'!$B:$B,$A14,'Shipments by country'!$R:$R) -> 180.47948 | AK14: =O14*4 -> 59392654 | AL14: =AK14*'Vaccine pricing'!B3 -> 1.7758403e+08 | AM14: =IF($A14="","", LET( ctry,$A14, ctryCol,'Shipments by country'!$B$2:$B1023, vaccCol,'Shipments by country'!$C$2:$C1023, finCol,'Shipments by country'!$D$2:$D1023, doseCol,'Shipments by country'!$F$2:$F1023, price,IFERROR(VLOOKUP(vaccCol,'Vaccine pricing'!$A$2:$B1023,2,FALSE),0), totCost,SUMPRODUCT((ctryCol=ctry)*doseCol*price), gaviCost,SUMPRODUCT((ctryCol=ctry)*(finCol="Gavi")*doseCol*price), IF(totCost=0,"",gaviCost/totCost) )) -> 0.95116244 | AN14: 11 | AO14: 11878531 | AP14: 610 | AQ14: ='Vaccine pricing'!$B$3*4/((S14/1000000)*'Vaccine efficacy curves'!$C$3) -> 50.904184 | AR14: ='Vaccine pricing'!$B$3*4/((T14/1000000)*'Vaccine efficacy curves'!$C$3) -> 25005.834 | AS14: =K14/5 -> 3855175.2 | AT14: =AS14*4 -> 15420701 | AU14: =AT14*'Vaccine pricing'!B3 -> 46107895 | AV14: =K14*31/60 -> 9959202.6 | AW14: =M14/AV14 -> 0.25103666 | AX14: =AV14-M14 -> 7459077.6 | AY14: =1-AW14 -> 0.74896334 | AZ14: =AX14*4 -> 29836310 | BA14: =AZ14*'Vaccine pricing'!B3 -> 89210568 | BB14: 5967262.1
A15: Equatorial Guinea | B15: =SUMIFS('Shipments by country'!F:F, 'Shipments by country'!B:B, A15, 'Shipments by country'!C:C, "RTS,S", 'Shipments by country'!G:G, "Delivered") -> 0 | C15: =SUMIFS('Shipments by country'!F:F, 'Shipments by country'!B:B, A15, 'Shipments by country'!C:C, "R21", 'Shipments by country'!G:G, "Delivered") -> 0 | D15: =B15+C15 -> 0 | E15: =SUMIFS('Shipments by country'!F:F, 'Shipments by country'!B:B, A15, 'Shipments by country'!C:C, "RTS,S") -> 0 | F15: =SUMIFS('Shipments by country'!F:F, 'Shipments by country'!B:B, A15, 'Shipments by country'!C:C, "R21") -> 0 | G15: =E15+F15 -> 0 | H15: N/A | I15: 0 | J15: 1847549 | K15: 252431 | L15: =K15*0.9 -> 227187.9 | M15: =G15/4 -> 0 | N15: =M15/L15 -> 0 | O15: =L15-M15 -> 227187.9 | P15: =1-N15 -> 1 | Q15: 422756 | R15: 757 | S15: =Q15*1000000/J15 -> 228819.91 | T15: =R15*1000000/J15 -> 409.73203 | U15: =IFERROR(__xludf.DUMMYFUNCTION("IFERROR( SUM( FILTER( 'Shipments by country'!$H$2:$H1023 * ( INDEX(Countries!$S$2:$S1023, MATCH('Shipments by country'!$B$2:$B1023, Countries!$A$2:$A1023, 0) ) / 1000000 ) * INDEX('Vaccine efficacy curves'!$C$2:$C1023, MATCH('Shipments by country'!$C$2:$C"&"1023, 'Vaccine efficacy curves'!$A$2:$A1023, 0) ), ('Shipments by country'!$E$2:$E1023 < NOW()) * ('Shipments by country'!$I$2:$I1023 > 0) * ('Shipments by country'!$B$2:$B1023 = $A15) ) ), 0 )"),0.0) -> 0 | V15: =SUMIF('Shipments by country'!$B:$B,$A15,'Shipments by country'!$K:$K) -> 0 | W15: =IFERROR(__xludf.DUMMYFUNCTION("IFERROR( SUM( FILTER( 'Shipments by country'!$H$2:$H1023 * ( INDEX(Countries!$T$2:$T1023, MATCH('Shipments by country'!$B$2:$B1023, Countries!$A$2:$A1023, 0) ) / 1000000 ) * INDEX('Vaccine efficacy curves'!$C$2:$C1023, MATCH('Shipments by country'!$C$2:$C"&"1023, 'Vaccine efficacy curves'!$A$2:$A1023, 0) ), ('Shipments by country'!$E$2:$E1023 < NOW()) * ('Shipments by country'!$I$2:$I1023 > 0) * ('Shipments by country'!$B$2:$B1023 = $A15) ) ), 0 )"),0.0) -> 0 | X15: =SUMIF('Shipments by country'!$B:$B,$A15,'Shipments by country'!$L:$L) -> 0 | Y15: =IFERROR(__xludf.DUMMYFUNCTION("IFERROR( SUM( FILTER( 'Shipments by country'!$H$2:$H1023 * ( INDEX(Countries!$S$2:$S1023, MATCH('Shipments by country'!$B$2:$B1023, Countries!$A$2:$A1023, 0) ) / 1000000 ) * INDEX('Vaccine efficacy curves'!$C$2:$C1023, MATCH('Shipments by country'!$C$2:$C"&"1023, 'Vaccine efficacy curves'!$A$2:$A1023, 0) ), ('Shipments by country'!$E$2:$E1023 < NOW()) * ('Shipments by country'!$I$2:$I1023 > 0.25) * ('Shipments by country'!$B$2:$B1023 = $A15) ) ), 0 )"),0.0) -> 0 | Z15: =SUMIF('Shipments by country'!$B:$B,$A15,'Shipments by country'!$M:$M) -> 0 | AA15: =IFERROR(__xludf.DUMMYFUNCTION("IFERROR( SUM( FILTER( 'Shipments by country'!$H$2:$H1023 * ( INDEX(Countries!$T$2:$T1023, MATCH('Shipments by country'!$B$2:$B1023, Countries!$A$2:$A1023, 0) ) / 1000000 ) * INDEX('Vaccine efficacy curves'!$C$2:$C1023, MATCH('Shipments by country'!$C$2:$C"&"1023, 'Vaccine efficacy curves'!$A$2:$A1023, 0) ), ('Shipments by country'!$E$2:$E1023 < NOW()) * ('Shipments by country'!$I$2:$I1023 > 0.25) * ('Shipments by country'!$B$2:$B1023 = $A15) ) ), 0 )"),0.0) -> 0 | AB15: =SUMIF('Shipments by country'!$B:$B,$A15,'Shipments by country'!$N:$N) -> 0 | AC15: =IFERROR(__xludf.DUMMYFUNCTION("IFERROR( SUM( FILTER( 'Shipments by country'!$H$2:$H1023 * ( INDEX(Countries!$S$2:$S1023, MATCH('Shipments by country'!$B$2:$B1023, Countries!$A$2:$A1023, 0) ) / 1000000 ) * 'Shipments by country'!$J$2:$J1023, ('Shipments by country'!$E$2:$E1023 < NOW()) "&"* ('Shipments by country'!$I$2:$I1023 > 0) * ('Shipments by country'!$B$2:$B1023 = $A15) ) ), 0 )"),0.0) -> 0 | AD15: =SUMIF('Shipments by country'!$B:$B,$A15,'Shipments by country'!$O:$O) -> 0 | AE15: =IFERROR(__xludf.DUMMYFUNCTION("IFERROR( SUM( FILTER( 'Shipments by country'!$H$2:$H1023 * ( INDEX(Countries!$T$2:$T1023, MATCH('Shipments by country'!$B$2:$B1023, Countries!$A$2:$A1023, 0) ) / 1000000 ) * 'Shipments by country'!$J$2:$J1023, ('Shipments by country'!$E$2:$E1023 < NOW()) "&"* ('Shipments by country'!$I$2:$I1023 > 0) * ('Shipments by country'!$B$2:$B1023 = $A15) ) ), 0 )"),0.0) -> 0 | AF15: =SUMIF('Shipments by country'!$B:$B,$A15,'Shipments by country'!$P:$P) -> 0 | AG15: =IFERROR(__xludf.DUMMYFUNCTION("IFERROR( SUM( FILTER( 'Shipments by country'!$H$2:$H1023 * INDEX(Countries!$S$2:$S1023, MATCH('Shipments by country'!$B$2:$B1023, Countries!$A$2:$A1023, 0) ) / 1000000 "&" * 'Shipments by country'!$J$2:$J1023, ( 'Shipments by country'!$E$2:$E1023 < NOW() ) * ( 'Shipments by country'!$I$2:$I1023 > 0.25 ) * ( 'Shipments by country'!$"&"B$2:$B1023 = $A15 ) ) ), 0 ) "),0.0) -> 0 | AH15: =SUMIF('Shipments by country'!$B:$B,$A15,'Shipments by country'!$Q:$Q) -> 0 | AI15: =IFERROR(__xludf.DUMMYFUNCTION("IFERROR( SUM( FILTER( 'Shipments by country'!$H$2:$H1023 * ( INDEX(Countries!$T$2:$T1023, MATCH('Shipments by country'!$B$2:$B1023, Countries!$A$2:$A1023, 0) ) / 1000000 ) * 'Shipments by country"&"'!$J$2:$J1023, ('Shipments by country'!$E$2:$E1023 < NOW()) * ('Shipments by country'!$I$2:$I1023 > 0.25) * ('Shipments by country'!$B$2:$B1023 = $A15) ) ), 0 ) "),0.0) -> 0 | AJ15: =SUMIF('Shipments by country'!$B:$B,$A15,'Shipments by country'!$R:$R) -> 0 | AK15: =O15*4 -> 908751.6 | AL15: =AK15*'Vaccine pricing'!B3 -> 2717167.3 | AM15: =IF($A15="","", LET( ctry,$A15, ctryCol,'Shipments by country'!$B$2:$B1023, vaccCol,'Shipments by country'!$C$2:$C1023, finCol,'Shipments by country'!$D$2:$D1023, doseCol,'Shipments by country'!$F$2:$F1023, price,IFERROR(VLOOKUP(vaccCol,'Vaccine pricing'!$A$2:$B1023,2,FALSE),0), totCost,SUMPRODUCT((ctryCol=ctry)*doseCol*price), gaviCost,SUMPRODUCT((ctryCol=ctry)*(finCol="Gavi")*doseCol*price), IF(totCost=0,"",gaviCost/totCost) )) | AN15: - | AP15: - | AQ15: ='Vaccine pricing'!$B$3*4/((S15/1000000)*'Vaccine efficacy curves'!$C$3) -> 69.690905 | AR15: ='Vaccine pricing'!$B$3*4/((T15/1000000)*'Vaccine efficacy curves'!$C$3) -> 38919.746 | AS15: =K15/5 -> 50486.2 | AT15: =AS15*4 -> 201944.8 | AU15: =AT15*'Vaccine pricing'!B3 -> 603814.95 | AV15: =K15*31/60 -> 130422.68 | AW15: =M15/AV15 -> 0 | AX15: =AV15-M15 -> 130422.68 | AY15: =1-AW15 -> 1 | AZ15: =AX15*4 -> 521690.73 | BA15: =AZ15*'Vaccine pricing'!B3 -> 1559855.3
A16: Eritrea | B16: =SUMIFS('Shipments by country'!F:F, 'Shipments by country'!B:B, A16, 'Shipments by country'!C:C, "RTS,S", 'Shipments by country'!G:G, "Delivered") -> 0 | C16: =SUMIFS('Shipments by country'!F:F, 'Shipments by country'!B:B, A16, 'Shipments by country'!C:C, "R21", 'Shipments by country'!G:G, "Delivered") -> 0 | D16: =B16+C16 -> 0 | E16: =SUMIFS('Shipments by country'!F:F, 'Shipments by country'!B:B, A16, 'Shipments by country'!C:C, "RTS,S") -> 0 | F16: =SUMIFS('Shipments by country'!F:F, 'Shipments by country'!B:B, A16, 'Shipments by country'!C:C, "R21") -> 0 | G16: =E16+F16 -> 0 | H16: Initial self-financing | I16: 0 | J16: 3470389 | K16: 461114 | L16: =K16*0.9 -> 415002.6 | M16: =G16/4 -> 0 | N16: =M16/L16 -> 0 | O16: =L16-M16 -> 415002.6 | P16: =1-N16 -> 1 | Q16: 219981 | R16: 459 | S16: =Q16*1000000/J16 -> 63387.995 | T16: =R16*1000000/J16 -> 132.26183 | U16: =IFERROR(__xludf.DUMMYFUNCTION("IFERROR( SUM( FILTER( 'Shipments by country'!$H$2:$H1023 * ( INDEX(Countries!$S$2:$S1023, MATCH('Shipments by country'!$B$2:$B1023, Countries!$A$2:$A1023, 0) ) / 1000000 ) * INDEX('Vaccine efficacy curves'!$C$2:$C1023, MATCH('Shipments by country'!$C$2:$C"&"1023, 'Vaccine efficacy curves'!$A$2:$A1023, 0) ), ('Shipments by country'!$E$2:$E1023 < NOW()) * ('Shipments by country'!$I$2:$I1023 > 0) * ('Shipments by country'!$B$2:$B1023 = $A16) ) ), 0 )"),0.0) -> 0 | V16: =SUMIF('Shipments by country'!$B:$B,$A16,'Shipments by country'!$K:$K) -> 0 | W16: =IFERROR(__xludf.DUMMYFUNCTION("IFERROR( SUM( FILTER( 'Shipments by country'!$H$2:$H1023 * ( INDEX(Countries!$T$2:$T1023, MATCH('Shipments by country'!$B$2:$B1023, Countries!$A$2:$A1023, 0) ) / 1000000 ) * INDEX('Vaccine efficacy curves'!$C$2:$C1023, MATCH('Shipments by country'!$C$2:$C"&"1023, 'Vaccine efficacy curves'!$A$2:$A1023, 0) ), ('Shipments by country'!$E$2:$E1023 < NOW()) * ('Shipments by country'!$I$2:$I1023 > 0) * ('Shipments by country'!$B$2:$B1023 = $A16) ) ), 0 )"),0.0) -> 0 | X16: =SUMIF('Shipments by country'!$B:$B,$A16,'Shipments by country'!$L:$L) -> 0 | Y16: =IFERROR(__xludf.DUMMYFUNCTION("IFERROR( SUM( FILTER( 'Shipments by country'!$H$2:$H1023 * ( INDEX(Countries!$S$2:$S1023, MATCH('Shipments by country'!$B$2:$B1023, Countries!$A$2:$A1023, 0) ) / 1000000 ) * INDEX('Vaccine efficacy curves'!$C$2:$C1023, MATCH('Shipments by country'!$C$2:$C"&"1023, 'Vaccine efficacy curves'!$A$2:$A1023, 0) ), ('Shipments by country'!$E$2:$E1023 < NOW()) * ('Shipments by country'!$I$2:$I1023 > 0.25) * ('Shipments by country'!$B$2:$B1023 = $A16) ) ), 0 )"),0.0) -> 0 | Z16: =SUMIF('Shipments by country'!$B:$B,$A16,'Shipments by country'!$M:$M) -> 0 | AA16: =IFERROR(__xludf.DUMMYFUNCTION("IFERROR( SUM( FILTER( 'Shipments by country'!$H$2:$H1023 * ( INDEX(Countries!$T$2:$T1023, MATCH('Shipments by country'!$B$2:$B1023, Countries!$A$2:$A1023, 0) ) / 1000000 ) * INDEX('Vaccine efficacy curves'!$C$2:$C1023, MATCH('Shipments by country'!$C$2:$C"&"1023, 'Vaccine efficacy curves'!$A$2:$A1023, 0) ), ('Shipments by country'!$E$2:$E1023 < NOW()) * ('Shipments by country'!$I$2:$I1023 > 0.25) * ('Shipments by country'!$B$2:$B1023 = $A16) ) ), 0 )"),0.0) -> 0 | AB16: =SUMIF('Shipments by country'!$B:$B,$A16,'Shipments by country'!$N:$N) -> 0 | AC16: =IFERROR(__xludf.DUMMYFUNCTION("IFERROR( SUM( FILTER( 'Shipments by country'!$H$2:$H1023 * ( INDEX(Countries!$S$2:$S1023, MATCH('Shipments by country'!$B$2:$B1023, Countries!$A$2:$A1023, 0) ) / 1000000 ) * 'Shipments by country'!$J$2:$J1023, ('Shipments by country'!$E$2:$E1023 < NOW()) "&"* ('Shipments by country'!$I$2:$I1023 > 0) * ('Shipments by country'!$B$2:$B1023 = $A16) ) ), 0 )"),0.0) -> 0 | AD16: =SUMIF('Shipments by country'!$B:$B,$A16,'Shipments by country'!$O:$O) -> 0 | AE16: =IFERROR(__xludf.DUMMYFUNCTION("IFERROR( SUM( FILTER( 'Shipments by country'!$H$2:$H1023 * ( INDEX(Countries!$T$2:$T1023, MATCH('Shipments by country'!$B$2:$B1023, Countries!$A$2:$A1023, 0) ) / 1000000 ) * 'Shipments by country'!$J$2:$J1023, ('Shipments by country'!$E$2:$E1023 < NOW()) "&"* ('Shipments by country'!$I$2:$I1023 > 0) * ('Shipments by country'!$B$2:$B1023 = $A16) ) ), 0 )"),0.0) -> 0 | AF16: =SUMIF('Shipments by country'!$B:$B,$A16,'Shipments by country'!$P:$P) -> 0 | AG16: =IFERROR(__xludf.DUMMYFUNCTION("IFERROR( SUM( FILTER( 'Shipments by country'!$H$2:$H1023 * INDEX(Countries!$S$2:$S1023, MATCH('Shipments by country'!$B$2:$B1023, Countries!$A$2:$A1023, 0) ) / 1000000 "&" * 'Shipments by country'!$J$2:$J1023, ( 'Shipments by country'!$E$2:$E1023 < NOW() ) * ( 'Shipments by country'!$I$2:$I1023 > 0.25 ) * ( 'Shipments by country'!$"&"B$2:$B1023 = $A16 ) ) ), 0 ) "),0.0) -> 0 | AH16: =SUMIF('Shipments by country'!$B:$B,$A16,'Shipments by country'!$Q:$Q) -> 0 | AI16: =IFERROR(__xludf.DUMMYFUNCTION("IFERROR( SUM( FILTER( 'Shipments by country'!$H$2:$H1023 * ( INDEX(Countries!$T$2:$T1023, MATCH('Shipments by country'!$B$2:$B1023, Countries!$A$2:$A1023, 0) ) / 1000000 ) * 'Shipments by country"&"'!$J$2:$J1023, ('Shipments by country'!$E$2:$E1023 < NOW()) * ('Shipments by country'!$I$2:$I1023 > 0.25) * ('Shipments by country'!$B$2:$B1023 = $A16) ) ), 0 ) "),0.0) -> 0 | AJ16: =SUMIF('Shipments by country'!$B:$B,$A16,'Shipments by country'!$R:$R) -> 0 | AK16: =O16*4 -> 1660010.4 | AL16: =AK16*'Vaccine pricing'!B3 -> 4963431.1 | AM16: =IF($A16="","", LET( ctry,$A16, ctryCol,'Shipments by country'!$B$2:$B1023, vaccCol,'Shipments by country'!$C$2:$C1023, finCol,'Shipments by country'!$D$2:$D1023, doseCol,'Shipments by country'!$F$2:$F1023, price,IFERROR(VLOOKUP(vaccCol,'Vaccine pricing'!$A$2:$B1023,2,FALSE),0), totCost,SUMPRODUCT((ctryCol=ctry)*doseCol*price), gaviCost,SUMPRODUCT((ctryCol=ctry)*(finCol="Gavi")*doseCol*price), IF(totCost=0,"",gaviCost/totCost) )) | AN16: 11 | AO16: 332002.08 | AP16: - | AQ16: ='Vaccine pricing'!$B$3*4/((S16/1000000)*'Vaccine efficacy curves'!$C$3) -> 251.57235 | AR16: ='Vaccine pricing'!$B$3*4/((T16/1000000)*'Vaccine efficacy curves'!$C$3) -> 120568.93 | AS16: =K16/5 -> 92222.8 | AT16: =AS16*4 -> 368891.2 | AU16: =AT16*'Vaccine pricing'!B3 -> 1102984.7 | AV16: =K16*31/60 -> 238242.23 | AW16: =M16/AV16 -> 0 | AX16: =AV16-M16 -> 238242.23 | AY16: =1-AW16 -> 1 | AZ16: =AX16*4 -> 952968.93 | BA16: =AZ16*'Vaccine pricing'!B3 -> 2849377.1 | BB16: 190593.79
A17: Eswatini | B17: =SUMIFS('Shipments by country'!F:F, 'Shipments by country'!B:B, A17, 'Shipments by country'!C:C, "RTS,S", 'Shipments by country'!G:G, "Delivered") -> 0 | C17: =SUMIFS('Shipments by country'!F:F, 'Shipments by country'!B:B, A17, 'Shipments by country'!C:C, "R21", 'Shipments by country'!G:G, "Delivered") -> 0 | D17: =B17+C17 -> 0 | E17: =SUMIFS('Shipments by country'!F:F, 'Shipments by country'!B:B, A17, 'Shipments by country'!C:C, "RTS,S") -> 0 | F17: =SUMIFS('Shipments by country'!F:F, 'Shipments by country'!B:B, A17, 'Shipments by country'!C:C, "R21") -> 0 | G17: =E17+F17 -> 0 | H17: N/A | I17: 0 | J17: 344541 | K17: 142151 | L17: =K17*0.9 -> 127935.9 | M17: =G17/4 -> 0 | N17: =M17/L17 -> 0 | O17: =L17-M17 -> 127935.9 | P17: =1-N17 -> 1 | Q17: 597 | R17: 7 | S17: =Q17*1000000/J17 -> 1732.7401 | T17: =R17*1000000/J17 -> 20.316885 | U17: =IFERROR(__xludf.DUMMYFUNCTION("IFERROR( SUM( FILTER( 'Shipments by country'!$H$2:$H1023 * ( INDEX(Countries!$S$2:$S1023, MATCH('Shipments by country'!$B$2:$B1023, Countries!$A$2:$A1023, 0) ) / 1000000 ) * INDEX('Vaccine efficacy curves'!$C$2:$C1023, MATCH('Shipments by country'!$C$2:$C"&"1023, 'Vaccine efficacy curves'!$A$2:$A1023, 0) ), ('Shipments by country'!$E$2:$E1023 < NOW()) * ('Shipments by country'!$I$2:$I1023 > 0) * ('Shipments by country'!$B$2:$B1023 = $A17) ) ), 0 )"),0.0) -> 0 | V17: =SUMIF('Shipments by country'!$B:$B,$A17,'Shipments by country'!$K:$K) -> 0 | W17: =IFERROR(__xludf.DUMMYFUNCTION("IFERROR( SUM( FILTER( 'Shipments by country'!$H$2:$H1023 * ( INDEX(Countries!$T$2:$T1023, MATCH('Shipments by country'!$B$2:$B1023, Countries!$A$2:$A1023, 0) ) / 1000000 ) * INDEX('Vaccine efficacy curves'!$C$2:$C1023, MATCH('Shipments by country'!$C$2:$C"&"1023, 'Vaccine efficacy curves'!$A$2:$A1023, 0) ), ('Shipments by country'!$E$2:$E1023 < NOW()) * ('Shipments by country'!$I$2:$I1023 > 0) * ('Shipments by country'!$B$2:$B1023 = $A17) ) ), 0 )"),0.0) -> 0 | X17: =SUMIF('Shipments by country'!$B:$B,$A17,'Shipments by country'!$L:$L) -> 0 | Y17: =IFERROR(__xludf.DUMMYFUNCTION("IFERROR( SUM( FILTER( 'Shipments by country'!$H$2:$H1023 * ( INDEX(Countries!$S$2:$S1023, MATCH('Shipments by country'!$B$2:$B1023, Countries!$A$2:$A1023, 0) ) / 1000000 ) * INDEX('Vaccine efficacy curves'!$C$2:$C1023, MATCH('Shipments by country'!$C$2:$C"&"1023, 'Vaccine efficacy curves'!$A$2:$A1023, 0) ), ('Shipments by country'!$E$2:$E1023 < NOW()) * ('Shipments by country'!$I$2:$I1023 > 0.25) * ('Shipments by country'!$B$2:$B1023 = $A17) ) ), 0 )"),0.0) -> 0 | Z17: =SUMIF('Shipments by country'!$B:$B,$A17,'Shipments by country'!$M:$M) -> 0 | AA17: =IFERROR(__xludf.DUMMYFUNCTION("IFERROR( SUM( FILTER( 'Shipments by country'!$H$2:$H1023 * ( INDEX(Countries!$T$2:$T1023, MATCH('Shipments by country'!$B$2:$B1023, Countries!$A$2:$A1023, 0) ) / 1000000 ) * INDEX('Vaccine efficacy curves'!$C$2:$C1023, MATCH('Shipments by country'!$C$2:$C"&"1023, 'Vaccine efficacy curves'!$A$2:$A1023, 0) ), ('Shipments by country'!$E$2:$E1023 < NOW()) * ('Shipments by country'!$I$2:$I1023 > 0.25) * ('Shipments by country'!$B$2:$B1023 = $A17) ) ), 0 )"),0.0) -> 0 | AB17: =SUMIF('Shipments by country'!$B:$B,$A17,'Shipments by country'!$N:$N) -> 0 | AC17: =IFERROR(__xludf.DUMMYFUNCTION("IFERROR( SUM( FILTER( 'Shipments by country'!$H$2:$H1023 * ( INDEX(Countries!$S$2:$S1023, MATCH('Shipments by country'!$B$2:$B1023, Countries!$A$2:$A1023, 0) ) / 1000000 ) * 'Shipments by country'!$J$2:$J1023, ('Shipments by country'!$E$2:$E1023 < NOW()) "&"* ('Shipments by country'!$I$2:$I1023 > 0) * ('Shipments by country'!$B$2:$B1023 = $A17) ) ), 0 )"),0.0) -> 0 | AD17: =SUMIF('Shipments by country'!$B:$B,$A17,'Shipments by country'!$O:$O) -> 0 | AE17: =IFERROR(__xludf.DUMMYFUNCTION("IFERROR( SUM( FILTER( 'Shipments by country'!$H$2:$H1023 * ( INDEX(Countries!$T$2:$T1023, MATCH('Shipments by country'!$B$2:$B1023, Countries!$A$2:$A1023, 0) ) / 1000000 ) * 'Shipments by country'!$J$2:$J1023, ('Shipments by country'!$E$2:$E1023 < NOW()) "&"* ('Shipments by country'!$I$2:$I1023 > 0) * ('Shipments by country'!$B$2:$B1023 = $A17) ) ), 0 )"),0.0) -> 0 | AF17: =SUMIF('Shipments by country'!$B:$B,$A17,'Shipments by country'!$P:$P) -> 0 | AG17: =IFERROR(__xludf.DUMMYFUNCTION("IFERROR( SUM( FILTER( 'Shipments by country'!$H$2:$H1023 * INDEX(Countries!$S$2:$S1023, MATCH('Shipments by country'!$B$2:$B1023, Countries!$A$2:$A1023, 0) ) / 1000000 "&" * 'Shipments by country'!$J$2:$J1023, ( 'Shipments by country'!$E$2:$E1023 < NOW() ) * ( 'Shipments by country'!$I$2:$I1023 > 0.25 ) * ( 'Shipments by country'!$"&"B$2:$B1023 = $A17 ) ) ), 0 ) "),0.0) -> 0 | AH17: =SUMIF('Shipments by country'!$B:$B,$A17,'Shipments by country'!$Q:$Q) -> 0 | AI17: =IFERROR(__xludf.DUMMYFUNCTION("IFERROR( SUM( FILTER( 'Shipments by country'!$H$2:$H1023 * ( INDEX(Countries!$T$2:$T1023, MATCH('Shipments by country'!$B$2:$B1023, Countries!$A$2:$A1023, 0) ) / 1000000 ) * 'Shipments by country"&"'!$J$2:$J1023, ('Shipments by country'!$E$2:$E1023 < NOW()) * ('Shipments by country'!$I$2:$I1023 > 0.25) * ('Shipments by country'!$B$2:$B1023 = $A17) ) ), 0 ) "),0.0) -> 0 | AJ17: =SUMIF('Shipments by country'!$B:$B,$A17,'Shipments by country'!$R:$R) -> 0 | AK17: =O17*4 -> 511743.6 | AL17: =AK17*'Vaccine pricing'!B3 -> 1530113.4 | AM17: =IF($A17="","", LET( ctry,$A17, ctryCol,'Shipments by country'!$B$2:$B1023, vaccCol,'Shipments by country'!$C$2:$C1023, finCol,'Shipments by country'!$D$2:$D1023, doseCol,'Shipments by country'!$F$2:$F1023, price,IFERROR(VLOOKUP(vaccCol,'Vaccine pricing'!$A$2:$B1023,2,FALSE),0), totCost,SUMPRODUCT((ctryCol=ctry)*doseCol*price), gaviCost,SUMPRODUCT((ctryCol=ctry)*(finCol="Gavi")*doseCol*price), IF(totCost=0,"",gaviCost/totCost) )) | AN17: - | AP17: - | AQ17: ='Vaccine pricing'!$B$3*4/((S17/1000000)*'Vaccine efficacy curves'!$C$3) -> 9203.1499 | AR17: ='Vaccine pricing'!$B$3*4/((T17/1000000)*'Vaccine efficacy curves'!$C$3) -> 784897.21 | AS17: =K17/5 -> 28430.2 | AT17: =AS17*4 -> 113720.8 | AU17: =AT17*'Vaccine pricing'!B3 -> 340025.19 | AV17: =K17*31/60 -> 73444.683 | AW17: =M17/AV17 -> 0 | AX17: =AV17-M17 -> 73444.683 | AY17: =1-AW17 -> 1 | AZ17: =AX17*4 -> 293778.73 | BA17: =AZ17*'Vaccine pricing'!B3 -> 878398.41
A18: Ethiopia | B18: =SUMIFS('Shipments by country'!F:F, 'Shipments by country'!B:B, A18, 'Shipments by country'!C:C, "RTS,S", 'Shipments by country'!G:G, "Delivered") -> 0 | C18: =SUMIFS('Shipments by country'!F:F, 'Shipments by country'!B:B, A18, 'Shipments by country'!C:C, "R21", 'Shipments by country'!G:G, "Delivered") -> 186200 | D18: =B18+C18 -> 186200 | E18: =SUMIFS('Shipments by country'!F:F, 'Shipments by country'!B:B, A18, 'Shipments by country'!C:C, "RTS,S") -> 0 | F18: =SUMIFS('Shipments by country'!F:F, 'Shipments by country'!B:B, A18, 'Shipments by country'!C:C, "R21") -> 186200 | G18: =E18+F18 -> 186200 | H18: Initial self-financing | I18: 36000000 | J18: 128691692 | K18: 19066529 | L18: =K18*0.9 -> 17159876 | M18: =G18/4 -> 46550 | N18: =M18/L18 -> 0.0027127235 | O18: =L18-M18 -> 17113326 | P18: =1-N18 -> 0.99728728 | Q18: 9559569 | R18: 18567 | S18: =Q18*1000000/J18 -> 74282.721 | T18: =R18*1000000/J18 -> 144.27505 | U18: =IFERROR(__xludf.DUMMYFUNCTION("IFERROR( SUM( FILTER( 'Shipments by country'!$H$2:$H1023 * ( INDEX(Countries!$S$2:$S1023, MATCH('Shipments by country'!$B$2:$B1023, Countries!$A$2:$A1023, 0) ) / 1000000 ) * INDEX('Vaccine efficacy curves'!$C$2:$C1023, MATCH('Shipments by country'!$C$2:$C"&"1023, 'Vaccine efficacy curves'!$A$2:$A1023, 0) ), ('Shipments by country'!$E$2:$E1023 < NOW()) * ('Shipments by country'!$I$2:$I1023 > 0) * ('Shipments by country'!$B$2:$B1023 = $A18) ) ), 0 )"),9214.747252817886) -> 9214.7473 | V18: =SUMIF('Shipments by country'!$B:$B,$A18,'Shipments by country'!$K:$K) -> 367.93152 | W18: =IFERROR(__xludf.DUMMYFUNCTION("IFERROR( SUM( FILTER( 'Shipments by country'!$H$2:$H1023 * ( INDEX(Countries!$T$2:$T1023, MATCH('Shipments by country'!$B$2:$B1023, Countries!$A$2:$A1023, 0) ) / 1000000 ) * INDEX('Vaccine efficacy curves'!$C$2:$C1023, MATCH('Shipments by country'!$C$2:$C"&"1023, 'Vaccine efficacy curves'!$A$2:$A1023, 0) ), ('Shipments by country'!$E$2:$E1023 < NOW()) * ('Shipments by country'!$I$2:$I1023 > 0) * ('Shipments by country'!$B$2:$B1023 = $A18) ) ), 0 )"),18.279250523413413) -> 18.279251 | X18: =SUMIF('Shipments by country'!$B:$B,$A18,'Shipments by country'!$L:$L) -> 1472.0178 | Y18: =IFERROR(__xludf.DUMMYFUNCTION("IFERROR( SUM( FILTER( 'Shipments by country'!$H$2:$H1023 * ( INDEX(Countries!$S$2:$S1023, MATCH('Shipments by country'!$B$2:$B1023, Countries!$A$2:$A1023, 0) ) / 1000000 ) * INDEX('Vaccine efficacy curves'!$C$2:$C1023, MATCH('Shipments by country'!$C$2:$C"&"1023, 'Vaccine efficacy curves'!$A$2:$A1023, 0) ), ('Shipments by country'!$E$2:$E1023 < NOW()) * ('Shipments by country'!$I$2:$I1023 > 0.25) * ('Shipments by country'!$B$2:$B1023 = $A18) ) ), 0 )"),9214.747252817886) -> 9214.7473 | Z18: =SUMIF('Shipments by country'!$B:$B,$A18,'Shipments by country'!$M:$M) -> 205.87643 | AA18: =IFERROR(__xludf.DUMMYFUNCTION("IFERROR( SUM( FILTER( 'Shipments by country'!$H$2:$H1023 * ( INDEX(Countries!$T$2:$T1023, MATCH('Shipments by country'!$B$2:$B1023, Countries!$A$2:$A1023, 0) ) / 1000000 ) * INDEX('Vaccine efficacy curves'!$C$2:$C1023, MATCH('Shipments by country'!$C$2:$C"&"1023, 'Vaccine efficacy curves'!$A$2:$A1023, 0) ), ('Shipments by country'!$E$2:$E1023 < NOW()) * ('Shipments by country'!$I$2:$I1023 > 0.25) * ('Shipments by country'!$B$2:$B1023 = $A18) ) ), 0 )"),18.279250523413413) -> 18.279251 | AB18: =SUMIF('Shipments by country'!$B:$B,$A18,'Shipments by country'!$N:$N) -> 823.66893 | AC18: =IFERROR(__xludf.DUMMYFUNCTION("IFERROR( SUM( FILTER( 'Shipments by country'!$H$2:$H1023 * ( INDEX(Countries!$S$2:$S1023, MATCH('Shipments by country'!$B$2:$B1023, Countries!$A$2:$A1023, 0) ) / 1000000 ) * 'Shipments by country'!$J$2:$J1023, ('Shipments by country'!$E$2:$E1023 < NOW()) "&"* ('Shipments by country'!$I$2:$I1023 > 0) * ('Shipments by country'!$B$2:$B1023 = $A18) ) ), 0 )"),12341.179356452523) -> 12341.179 | AD18: =SUMIF('Shipments by country'!$B:$B,$A18,'Shipments by country'!$O:$O) -> 367.93152 | AE18: =IFERROR(__xludf.DUMMYFUNCTION("IFERROR( SUM( FILTER( 'Shipments by country'!$H$2:$H1023 * ( INDEX(Countries!$T$2:$T1023, MATCH('Shipments by country'!$B$2:$B1023, Countries!$A$2:$A1023, 0) ) / 1000000 ) * 'Shipments by country'!$J$2:$J1023, ('Shipments by country'!$E$2:$E1023 < NOW()) "&"* ('Shipments by country'!$I$2:$I1023 > 0) * ('Shipments by country'!$B$2:$B1023 = $A18) ) ), 0 )"),24.48113909385725) -> 24.481139 | AF18: =SUMIF('Shipments by country'!$B:$B,$A18,'Shipments by country'!$P:$P) -> 1472.0178 | AG18: =IFERROR(__xludf.DUMMYFUNCTION("IFERROR( SUM( FILTER( 'Shipments by country'!$H$2:$H1023 * INDEX(Countries!$S$2:$S1023, MATCH('Shipments by country'!$B$2:$B1023, Countries!$A$2:$A1023, 0) ) / 1000000 "&" * 'Shipments by country'!$J$2:$J1023, ( 'Shipments by country'!$E$2:$E1023 < NOW() ) * ( 'Shipments by country'!$I$2:$I1023 > 0.25 ) * ( 'Shipments by country'!$"&"B$2:$B1023 = $A18 ) ) ), 0 ) "),12341.179356452523) -> 12341.179 | AH18: =SUMIF('Shipments by country'!$B:$B,$A18,'Shipments by country'!$Q:$Q) -> 648.34887 | AI18: =IFERROR(__xludf.DUMMYFUNCTION("IFERROR( SUM( FILTER( 'Shipments by country'!$H$2:$H1023 * ( INDEX(Countries!$T$2:$T1023, MATCH('Shipments by country'!$B$2:$B1023, Countries!$A$2:$A1023, 0) ) / 1000000 ) * 'Shipments by country"&"'!$J$2:$J1023, ('Shipments by country'!$E$2:$E1023 < NOW()) * ('Shipments by country'!$I$2:$I1023 > 0.25) * ('Shipments by country'!$B$2:$B1023 = $A18) ) ), 0 ) "),24.48113909385725) -> 24.481139 | AJ18: =SUMIF('Shipments by country'!$B:$B,$A18,'Shipments by country'!$R:$R) -> 1.2592507 | AK18: =O18*4 -> 68453304 | AL18: =AK18*'Vaccine pricing'!B3 -> 2.0467538e+08 | AM18: =IF($A18="","", LET( ctry,$A18, ctryCol,'Shipments by country'!$B$2:$B1023, vaccCol,'Shipments by country'!$C$2:$C1023, finCol,'Shipments by country'!$D$2:$D1023, doseCol,'Shipments by country'!$F$2:$F1023, price,IFERROR(VLOOKUP(vaccCol,'Vaccine pricing'!$A$2:$B1023,2,FALSE),0), totCost,SUMPRODUCT((ctryCol=ctry)*doseCol*price), gaviCost,SUMPRODUCT((ctryCol=ctry)*(finCol="Gavi")*doseCol*price), IF(totCost=0,"",gaviCost/totCost) )) -> 0.94897959 | AN18: 11 | AO18: 13690661 | AP18: 1037 | AQ18: ='Vaccine pricing'!$B$3*4/((S18/1000000)*'Vaccine efficacy curves'!$C$3) -> 214.67532 | AR18: ='Vaccine pricing'!$B$3*4/((T18/1000000)*'Vaccine efficacy curves'!$C$3) -> 110529.62 | AS18: =K18/5 -> 3813305.8 | AT18: =AS18*4 -> 15253223 | AU18: =AT18*'Vaccine pricing'!B3 -> 45607137 | AV18: =K18*31/60 -> 9851040 | AW18: =M18/AV18 -> 0.0047253894 | AX18: =AV18-M18 -> 9804490 | AY18: =1-AW18 -> 0.99527461 | AZ18: =AX18*4 -> 39217960 | BA18: =AZ18*'Vaccine pricing'!B3 -> 1.172617e+08 | BB18: 7843592
A19: Gabon | B19: =SUMIFS('Shipments by country'!F:F, 'Shipments by country'!B:B, A19, 'Shipments by country'!C:C, "RTS,S", 'Shipments by country'!G:G, "Delivered") -> 0 | C19: =SUMIFS('Shipments by country'!F:F, 'Shipments by country'!B:B, A19, 'Shipments by country'!C:C, "R21", 'Shipments by country'!G:G, "Delivered") -> 0 | D19: =B19+C19 -> 0 | E19: =SUMIFS('Shipments by country'!F:F, 'Shipments by country'!B:B, A19, 'Shipments by country'!C:C, "RTS,S") -> 0 | F19: =SUMIFS('Shipments by country'!F:F, 'Shipments by country'!B:B, A19, 'Shipments by country'!C:C, "R21") -> 0 | G19: =E19+F19 -> 0 | H19: N/A | I19: 0 | J19: 2484788 | K19: 331234 | L19: =K19*0.9 -> 298110.6 | M19: =G19/4 -> 0 | N19: =M19/L19 -> 0 | O19: =L19-M19 -> 298110.6 | P19: =1-N19 -> 1 | Q19: 569819 | R19: 433 | S19: =Q19*1000000/J19 -> 229322.98 | T19: =R19*1000000/J19 -> 174.26034 | U19: =IFERROR(__xludf.DUMMYFUNCTION("IFERROR( SUM( FILTER( 'Shipments by country'!$H$2:$H1023 * ( INDEX(Countries!$S$2:$S1023, MATCH('Shipments by country'!$B$2:$B1023, Countries!$A$2:$A1023, 0) ) / 1000000 ) * INDEX('Vaccine efficacy curves'!$C$2:$C1023, MATCH('Shipments by country'!$C$2:$C"&"1023, 'Vaccine efficacy curves'!$A$2:$A1023, 0) ), ('Shipments by country'!$E$2:$E1023 < NOW()) * ('Shipments by country'!$I$2:$I1023 > 0) * ('Shipments by country'!$B$2:$B1023 = $A19) ) ), 0 )"),0.0) -> 0 | V19: =SUMIF('Shipments by country'!$B:$B,$A19,'Shipments by country'!$K:$K) -> 0 | W19: =IFERROR(__xludf.DUMMYFUNCTION("IFERROR( SUM( FILTER( 'Shipments by country'!$H$2:$H1023 * ( INDEX(Countries!$T$2:$T1023, MATCH('Shipments by country'!$B$2:$B1023, Countries!$A$2:$A1023, 0) ) / 1000000 ) * INDEX('Vaccine efficacy curves'!$C$2:$C1023, MATCH('Shipments by country'!$C$2:$C"&"1023, 'Vaccine efficacy curves'!$A$2:$A1023, 0) ), ('Shipments by country'!$E$2:$E1023 < NOW()) * ('Shipments by country'!$I$2:$I1023 > 0) * ('Shipments by country'!$B$2:$B1023 = $A19) ) ), 0 )"),0.0) -> 0 | X19: =SUMIF('Shipments by country'!$B:$B,$A19,'Shipments by country'!$L:$L) -> 0 | Y19: =IFERROR(__xludf.DUMMYFUNCTION("IFERROR( SUM( FILTER( 'Shipments by country'!$H$2:$H1023 * ( INDEX(Countries!$S$2:$S1023, MATCH('Shipments by country'!$B$2:$B1023, Countries!$A$2:$A1023, 0) ) / 1000000 ) * INDEX('Vaccine efficacy curves'!$C$2:$C1023, MATCH('Shipments by country'!$C$2:$C"&"1023, 'Vaccine efficacy curves'!$A$2:$A1023, 0) ), ('Shipments by country'!$E$2:$E1023 < NOW()) * ('Shipments by country'!$I$2:$I1023 > 0.25) * ('Shipments by country'!$B$2:$B1023 = $A19) ) ), 0 )"),0.0) -> 0 | Z19: =SUMIF('Shipments by country'!$B:$B,$A19,'Shipments by country'!$M:$M) -> 0 | AA19: =IFERROR(__xludf.DUMMYFUNCTION("IFERROR( SUM( FILTER( 'Shipments by country'!$H$2:$H1023 * ( INDEX(Countries!$T$2:$T1023, MATCH('Shipments by country'!$B$2:$B1023, Countries!$A$2:$A1023, 0) ) / 1000000 ) * INDEX('Vaccine efficacy curves'!$C$2:$C1023, MATCH('Shipments by country'!$C$2:$C"&"1023, 'Vaccine efficacy curves'!$A$2:$A1023, 0) ), ('Shipments by country'!$E$2:$E1023 < NOW()) * ('Shipments by country'!$I$2:$I1023 > 0.25) * ('Shipments by country'!$B$2:$B1023 = $A19) ) ), 0 )"),0.0) -> 0 | AB19: =SUMIF('Shipments by country'!$B:$B,$A19,'Shipments by country'!$N:$N) -> 0 | AC19: =IFERROR(__xludf.DUMMYFUNCTION("IFERROR( SUM( FILTER( 'Shipments by country'!$H$2:$H1023 * ( INDEX(Countries!$S$2:$S1023, MATCH('Shipments by country'!$B$2:$B1023, Countries!$A$2:$A1023, 0) ) / 1000000 ) * 'Shipments by country'!$J$2:$J1023, ('Shipments by country'!$E$2:$E1023 < NOW()) "&"* ('Shipments by country'!$I$2:$I1023 > 0) * ('Shipments by country'!$B$2:$B1023 = $A19) ) ), 0 )"),0.0) -> 0 | AD19: =SUMIF('Shipments by country'!$B:$B,$A19,'Shipments by country'!$O:$O) -> 0 | AE19: =IFERROR(__xludf.DUMMYFUNCTION("IFERROR( SUM( FILTER( 'Shipments by country'!$H$2:$H1023 * ( INDEX(Countries!$T$2:$T1023, MATCH('Shipments by country'!$B$2:$B1023, Countries!$A$2:$A1023, 0) ) / 1000000 ) * 'Shipments by country'!$J$2:$J1023, ('Shipments by country'!$E$2:$E1023 < NOW()) "&"* ('Shipments by country'!$I$2:$I1023 > 0) * ('Shipments by country'!$B$2:$B1023 = $A19) ) ), 0 )"),0.0) -> 0 | AF19: =SUMIF('Shipments by country'!$B:$B,$A19,'Shipments by country'!$P:$P) -> 0 | AG19: =IFERROR(__xludf.DUMMYFUNCTION("IFERROR( SUM( FILTER( 'Shipments by country'!$H$2:$H1023 * INDEX(Countries!$S$2:$S1023, MATCH('Shipments by country'!$B$2:$B1023, Countries!$A$2:$A1023, 0) ) / 1000000 "&" * 'Shipments by country'!$J$2:$J1023, ( 'Shipments by country'!$E$2:$E1023 < NOW() ) * ( 'Shipments by country'!$I$2:$I1023 > 0.25 ) * ( 'Shipments by country'!$"&"B$2:$B1023 = $A19 ) ) ), 0 ) "),0.0) -> 0 | AH19: =SUMIF('Shipments by country'!$B:$B,$A19,'Shipments by country'!$Q:$Q) -> 0 | AI19: =IFERROR(__xludf.DUMMYFUNCTION("IFERROR( SUM( FILTER( 'Shipments by country'!$H$2:$H1023 * ( INDEX(Countries!$T$2:$T1023, MATCH('Shipments by country'!$B$2:$B1023, Countries!$A$2:$A1023, 0) ) / 1000000 ) * 'Shipments by country"&"'!$J$2:$J1023, ('Shipments by country'!$E$2:$E1023 < NOW()) * ('Shipments by country'!$I$2:$I1023 > 0.25) * ('Shipments by country'!$B$2:$B1023 = $A19) ) ), 0 ) "),0.0) -> 0 | AJ19: =SUMIF('Shipments by country'!$B:$B,$A19,'Shipments by country'!$R:$R) -> 0 | AK19: =O19*4 -> 1192442.4 | AL19: =AK19*'Vaccine pricing'!B3 -> 3565402.8 | AM19: =IF($A19="","", LET( ctry,$A19, ctryCol,'Shipments by country'!$B$2:$B1023, vaccCol,'Shipments by country'!$C$2:$C1023, finCol,'Shipments by country'!$D$2:$D1023, doseCol,'Shipments by country'!$F$2:$F1023, price,IFERROR(VLOOKUP(vaccCol,'Vaccine pricing'!$A$2:$B1023,2,FALSE),0), totCost,SUMPRODUCT((ctryCol=ctry)*doseCol*price), gaviCost,SUMPRODUCT((ctryCol=ctry)*(finCol="Gavi")*doseCol*price), IF(totCost=0,"",gaviCost/totCost) )) | AN19: - | AP19: - | AQ19: ='Vaccine pricing'!$B$3*4/((S19/1000000)*'Vaccine efficacy curves'!$C$3) -> 69.538022 | AR19: ='Vaccine pricing'!$B$3*4/((T19/1000000)*'Vaccine efficacy curves'!$C$3) -> 91510.591 | AS19: =K19/5 -> 66246.8 | AT19: =AS19*4 -> 264987.2 | AU19: =AT19*'Vaccine pricing'!B3 -> 792311.73 | AV19: =K19*31/60 -> 171137.57 | AW19: =M19/AV19 -> 0 | AX19: =AV19-M19 -> 171137.57 | AY19: =1-AW19 -> 1 | AZ19: =AX19*4 -> 684550.27 | BA19: =AZ19*'Vaccine pricing'!B3 -> 2046805.3
A20: The Gambia | B20: =SUMIFS('Shipments by country'!F:F, 'Shipments by country'!B:B, A20, 'Shipments by country'!C:C, "RTS,S", 'Shipments by country'!G:G, "Delivered") -> 0 | C20: =SUMIFS('Shipments by country'!F:F, 'Shipments by country'!B:B, A20, 'Shipments by country'!C:C, "R21", 'Shipments by country'!G:G, "Delivered") -> 0 | D20: =B20+C20 -> 0 | E20: =SUMIFS('Shipments by country'!F:F, 'Shipments by country'!B:B, A20, 'Shipments by country'!C:C, "RTS,S") -> 0 | F20: =SUMIFS('Shipments by country'!F:F, 'Shipments by country'!B:B, A20, 'Shipments by country'!C:C, "R21") -> 0 | G20: =E20+F20 -> 0 | H20: Initial self-financing | I20: 0 | J20: 2697845 | K20: 383559 | L20: =K20*0.9 -> 345203.1 | M20: =G20/4 -> 0 | N20: =M20/L20 -> 0 | O20: =L20-M20 -> 345203.1 | P20: =1-N20 -> 1 | Q20: 236079 | R20: 632 | S20: =Q20*1000000/J20 -> 87506.51 | T20: =R20*1000000/J20 -> 234.26105 | U20: =IFERROR(__xludf.DUMMYFUNCTION("IFERROR( SUM( FILTER( 'Shipments by country'!$H$2:$H1023 * ( INDEX(Countries!$S$2:$S1023, MATCH('Shipments by country'!$B$2:$B1023, Countries!$A$2:$A1023, 0) ) / 1000000 ) * INDEX('Vaccine efficacy curves'!$C$2:$C1023, MATCH('Shipments by country'!$C$2:$C"&"1023, 'Vaccine efficacy curves'!$A$2:$A1023, 0) ), ('Shipments by country'!$E$2:$E1023 < NOW()) * ('Shipments by country'!$I$2:$I1023 > 0) * ('Shipments by country'!$B$2:$B1023 = $A20) ) ), 0 )"),0.0) -> 0 | V20: =SUMIF('Shipments by country'!$B:$B,$A20,'Shipments by country'!$K:$K) -> 0 | W20: =IFERROR(__xludf.DUMMYFUNCTION("IFERROR( SUM( FILTER( 'Shipments by country'!$H$2:$H1023 * ( INDEX(Countries!$T$2:$T1023, MATCH('Shipments by country'!$B$2:$B1023, Countries!$A$2:$A1023, 0) ) / 1000000 ) * INDEX('Vaccine efficacy curves'!$C$2:$C1023, MATCH('Shipments by country'!$C$2:$C"&"1023, 'Vaccine efficacy curves'!$A$2:$A1023, 0) ), ('Shipments by country'!$E$2:$E1023 < NOW()) * ('Shipments by country'!$I$2:$I1023 > 0) * ('Shipments by country'!$B$2:$B1023 = $A20) ) ), 0 )"),0.0) -> 0 | X20: =SUMIF('Shipments by country'!$B:$B,$A20,'Shipments by country'!$L:$L) -> 0 | Y20: =IFERROR(__xludf.DUMMYFUNCTION("IFERROR( SUM( FILTER( 'Shipments by country'!$H$2:$H1023 * ( INDEX(Countries!$S$2:$S1023, MATCH('Shipments by country'!$B$2:$B1023, Countries!$A$2:$A1023, 0) ) / 1000000 ) * INDEX('Vaccine efficacy curves'!$C$2:$C1023, MATCH('Shipments by country'!$C$2:$C"&"1023, 'Vaccine efficacy curves'!$A$2:$A1023, 0) ), ('Shipments by country'!$E$2:$E1023 < NOW()) * ('Shipments by country'!$I$2:$I1023 > 0.25) * ('Shipments by country'!$B$2:$B1023 = $A20) ) ), 0 )"),0.0) -> 0 | Z20: =SUMIF('Shipments by country'!$B:$B,$A20,'Shipments by country'!$M:$M) -> 0 | AA20: =IFERROR(__xludf.DUMMYFUNCTION("IFERROR( SUM( FILTER( 'Shipments by country'!$H$2:$H1023 * ( INDEX(Countries!$T$2:$T1023, MATCH('Shipments by country'!$B$2:$B1023, Countries!$A$2:$A1023, 0) ) / 1000000 ) * INDEX('Vaccine efficacy curves'!$C$2:$C1023, MATCH('Shipments by country'!$C$2:$C"&"1023, 'Vaccine efficacy curves'!$A$2:$A1023, 0) ), ('Shipments by country'!$E$2:$E1023 < NOW()) * ('Shipments by country'!$I$2:$I1023 > 0.25) * ('Shipments by country'!$B$2:$B1023 = $A20) ) ), 0 )"),0.0) -> 0 | AB20: =SUMIF('Shipments by country'!$B:$B,$A20,'Shipments by country'!$N:$N) -> 0 | AC20: =IFERROR(__xludf.DUMMYFUNCTION("IFERROR( SUM( FILTER( 'Shipments by country'!$H$2:$H1023 * ( INDEX(Countries!$S$2:$S1023, MATCH('Shipments by country'!$B$2:$B1023, Countries!$A$2:$A1023, 0) ) / 1000000 ) * 'Shipments by country'!$J$2:$J1023, ('Shipments by country'!$E$2:$E1023 < NOW()) "&"* ('Shipments by country'!$I$2:$I1023 > 0) * ('Shipments by country'!$B$2:$B1023 = $A20) ) ), 0 )"),0.0) -> 0 | AD20: =SUMIF('Shipments by country'!$B:$B,$A20,'Shipments by country'!$O:$O) -> 0 | AE20: =IFERROR(__xludf.DUMMYFUNCTION("IFERROR( SUM( FILTER( 'Shipments by country'!$H$2:$H1023 * ( INDEX(Countries!$T$2:$T1023, MATCH('Shipments by country'!$B$2:$B1023, Countries!$A$2:$A1023, 0) ) / 1000000 ) * 'Shipments by country'!$J$2:$J1023, ('Shipments by country'!$E$2:$E1023 < NOW()) "&"* ('Shipments by country'!$I$2:$I1023 > 0) * ('Shipments by country'!$B$2:$B1023 = $A20) ) ), 0 )"),0.0) -> 0 | AF20: =SUMIF('Shipments by country'!$B:$B,$A20,'Shipments by country'!$P:$P) -> 0 | AG20: =IFERROR(__xludf.DUMMYFUNCTION("IFERROR( SUM( FILTER( 'Shipments by country'!$H$2:$H1023 * INDEX(Countries!$S$2:$S1023, MATCH('Shipments by country'!$B$2:$B1023, Countries!$A$2:$A1023, 0) ) / 1000000 "&" * 'Shipments by country'!$J$2:$J1023, ( 'Shipments by country'!$E$2:$E1023 < NOW() ) * ( 'Shipments by country'!$I$2:$I1023 > 0.25 ) * ( 'Shipments by country'!$"&"B$2:$B1023 = $A20 ) ) ), 0 ) "),0.0) -> 0 | AH20: =SUMIF('Shipments by country'!$B:$B,$A20,'Shipments by country'!$Q:$Q) -> 0 | AI20: =IFERROR(__xludf.DUMMYFUNCTION("IFERROR( SUM( FILTER( 'Shipments by country'!$H$2:$H1023 * ( INDEX(Countries!$T$2:$T1023, MATCH('Shipments by country'!$B$2:$B1023, Countries!$A$2:$A1023, 0) ) / 1000000 ) * 'Shipments by country"&"'!$J$2:$J1023, ('Shipments by country'!$E$2:$E1023 < NOW()) * ('Shipments by country'!$I$2:$I1023 > 0.25) * ('Shipments by country'!$B$2:$B1023 = $A20) ) ), 0 ) "),0.0) -> 0 | AJ20: =SUMIF('Shipments by country'!$B:$B,$A20,'Shipments by country'!$R:$R) -> 0 | AK20: =O20*4 -> 1380812.4 | AL20: =AK20*'Vaccine pricing'!B3 -> 4128629.1 | AM20: =IF($A20="","", LET( ctry,$A20, ctryCol,'Shipments by country'!$B$2:$B1023, vaccCol,'Shipments by country'!$C$2:$C1023, finCol,'Shipments by country'!$D$2:$D1023, doseCol,'Shipments by country'!$F$2:$F1023, price,IFERROR(VLOOKUP(vaccCol,'Vaccine pricing'!$A$2:$B1023,2,FALSE),0), totCost,SUMPRODUCT((ctryCol=ctry)*doseCol*price), gaviCost,SUMPRODUCT((ctryCol=ctry)*(finCol="Gavi")*doseCol*price), IF(totCost=0,"",gaviCost/totCost) )) | AN20: 11 | AO20: 276162.48 | AP20: 813 | AQ20: ='Vaccine pricing'!$B$3*4/((S20/1000000)*'Vaccine efficacy curves'!$C$3) -> 182.23406 | AR20: ='Vaccine pricing'!$B$3*4/((T20/1000000)*'Vaccine efficacy curves'!$C$3) -> 68072.207 | AS20: =K20/5 -> 76711.8 | AT20: =AS20*4 -> 306847.2 | AU20: =AT20*'Vaccine pricing'!B3 -> 917473.13 | AV20: =K20*31/60 -> 198172.15 | AW20: =M20/AV20 -> 0 | AX20: =AV20-M20 -> 198172.15 | AY20: =1-AW20 -> 1 | AZ20: =AX20*4 -> 792688.6 | BA20: =AZ20*'Vaccine pricing'!B3 -> 2370138.9 | BB20: 158537.72
A21: Ghana | B21: =SUMIFS('Shipments by country'!F:F, 'Shipments by country'!B:B, A21, 'Shipments by country'!C:C, "RTS,S", 'Shipments by country'!G:G, "Delivered") -> 2000000 | C21: =SUMIFS('Shipments by country'!F:F, 'Shipments by country'!B:B, A21, 'Shipments by country'!C:C, "R21", 'Shipments by country'!G:G, "Delivered") -> 1222000 | D21: =B21+C21 -> 3222000 | E21: =SUMIFS('Shipments by country'!F:F, 'Shipments by country'!B:B, A21, 'Shipments by country'!C:C, "RTS,S") -> 2300000 | F21: =SUMIFS('Shipments by country'!F:F, 'Shipments by country'!B:B, A21, 'Shipments by country'!C:C, "R21") -> 1389200 | G21: =E21+F21 -> 3689200 | H21: Accelerated transition | I21: 28000000 | J21: 33787914 | K21: 4225767 | L21: =K21*0.9 -> 3803190.3 | M21: =G21/4 -> 922300 | N21: =M21/L21 -> 0.24250693 | O21: =L21-M21 -> 2880890.3 | P21: =1-N21 -> 0.75749307 | Q21: 6551533 | R21: 11464 | S21: =Q21*1000000/J21 -> 193901.67 | T21: =R21*1000000/J21 -> 339.29292 | U21: =IFERROR(__xludf.DUMMYFUNCTION("IFERROR( SUM( FILTER( 'Shipments by country'!$H$2:$H1023 * ( INDEX(Countries!$S$2:$S1023, MATCH('Shipments by country'!$B$2:$B1023, Countries!$A$2:$A1023, 0) ) / 1000000 ) * INDEX('Vaccine efficacy curves'!$C$2:$C1023, MATCH('Shipments by country'!$C$2:$C"&"1023, 'Vaccine efficacy curves'!$A$2:$A1023, 0) ), ('Shipments by country'!$E$2:$E1023 < NOW()) * ('Shipments by country'!$I$2:$I1023 > 0) * ('Shipments by country'!$B$2:$B1023 = $A21) ) ), 0 )"),174298.28047489037) -> 174298.28 | V21: =SUMIF('Shipments by country'!$B:$B,$A21,'Shipments by country'!$K:$K) -> 6104.243 | W21: =IFERROR(__xludf.DUMMYFUNCTION("IFERROR( SUM( FILTER( 'Shipments by country'!$H$2:$H1023 * ( INDEX(Countries!$T$2:$T1023, MATCH('Shipments by country'!$B$2:$B1023, Countries!$A$2:$A1023, 0) ) / 1000000 ) * INDEX('Vaccine efficacy curves'!$C$2:$C1023, MATCH('Shipments by country'!$C$2:$C"&"1023, 'Vaccine efficacy curves'!$A$2:$A1023, 0) ), ('Shipments by country'!$E$2:$E1023 < NOW()) * ('Shipments by country'!$I$2:$I1023 > 0) * ('Shipments by country'!$B$2:$B1023 = $A21) ) ), 0 )"),345.7546742398606) -> 345.75467 | X21: =SUMIF('Shipments by country'!$B:$B,$A21,'Shipments by country'!$L:$L) -> 103246.94 | Y21: =IFERROR(__xludf.DUMMYFUNCTION("IFERROR( SUM( FILTER( 'Shipments by country'!$H$2:$H1023 * ( INDEX(Countries!$S$2:$S1023, MATCH('Shipments by country'!$B$2:$B1023, Countries!$A$2:$A1023, 0) ) / 1000000 ) * INDEX('Vaccine efficacy curves'!$C$2:$C1023, MATCH('Shipments by country'!$C$2:$C"&"1023, 'Vaccine efficacy curves'!$A$2:$A1023, 0) ), ('Shipments by country'!$E$2:$E1023 < NOW()) * ('Shipments by country'!$I$2:$I1023 > 0.25) * ('Shipments by country'!$B$2:$B1023 = $A21) ) ), 0 )"),159451.74891825576) -> 159451.75 | Z21: =SUMIF('Shipments by country'!$B:$B,$A21,'Shipments by country'!$M:$M) -> 4627.3342 | AA21: =IFERROR(__xludf.DUMMYFUNCTION("IFERROR( SUM( FILTER( 'Shipments by country'!$H$2:$H1023 * ( INDEX(Countries!$T$2:$T1023, MATCH('Shipments by country'!$B$2:$B1023, Countries!$A$2:$A1023, 0) ) / 1000000 ) * INDEX('Vaccine efficacy curves'!$C$2:$C1023, MATCH('Shipments by country'!$C$2:$C"&"1023, 'Vaccine efficacy curves'!$A$2:$A1023, 0) ), ('Shipments by country'!$E$2:$E1023 < NOW()) * ('Shipments by country'!$I$2:$I1023 > 0.25) * ('Shipments by country'!$B$2:$B1023 = $A21) ) ), 0 )"),316.30367984123535) -> 316.30368 | AB21: =SUMIF('Shipments by country'!$B:$B,$A21,'Shipments by country'!$N:$N) -> 78266.559 | AC21: =IFERROR(__xludf.DUMMYFUNCTION("IFERROR( SUM( FILTER( 'Shipments by country'!$H$2:$H1023 * ( INDEX(Countries!$S$2:$S1023, MATCH('Shipments by country'!$B$2:$B1023, Countries!$A$2:$A1023, 0) ) / 1000000 ) * 'Shipments by country'!$J$2:$J1023, ('Shipments by country'!$E$2:$E1023 < NOW()) "&"* ('Shipments by country'!$I$2:$I1023 > 0) * ('Shipments by country'!$B$2:$B1023 = $A21) ) ), 0 )"),188243.6778085504) -> 188243.68 | AD21: =SUMIF('Shipments by country'!$B:$B,$A21,'Shipments by country'!$O:$O) -> 5926.6059 | AE21: =IFERROR(__xludf.DUMMYFUNCTION("IFERROR( SUM( FILTER( 'Shipments by country'!$H$2:$H1023 * ( INDEX(Countries!$T$2:$T1023, MATCH('Shipments by country'!$B$2:$B1023, Countries!$A$2:$A1023, 0) ) / 1000000 ) * 'Shipments by country'!$J$2:$J1023, ('Shipments by country'!$E$2:$E1023 < NOW()) "&"* ('Shipments by country'!$I$2:$I1023 > 0) * ('Shipments by country'!$B$2:$B1023 = $A21) ) ), 0 )"),373.41809294432477) -> 373.41809 | AF21: =SUMIF('Shipments by country'!$B:$B,$A21,'Shipments by country'!$P:$P) -> 100242.39 | AG21: =IFERROR(__xludf.DUMMYFUNCTION("IFERROR( SUM( FILTER( 'Shipments by country'!$H$2:$H1023 * INDEX(Countries!$S$2:$S1023, MATCH('Shipments by country'!$B$2:$B1023, Countries!$A$2:$A1023, 0) ) / 1000000 "&" * 'Shipments by country'!$J$2:$J1023, ( 'Shipments by country'!$E$2:$E1023 < NOW() ) * ( 'Shipments by country'!$I$2:$I1023 > 0.25 ) * ( 'Shipments by country'!$"&"B$2:$B1023 = $A21 ) ) ), 0 ) "),173397.14625191578) -> 173397.15 | AH21: =SUMIF('Shipments by country'!$B:$B,$A21,'Shipments by country'!$Q:$Q) -> 23670.665 | AI21: =IFERROR(__xludf.DUMMYFUNCTION("IFERROR( SUM( FILTER( 'Shipments by country'!$H$2:$H1023 * ( INDEX(Countries!$T$2:$T1023, MATCH('Shipments by country'!$B$2:$B1023, Countries!$A$2:$A1023, 0) ) / 1000000 ) * 'Shipments by country"&"'!$J$2:$J1023, ('Shipments by country'!$E$2:$E1023 < NOW()) * ('Shipments by country'!$I$2:$I1023 > 0.25) * ('Shipments by country'!$B$2:$B1023 = $A21) ) ), 0 ) "),343.9670985456995) -> 343.9671 | AJ21: =SUMIF('Shipments by country'!$B:$B,$A21,'Shipments by country'!$R:$R) -> 41.41939 | AK21: =O21*4 -> 11523561 | AL21: =AK21*'Vaccine pricing'!B3 -> 34455448 | AM21: =IF($A21="","", LET( ctry,$A21, ctryCol,'Shipments by country'!$B$2:$B1023, vaccCol,'Shipments by country'!$C$2:$C1023, finCol,'Shipments by country'!$D$2:$D1023, doseCol,'Shipments by country'!$F$2:$F1023, price,IFERROR(VLOOKUP(vaccCol,'Vaccine pricing'!$A$2:$B1023,2,FALSE),0), totCost,SUMPRODUCT((ctryCol=ctry)*doseCol*price), gaviCost,SUMPRODUCT((ctryCol=ctry)*(finCol="Gavi")*doseCol*price), IF(totCost=0,"",gaviCost/totCost) )) -> 0.80456468 | AN21: 4 | AO21: 17227724 | AP21: 2350 | AQ21: ='Vaccine pricing'!$B$3*4/((S21/1000000)*'Vaccine efficacy curves'!$C$3) -> 82.240996 | AR21: ='Vaccine pricing'!$B$3*4/((T21/1000000)*'Vaccine efficacy curves'!$C$3) -> 46999.704 | AS21: =K21/5 -> 845153.4 | AT21: =AS21*4 -> 3380613.6 | AU21: =AT21*'Vaccine pricing'!B3 -> 10108035 | AV21: =K21*31/60 -> 2183313 | AW21: =M21/AV21 -> 0.42243142 | AX21: =AV21-M21 -> 1261012.9 | AY21: =1-AW21 -> 0.57756858 | AZ21: =AX21*4 -> 5044051.8 | BA21: =AZ21*'Vaccine pricing'!B3 -> 15081715 | BB21: 7540857.4
A22: Guinea | B22: =SUMIFS('Shipments by country'!F:F, 'Shipments by country'!B:B, A22, 'Shipments by country'!C:C, "RTS,S", 'Shipments by country'!G:G, "Delivered") -> 568300 | C22: =SUMIFS('Shipments by country'!F:F, 'Shipments by country'!B:B, A22, 'Shipments by country'!C:C, "R21", 'Shipments by country'!G:G, "Delivered") -> 0 | D22: =B22+C22 -> 568300 | E22: =SUMIFS('Shipments by country'!F:F, 'Shipments by country'!B:B, A22, 'Shipments by country'!C:C, "RTS,S") -> 579000 | F22: =SUMIFS('Shipments by country'!F:F, 'Shipments by country'!B:B, A22, 'Shipments by country'!C:C, "R21") -> 0 | G22: =E22+F22 -> 579000 | H22: Preparatory transition | I22: 17000000 | J22: 14405468 | K22: 2194570 | L22: =K22*0.9 -> 1975113 | M22: =G22/4 -> 144750 | N22: =M22/L22 -> 0.073286946 | O22: =L22-M22 -> 1830363 | P22: =1-N22 -> 0.92671305 | Q22: 4433772 | R22: 10188 | S22: =Q22*1000000/J22 -> 307783.96 | T22: =R22*1000000/J22 -> 707.23145 | U22: =IFERROR(__xludf.DUMMYFUNCTION("IFERROR( SUM( FILTER( 'Shipments by country'!$H$2:$H1023 * ( INDEX(Countries!$S$2:$S1023, MATCH('Shipments by country'!$B$2:$B1023, Countries!$A$2:$A1023, 0) ) / 1000000 ) * INDEX('Vaccine efficacy curves'!$C$2:$C1023, MATCH('Shipments by country'!$C$2:$C"&"1023, 'Vaccine efficacy curves'!$A$2:$A1023, 0) ), ('Shipments by country'!$E$2:$E1023 < NOW()) * ('Shipments by country'!$I$2:$I1023 > 0) * ('Shipments by country'!$B$2:$B1023 = $A22) ) ), 0 )"),28124.279612118175) -> 28124.28 | V22: =SUMIF('Shipments by country'!$B:$B,$A22,'Shipments by country'!$K:$K) -> 510.7414 | W22: =IFERROR(__xludf.DUMMYFUNCTION("IFERROR( SUM( FILTER( 'Shipments by country'!$H$2:$H1023 * ( INDEX(Countries!$T$2:$T1023, MATCH('Shipments by country'!$B$2:$B1023, Countries!$A$2:$A1023, 0) ) / 1000000 ) * INDEX('Vaccine efficacy curves'!$C$2:$C1023, MATCH('Shipments by country'!$C$2:$C"&"1023, 'Vaccine efficacy curves'!$A$2:$A1023, 0) ), ('Shipments by country'!$E$2:$E1023 < NOW()) * ('Shipments by country'!$I$2:$I1023 > 0) * ('Shipments by country'!$B$2:$B1023 = $A22) ) ), 0 )"),55.79000038912913) -> 55.79 | X22: =SUMIF('Shipments by country'!$B:$B,$A22,'Shipments by country'!$L:$L) -> 15429.722 | Y22: =IFERROR(__xludf.DUMMYFUNCTION("IFERROR( SUM( FILTER( 'Shipments by country'!$H$2:$H1023 * ( INDEX(Countries!$S$2:$S1023, MATCH('Shipments by country'!$B$2:$B1023, Countries!$A$2:$A1023, 0) ) / 1000000 ) * INDEX('Vaccine efficacy curves'!$C$2:$C1023, MATCH('Shipments by country'!$C$2:$C"&"1023, 'Vaccine efficacy curves'!$A$2:$A1023, 0) ), ('Shipments by country'!$E$2:$E1023 < NOW()) * ('Shipments by country'!$I$2:$I1023 > 0.25) * ('Shipments by country'!$B$2:$B1023 = $A22) ) ), 0 )"),28124.279612118175) -> 28124.28 | Z22: =SUMIF('Shipments by country'!$B:$B,$A22,'Shipments by country'!$M:$M) -> 308.09699 | AA22: =IFERROR(__xludf.DUMMYFUNCTION("IFERROR( SUM( FILTER( 'Shipments by country'!$H$2:$H1023 * ( INDEX(Countries!$T$2:$T1023, MATCH('Shipments by country'!$B$2:$B1023, Countries!$A$2:$A1023, 0) ) / 1000000 ) * INDEX('Vaccine efficacy curves'!$C$2:$C1023, MATCH('Shipments by country'!$C$2:$C"&"1023, 'Vaccine efficacy curves'!$A$2:$A1023, 0) ), ('Shipments by country'!$E$2:$E1023 < NOW()) * ('Shipments by country'!$I$2:$I1023 > 0.25) * ('Shipments by country'!$B$2:$B1023 = $A22) ) ), 0 )"),55.79000038912913) -> 55.79 | AB22: =SUMIF('Shipments by country'!$B:$B,$A22,'Shipments by country'!$N:$N) -> 9307.7455 | AC22: =IFERROR(__xludf.DUMMYFUNCTION("IFERROR( SUM( FILTER( 'Shipments by country'!$H$2:$H1023 * ( INDEX(Countries!$S$2:$S1023, MATCH('Shipments by country'!$B$2:$B1023, Countries!$A$2:$A1023, 0) ) / 1000000 ) * 'Shipments by country'!$J$2:$J1023, ('Shipments by country'!$E$2:$E1023 < NOW()) "&"* ('Shipments by country'!$I$2:$I1023 > 0) * ('Shipments by country'!$B$2:$B1023 = $A22) ) ), 0 )"),28124.279612118175) -> 28124.28 | AD22: =SUMIF('Shipments by country'!$B:$B,$A22,'Shipments by country'!$O:$O) -> 510.7414 | AE22: =IFERROR(__xludf.DUMMYFUNCTION("IFERROR( SUM( FILTER( 'Shipments by country'!$H$2:$H1023 * ( INDEX(Countries!$T$2:$T1023, MATCH('Shipments by country'!$B$2:$B1023, Countries!$A$2:$A1023, 0) ) / 1000000 ) * 'Shipments by country'!$J$2:$J1023, ('Shipments by country'!$E$2:$E1023 < NOW()) "&"* ('Shipments by country'!$I$2:$I1023 > 0) * ('Shipments by country'!$B$2:$B1023 = $A22) ) ), 0 )"),55.79000038912913) -> 55.79 | AF22: =SUMIF('Shipments by country'!$B:$B,$A22,'Shipments by country'!$P:$P) -> 15429.722 | AG22: =IFERROR(__xludf.DUMMYFUNCTION("IFERROR( SUM( FILTER( 'Shipments by country'!$H$2:$H1023 * INDEX(Countries!$S$2:$S1023, MATCH('Shipments by country'!$B$2:$B1023, Countries!$A$2:$A1023, 0) ) / 1000000 "&" * 'Shipments by country'!$J$2:$J1023, ( 'Shipments by country'!$E$2:$E1023 < NOW() ) * ( 'Shipments by country'!$I$2:$I1023 > 0.25 ) * ( 'Shipments by country'!$"&"B$2:$B1023 = $A22 ) ) ), 0 ) "),28124.279612118175) -> 28124.28 | AH22: =SUMIF('Shipments by country'!$B:$B,$A22,'Shipments by country'!$Q:$Q) -> 6121.9769 | AI22: =IFERROR(__xludf.DUMMYFUNCTION("IFERROR( SUM( FILTER( 'Shipments by country'!$H$2:$H1023 * ( INDEX(Countries!$T$2:$T1023, MATCH('Shipments by country'!$B$2:$B1023, Countries!$A$2:$A1023, 0) ) / 1000000 ) * 'Shipments by country"&"'!$J$2:$J1023, ('Shipments by country'!$E$2:$E1023 < NOW()) * ('Shipments by country'!$I$2:$I1023 > 0.25) * ('Shipments by country'!$B$2:$B1023 = $A22) ) ), 0 ) "),55.79000038912913) -> 55.79 | AJ22: =SUMIF('Shipments by country'!$B:$B,$A22,'Shipments by country'!$R:$R) -> 14.067187 | AK22: =O22*4 -> 7321452 | AL22: =AK22*'Vaccine pricing'!B3 -> 21891141 | AM22: =IF($A22="","", LET( ctry,$A22, ctryCol,'Shipments by country'!$B$2:$B1023, vaccCol,'Shipments by country'!$C$2:$C1023, finCol,'Shipments by country'!$D$2:$D1023, doseCol,'Shipments by country'!$F$2:$F1023, price,IFERROR(VLOOKUP(vaccCol,'Vaccine pricing'!$A$2:$B1023,2,FALSE),0), totCost,SUMPRODUCT((ctryCol=ctry)*doseCol*price), gaviCost,SUMPRODUCT((ctryCol=ctry)*(finCol="Gavi")*doseCol*price), IF(totCost=0,"",gaviCost/totCost) )) -> 0.98151986 | AN22: 2 | AO22: 1683934 | AP22: 1183 | AQ22: ='Vaccine pricing'!$B$3*4/((S22/1000000)*'Vaccine efficacy curves'!$C$3) -> 51.811234 | AR22: ='Vaccine pricing'!$B$3*4/((T22/1000000)*'Vaccine efficacy curves'!$C$3) -> 22548.017 | AS22: =K22/5 -> 438914 | AT22: =AS22*4 -> 1755656 | AU22: =AT22*'Vaccine pricing'!B3 -> 5249411.4 | AV22: =K22*31/60 -> 1133861.2 | AW22: =M22/AV22 -> 0.12766113 | AX22: =AV22-M22 -> 989111.17 | AY22: =1-AW22 -> 0.87233887 | AZ22: =AX22*4 -> 3956444.7 | BA22: =AZ22*'Vaccine pricing'!B3 -> 11829770 | BB22: 909982.27
A23: Guinea-Bissau | B23: =SUMIFS('Shipments by country'!F:F, 'Shipments by country'!B:B, A23, 'Shipments by country'!C:C, "RTS,S", 'Shipments by country'!G:G, "Delivered") -> 110050 | C23: =SUMIFS('Shipments by country'!F:F, 'Shipments by country'!B:B, A23, 'Shipments by country'!C:C, "R21", 'Shipments by country'!G:G, "Delivered") -> 0 | D23: =B23+C23 -> 110050 | E23: =SUMIFS('Shipments by country'!F:F, 'Shipments by country'!B:B, A23, 'Shipments by country'!C:C, "RTS,S") -> 112050 | F23: =SUMIFS('Shipments by country'!F:F, 'Shipments by country'!B:B, A23, 'Shipments by country'!C:C, "R21") -> 0 | G23: =E23+F23 -> 112050 | H23: Initial self-financing | I23: 0 | J23: 2153339 | K23: 297297 | L23: =K23*0.9 -> 267567.3 | M23: =G23/4 -> 28012.5 | N23: =M23/L23 -> 0.10469329 | O23: =L23-M23 -> 239554.8 | P23: =1-N23 -> 0.89530671 | Q23: 223937 | R23: 885 | S23: =Q23*1000000/J23 -> 103995.24 | T23: =R23*1000000/J23 -> 410.98963 | U23: =IFERROR(__xludf.DUMMYFUNCTION("IFERROR( SUM( FILTER( 'Shipments by country'!$H$2:$H1023 * ( INDEX(Countries!$S$2:$S1023, MATCH('Shipments by country'!$B$2:$B1023, Countries!$A$2:$A1023, 0) ) / 1000000 ) * INDEX('Vaccine efficacy curves'!$C$2:$C1023, MATCH('Shipments by country'!$C$2:$C"&"1023, 'Vaccine efficacy curves'!$A$2:$A1023, 0) ), ('Shipments by country'!$E$2:$E1023 < NOW()) * ('Shipments by country'!$I$2:$I1023 > 0) * ('Shipments by country'!$B$2:$B1023 = $A23) ) ), 0 )"),5446.202659358798) -> 5446.2027 | V23: =SUMIF('Shipments by country'!$B:$B,$A23,'Shipments by country'!$K:$K) -> 3.9373097 | W23: =IFERROR(__xludf.DUMMYFUNCTION("IFERROR( SUM( FILTER( 'Shipments by country'!$H$2:$H1023 * ( INDEX(Countries!$T$2:$T1023, MATCH('Shipments by country'!$B$2:$B1023, Countries!$A$2:$A1023, 0) ) / 1000000 ) * INDEX('Vaccine efficacy curves'!$C$2:$C1023, MATCH('Shipments by country'!$C$2:$C"&"1023, 'Vaccine efficacy curves'!$A$2:$A1023, 0) ), ('Shipments by country'!$E$2:$E1023 < NOW()) * ('Shipments by country'!$I$2:$I1023 > 0) * ('Shipments by country'!$B$2:$B1023 = $A23) ) ), 0 )"),10.803606445229034) -> 10.803606 | X23: =SUMIF('Shipments by country'!$B:$B,$A23,'Shipments by country'!$L:$L) -> 462.66832 | Y23: =IFERROR(__xludf.DUMMYFUNCTION("IFERROR( SUM( FILTER( 'Shipments by country'!$H$2:$H1023 * ( INDEX(Countries!$S$2:$S1023, MATCH('Shipments by country'!$B$2:$B1023, Countries!$A$2:$A1023, 0) ) / 1000000 ) * INDEX('Vaccine efficacy curves'!$C$2:$C1023, MATCH('Shipments by country'!$C$2:$C"&"1023, 'Vaccine efficacy curves'!$A$2:$A1023, 0) ), ('Shipments by country'!$E$2:$E1023 < NOW()) * ('Shipments by country'!$I$2:$I1023 > 0.25) * ('Shipments by country'!$B$2:$B1023 = $A23) ) ), 0 )"),5446.202659358798) -> 5446.2027 | Z23: =SUMIF('Shipments by country'!$B:$B,$A23,'Shipments by country'!$M:$M) -> 0.52851098 | AA23: =IFERROR(__xludf.DUMMYFUNCTION("IFERROR( SUM( FILTER( 'Shipments by country'!$H$2:$H1023 * ( INDEX(Countries!$T$2:$T1023, MATCH('Shipments by country'!$B$2:$B1023, Countries!$A$2:$A1023, 0) ) / 1000000 ) * INDEX('Vaccine efficacy curves'!$C$2:$C1023, MATCH('Shipments by country'!$C$2:$C"&"1023, 'Vaccine efficacy curves'!$A$2:$A1023, 0) ), ('Shipments by country'!$E$2:$E1023 < NOW()) * ('Shipments by country'!$I$2:$I1023 > 0.25) * ('Shipments by country'!$B$2:$B1023 = $A23) ) ), 0 )"),10.803606445229034) -> 10.803606 | AB23: =SUMIF('Shipments by country'!$B:$B,$A23,'Shipments by country'!$N:$N) -> 62.10466 | AC23: =IFERROR(__xludf.DUMMYFUNCTION("IFERROR( SUM( FILTER( 'Shipments by country'!$H$2:$H1023 * ( INDEX(Countries!$S$2:$S1023, MATCH('Shipments by country'!$B$2:$B1023, Countries!$A$2:$A1023, 0) ) / 1000000 ) * 'Shipments by country'!$J$2:$J1023, ('Shipments by country'!$E$2:$E1023 < NOW()) "&"* ('Shipments by country'!$I$2:$I1023 > 0) * ('Shipments by country'!$B$2:$B1023 = $A23) ) ), 0 )"),5446.202659358798) -> 5446.2027 | AD23: =SUMIF('Shipments by country'!$B:$B,$A23,'Shipments by country'!$O:$O) -> 3.9373097 | AE23: =IFERROR(__xludf.DUMMYFUNCTION("IFERROR( SUM( FILTER( 'Shipments by country'!$H$2:$H1023 * ( INDEX(Countries!$T$2:$T1023, MATCH('Shipments by country'!$B$2:$B1023, Countries!$A$2:$A1023, 0) ) / 1000000 ) * 'Shipments by country'!$J$2:$J1023, ('Shipments by country'!$E$2:$E1023 < NOW()) "&"* ('Shipments by country'!$I$2:$I1023 > 0) * ('Shipments by country'!$B$2:$B1023 = $A23) ) ), 0 )"),10.803606445229034) -> 10.803606 | AF23: =SUMIF('Shipments by country'!$B:$B,$A23,'Shipments by country'!$P:$P) -> 462.66832 | AG23: =IFERROR(__xludf.DUMMYFUNCTION("IFERROR( SUM( FILTER( 'Shipments by country'!$H$2:$H1023 * INDEX(Countries!$S$2:$S1023, MATCH('Shipments by country'!$B$2:$B1023, Countries!$A$2:$A1023, 0) ) / 1000000 "&" * 'Shipments by country'!$J$2:$J1023, ( 'Shipments by country'!$E$2:$E1023 < NOW() ) * ( 'Shipments by country'!$I$2:$I1023 > 0.25 ) * ( 'Shipments by country'!$"&"B$2:$B1023 = $A23 ) ) ), 0 ) "),5446.202659358798) -> 5446.2027 | AH23: =SUMIF('Shipments by country'!$B:$B,$A23,'Shipments by country'!$Q:$Q) -> 400.56365 | AI23: =IFERROR(__xludf.DUMMYFUNCTION("IFERROR( SUM( FILTER( 'Shipments by country'!$H$2:$H1023 * ( INDEX(Countries!$T$2:$T1023, MATCH('Shipments by country'!$B$2:$B1023, Countries!$A$2:$A1023, 0) ) / 1000000 ) * 'Shipments by country"&"'!$J$2:$J1023, ('Shipments by country'!$E$2:$E1023 < NOW()) * ('Shipments by country'!$I$2:$I1023 > 0.25) * ('Shipments by country'!$B$2:$B1023 = $A23) ) ), 0 ) "),10.803606445229034) -> 10.803606 | AJ23: =SUMIF('Shipments by country'!$B:$B,$A23,'Shipments by country'!$R:$R) -> 1.5830293 | AK23: =O23*4 -> 958219.2 | AL23: =AK23*'Vaccine pricing'!B3 -> 2865075.4 | AM23: =IF($A23="","", LET( ctry,$A23, ctryCol,'Shipments by country'!$B$2:$B1023, vaccCol,'Shipments by country'!$C$2:$C1023, finCol,'Shipments by country'!$D$2:$D1023, doseCol,'Shipments by country'!$F$2:$F1023, price,IFERROR(VLOOKUP(vaccCol,'Vaccine pricing'!$A$2:$B1023,2,FALSE),0), totCost,SUMPRODUCT((ctryCol=ctry)*doseCol*price), gaviCost,SUMPRODUCT((ctryCol=ctry)*(finCol="Gavi")*doseCol*price), IF(totCost=0,"",gaviCost/totCost) )) -> 0.98215083 | AN23: 11 | AO23: 191643.84 | AP23: 833 | AQ23: ='Vaccine pricing'!$B$3*4/((S23/1000000)*'Vaccine efficacy curves'!$C$3) -> 153.34036 | AR23: ='Vaccine pricing'!$B$3*4/((T23/1000000)*'Vaccine efficacy curves'!$C$3) -> 38800.655 | AS23: =K23/5 -> 59459.4 | AT23: =AS23*4 -> 237837.6 | AU23: =AT23*'Vaccine pricing'!B3 -> 711134.42 | AV23: =K23*31/60 -> 153603.45 | AW23: =M23/AV23 -> 0.18236895 | AX23: =AV23-M23 -> 125590.95 | AY23: =1-AW23 -> 0.81763105 | AZ23: =AX23*4 -> 502363.8 | BA23: =AZ23*'Vaccine pricing'!B3 -> 1502067.8 | BB23: 100472.76
A24: Kenya | B24: =SUMIFS('Shipments by country'!F:F, 'Shipments by country'!B:B, A24, 'Shipments by country'!C:C, "RTS,S", 'Shipments by country'!G:G, "Delivered") -> 2000500 | C24: =SUMIFS('Shipments by country'!F:F, 'Shipments by country'!B:B, A24, 'Shipments by country'!C:C, "R21", 'Shipments by country'!G:G, "Delivered") -> 0 | D24: =B24+C24 -> 2000500 | E24: =SUMIFS('Shipments by country'!F:F, 'Shipments by country'!B:B, A24, 'Shipments by country'!C:C, "RTS,S") -> 2000500 | F24: =SUMIFS('Shipments by country'!F:F, 'Shipments by country'!B:B, A24, 'Shipments by country'!C:C, "R21") -> 0 | G24: =E24+F24 -> 2000500 | H24: Accelerated transition | I24: 33500000 | J24: 55339002 | K24: 7036696 | L24: =K24*0.9 -> 6333026.4 | M24: =G24/4 -> 500125 | N24: =M24/L24 -> 0.078970932 | O24: =L24-M24 -> 5832901.4 | P24: =1-N24 -> 0.92102907 | Q24: 3294221 | R24: 11478 | S24: =Q24*1000000/J24 -> 59528.016 | T24: =R24*1000000/J24 -> 207.41249 | U24: =IFERROR(__xludf.DUMMYFUNCTION("IFERROR( SUM( FILTER( 'Shipments by country'!$H$2:$H1023 * ( INDEX(Countries!$S$2:$S1023, MATCH('Shipments by country'!$B$2:$B1023, Countries!$A$2:$A1023, 0) ) / 1000000 ) * INDEX('Vaccine efficacy curves'!$C$2:$C1023, MATCH('Shipments by country'!$C$2:$C"&"1023, 'Vaccine efficacy curves'!$A$2:$A1023, 0) ), ('Shipments by country'!$E$2:$E1023 < NOW()) * ('Shipments by country'!$I$2:$I1023 > 0) * ('Shipments by country'!$B$2:$B1023 = $A24) ) ), 0 )"),99001.62126349185) -> 99001.621 | V24: =SUMIF('Shipments by country'!$B:$B,$A24,'Shipments by country'!$K:$K) -> 3612.1674 | W24: =IFERROR(__xludf.DUMMYFUNCTION("IFERROR( SUM( FILTER( 'Shipments by country'!$H$2:$H1023 * ( INDEX(Countries!$T$2:$T1023, MATCH('Shipments by country'!$B$2:$B1023, Countries!$A$2:$A1023, 0) ) / 1000000 ) * INDEX('Vaccine efficacy curves'!$C$2:$C1023, MATCH('Shipments by country'!$C$2:$C"&"1023, 'Vaccine efficacy curves'!$A$2:$A1023, 0) ), ('Shipments by country'!$E$2:$E1023 < NOW()) * ('Shipments by country'!$I$2:$I1023 > 0) * ('Shipments by country'!$B$2:$B1023 = $A24) ) ), 0 )"),196.38904764816616) -> 196.38905 | X24: =SUMIF('Shipments by country'!$B:$B,$A24,'Shipments by country'!$L:$L) -> 18733.678 | Y24: =IFERROR(__xludf.DUMMYFUNCTION("IFERROR( SUM( FILTER( 'Shipments by country'!$H$2:$H1023 * ( INDEX(Countries!$S$2:$S1023, MATCH('Shipments by country'!$B$2:$B1023, Countries!$A$2:$A1023, 0) ) / 1000000 ) * INDEX('Vaccine efficacy curves'!$C$2:$C1023, MATCH('Shipments by country'!$C$2:$C"&"1023, 'Vaccine efficacy curves'!$A$2:$A1023, 0) ), ('Shipments by country'!$E$2:$E1023 < NOW()) * ('Shipments by country'!$I$2:$I1023 > 0.25) * ('Shipments by country'!$B$2:$B1023 = $A24) ) ), 0 )"),88866.38905416262) -> 88866.389 | Z24: =SUMIF('Shipments by country'!$B:$B,$A24,'Shipments by country'!$M:$M) -> 2818.2759 | AA24: =IFERROR(__xludf.DUMMYFUNCTION("IFERROR( SUM( FILTER( 'Shipments by country'!$H$2:$H1023 * ( INDEX(Countries!$T$2:$T1023, MATCH('Shipments by country'!$B$2:$B1023, Countries!$A$2:$A1023, 0) ) / 1000000 ) * INDEX('Vaccine efficacy curves'!$C$2:$C1023, MATCH('Shipments by country'!$C$2:$C"&"1023, 'Vaccine efficacy curves'!$A$2:$A1023, 0) ), ('Shipments by country'!$E$2:$E1023 < NOW()) * ('Shipments by country'!$I$2:$I1023 > 0.25) * ('Shipments by country'!$B$2:$B1023 = $A24) ) ), 0 )"),176.28383547203796) -> 176.28384 | AB24: =SUMIF('Shipments by country'!$B:$B,$A24,'Shipments by country'!$N:$N) -> 14616.342 | AC24: =IFERROR(__xludf.DUMMYFUNCTION("IFERROR( SUM( FILTER( 'Shipments by country'!$H$2:$H1023 * ( INDEX(Countries!$S$2:$S1023, MATCH('Shipments by country'!$B$2:$B1023, Countries!$A$2:$A1023, 0) ) / 1000000 ) * 'Shipments by country'!$J$2:$J1023, ('Shipments by country'!$E$2:$E1023 < NOW()) "&"* ('Shipments by country'!$I$2:$I1023 > 0) * ('Shipments by country'!$B$2:$B1023 = $A24) ) ), 0 )"),95540.26564401436) -> 95540.266 | AD24: =SUMIF('Shipments by country'!$B:$B,$A24,'Shipments by country'!$O:$O) -> 3518.5071 | AE24: =IFERROR(__xludf.DUMMYFUNCTION("IFERROR( SUM( FILTER( 'Shipments by country'!$H$2:$H1023 * ( INDEX(Countries!$T$2:$T1023, MATCH('Shipments by country'!$B$2:$B1023, Countries!$A$2:$A1023, 0) ) / 1000000 ) * 'Shipments by country'!$J$2:$J1023, ('Shipments by country'!$E$2:$E1023 < NOW()) "&"* ('Shipments by country'!$I$2:$I1023 > 0) * ('Shipments by country'!$B$2:$B1023 = $A24) ) ), 0 )"),189.5227728841236) -> 189.52277 | AF24: =SUMIF('Shipments by country'!$B:$B,$A24,'Shipments by country'!$P:$P) -> 18247.931 | AG24: =IFERROR(__xludf.DUMMYFUNCTION("IFERROR( SUM( FILTER( 'Shipments by country'!$H$2:$H1023 * INDEX(Countries!$S$2:$S1023, MATCH('Shipments by country'!$B$2:$B1023, Countries!$A$2:$A1023, 0) ) / 1000000 "&" * 'Shipments by country'!$J$2:$J1023, ( 'Shipments by country'!$E$2:$E1023 < NOW() ) * ( 'Shipments by country'!$I$2:$I1023 > 0.25 ) * ( 'Shipments by country'!$"&"B$2:$B1023 = $A24 ) ) ), 0 ) "),85405.03343468513) -> 85405.033 | AH24: =SUMIF('Shipments by country'!$B:$B,$A24,'Shipments by country'!$Q:$Q) -> 3931.7664 | AI24: =IFERROR(__xludf.DUMMYFUNCTION("IFERROR( SUM( FILTER( 'Shipments by country'!$H$2:$H1023 * ( INDEX(Countries!$T$2:$T1023, MATCH('Shipments by country'!$B$2:$B1023, Countries!$A$2:$A1023, 0) ) / 1000000 ) * 'Shipments by country"&"'!$J$2:$J1023, ('Shipments by country'!$E$2:$E1023 < NOW()) * ('Shipments by country'!$I$2:$I1023 > 0.25) * ('Shipments by country'!$B$2:$B1023 = $A24) ) ), 0 ) "),169.41756070799542) -> 169.41756 | AJ24: =SUMIF('Shipments by country'!$B:$B,$A24,'Shipments by country'!$R:$R) -> 13.699389 | AK24: =O24*4 -> 23331606 | AL24: =AK24*'Vaccine pricing'!B3 -> 69761501 | AM24: =IF($A24="","", LET( ctry,$A24, ctryCol,'Shipments by country'!$B$2:$B1023, vaccCol,'Shipments by country'!$C$2:$C1023, finCol,'Shipments by country'!$D$2:$D1023, doseCol,'Shipments by country'!$F$2:$F1023, price,IFERROR(VLOOKUP(vaccCol,'Vaccine pricing'!$A$2:$B1023,2,FALSE),0), totCost,SUMPRODUCT((ctryCol=ctry)*doseCol*price), gaviCost,SUMPRODUCT((ctryCol=ctry)*(finCol="Gavi")*doseCol*price), IF(totCost=0,"",gaviCost/totCost) )) -> 0.89762559 | AN24: 4 | AO24: 34880750 | AP24: 2097 | AQ24: ='Vaccine pricing'!$B$3*4/((S24/1000000)*'Vaccine efficacy curves'!$C$3) -> 267.88507 | AR24: ='Vaccine pricing'!$B$3*4/((T24/1000000)*'Vaccine efficacy curves'!$C$3) -> 76883.832 | AS24: =K24/5 -> 1407339.2 | AT24: =AS24*4 -> 5629356.8 | AU24: =AT24*'Vaccine pricing'!B3 -> 16831777 | AV24: =K24*31/60 -> 3635626.3 | AW24: =M24/AV24 -> 0.13756227 | AX24: =AV24-M24 -> 3135501.3 | AY24: =1-AW24 -> 0.86243773 | AZ24: =AX24*4 -> 12542005 | BA24: =AZ24*'Vaccine pricing'!B3 -> 37500595 | BB24: 18750298
A25: Liberia | B25: =SUMIFS('Shipments by country'!F:F, 'Shipments by country'!B:B, A25, 'Shipments by country'!C:C, "RTS,S", 'Shipments by country'!G:G, "Delivered") -> 371900 | C25: =SUMIFS('Shipments by country'!F:F, 'Shipments by country'!B:B, A25, 'Shipments by country'!C:C, "R21", 'Shipments by country'!G:G, "Delivered") -> 0 | D25: =B25+C25 -> 371900 | E25: =SUMIFS('Shipments by country'!F:F, 'Shipments by country'!B:B, A25, 'Shipments by country'!C:C, "RTS,S") -> 380150 | F25: =SUMIFS('Shipments by country'!F:F, 'Shipments by country'!B:B, A25, 'Shipments by country'!C:C, "R21") -> 0 | G25: =E25+F25 -> 380150 | H25: Initial self-financing | I25: 15000000 | J25: 5493031 | K25: 772932 | L25: =K25*0.9 -> 695638.8 | M25: =G25/4 -> 95037.5 | N25: =M25/L25 -> 0.13661903 | O25: =L25-M25 -> 600601.3 | P25: =1-N25 -> 0.86338097 | Q25: 1026103 | R25: 3541 | S25: =Q25*1000000/J25 -> 186800.88 | T25: =R25*1000000/J25 -> 644.63499 | U25: =IFERROR(__xludf.DUMMYFUNCTION("IFERROR( SUM( FILTER( 'Shipments by country'!$H$2:$H1023 * ( INDEX(Countries!$S$2:$S1023, MATCH('Shipments by country'!$B$2:$B1023, Countries!$A$2:$A1023, 0) ) / 1000000 ) * INDEX('Vaccine efficacy curves'!$C$2:$C1023, MATCH('Shipments by country'!$C$2:$C"&"1023, 'Vaccine efficacy curves'!$A$2:$A1023, 0) ), ('Shipments by country'!$E$2:$E1023 < NOW()) * ('Shipments by country'!$I$2:$I1023 > 0) * ('Shipments by country'!$B$2:$B1023 = $A25) ) ), 0 )"),18813.029904182167) -> 18813.03 | V25: =SUMIF('Shipments by country'!$B:$B,$A25,'Shipments by country'!$K:$K) -> 184.20915 | W25: =IFERROR(__xludf.DUMMYFUNCTION("IFERROR( SUM( FILTER( 'Shipments by country'!$H$2:$H1023 * ( INDEX(Countries!$T$2:$T1023, MATCH('Shipments by country'!$B$2:$B1023, Countries!$A$2:$A1023, 0) ) / 1000000 ) * INDEX('Vaccine efficacy curves'!$C$2:$C1023, MATCH('Shipments by country'!$C$2:$C"&"1023, 'Vaccine efficacy curves'!$A$2:$A1023, 0) ), ('Shipments by country'!$E$2:$E1023 < NOW()) * ('Shipments by country'!$I$2:$I1023 > 0) * ('Shipments by country'!$B$2:$B1023 = $A25) ) ), 0 )"),37.31931840212465) -> 37.319318 | X25: =SUMIF('Shipments by country'!$B:$B,$A25,'Shipments by country'!$L:$L) -> 9717.7152 | Y25: =IFERROR(__xludf.DUMMYFUNCTION("IFERROR( SUM( FILTER( 'Shipments by country'!$H$2:$H1023 * ( INDEX(Countries!$S$2:$S1023, MATCH('Shipments by country'!$B$2:$B1023, Countries!$A$2:$A1023, 0) ) / 1000000 ) * INDEX('Vaccine efficacy curves'!$C$2:$C1023, MATCH('Shipments by country'!$C$2:$C"&"1023, 'Vaccine efficacy curves'!$A$2:$A1023, 0) ), ('Shipments by country'!$E$2:$E1023 < NOW()) * ('Shipments by country'!$I$2:$I1023 > 0.25) * ('Shipments by country'!$B$2:$B1023 = $A25) ) ), 0 )"),18404.750286374714) -> 18404.75 | Z25: =SUMIF('Shipments by country'!$B:$B,$A25,'Shipments by country'!$M:$M) -> 137.61977 | AA25: =IFERROR(__xludf.DUMMYFUNCTION("IFERROR( SUM( FILTER( 'Shipments by country'!$H$2:$H1023 * ( INDEX(Countries!$T$2:$T1023, MATCH('Shipments by country'!$B$2:$B1023, Countries!$A$2:$A1023, 0) ) / 1000000 ) * INDEX('Vaccine efficacy curves'!$C$2:$C1023, MATCH('Shipments by country'!$C$2:$C"&"1023, 'Vaccine efficacy curves'!$A$2:$A1023, 0) ), ('Shipments by country'!$E$2:$E1023 < NOW()) * ('Shipments by country'!$I$2:$I1023 > 0.25) * ('Shipments by country'!$B$2:$B1023 = $A25) ) ), 0 )"),36.50941605616245) -> 36.509416 | AB25: =SUMIF('Shipments by country'!$B:$B,$A25,'Shipments by country'!$N:$N) -> 7259.9531 | AC25: =IFERROR(__xludf.DUMMYFUNCTION("IFERROR( SUM( FILTER( 'Shipments by country'!$H$2:$H1023 * ( INDEX(Countries!$S$2:$S1023, MATCH('Shipments by country'!$B$2:$B1023, Countries!$A$2:$A1023, 0) ) / 1000000 ) * 'Shipments by country'!$J$2:$J1023, ('Shipments by country'!$E$2:$E1023 < NOW()) "&"* ('Shipments by country'!$I$2:$I1023 > 0) * ('Shipments by country'!$B$2:$B1023 = $A25) ) ), 0 )"),18235.079968274822) -> 18235.08 | AD25: =SUMIF('Shipments by country'!$B:$B,$A25,'Shipments by country'!$O:$O) -> 179.38457 | AE25: =IFERROR(__xludf.DUMMYFUNCTION("IFERROR( SUM( FILTER( 'Shipments by country'!$H$2:$H1023 * ( INDEX(Countries!$T$2:$T1023, MATCH('Shipments by country'!$B$2:$B1023, Countries!$A$2:$A1023, 0) ) / 1000000 ) * 'Shipments by country'!$J$2:$J1023, ('Shipments by country'!$E$2:$E1023 < NOW()) "&"* ('Shipments by country'!$I$2:$I1023 > 0) * ('Shipments by country'!$B$2:$B1023 = $A25) ) ), 0 )"),36.17284184898746) -> 36.172842 | AF25: =SUMIF('Shipments by country'!$B:$B,$A25,'Shipments by country'!$P:$P) -> 9463.201 | AG25: =IFERROR(__xludf.DUMMYFUNCTION("IFERROR( SUM( FILTER( 'Shipments by country'!$H$2:$H1023 * INDEX(Countries!$S$2:$S1023, MATCH('Shipments by country'!$B$2:$B1023, Countries!$A$2:$A1023, 0) ) / 1000000 "&" * 'Shipments by country'!$J$2:$J1023, ( 'Shipments by country'!$E$2:$E1023 < NOW() ) * ( 'Shipments by country'!$I$2:$I1023 > 0.25 ) * ( 'Shipments by country'!$"&"B$2:$B1023 = $A25 ) ) ), 0 ) "),17826.80035046737) -> 17826.8 | AH25: =SUMIF('Shipments by country'!$B:$B,$A25,'Shipments by country'!$Q:$Q) -> 2379.3058 | AI25: =IFERROR(__xludf.DUMMYFUNCTION("IFERROR( SUM( FILTER( 'Shipments by country'!$H$2:$H1023 * ( INDEX(Countries!$T$2:$T1023, MATCH('Shipments by country'!$B$2:$B1023, Countries!$A$2:$A1023, 0) ) / 1000000 ) * 'Shipments by country"&"'!$J$2:$J1023, ('Shipments by country'!$E$2:$E1023 < NOW()) * ('Shipments by country'!$I$2:$I1023 > 0.25) * ('Shipments by country'!$B$2:$B1023 = $A25) ) ), 0 ) "),35.36293950302526) -> 35.36294 | AJ25: =SUMIF('Shipments by country'!$B:$B,$A25,'Shipments by country'!$R:$R) -> 8.2107955 | AK25: =O25*4 -> 2402405.2 | AL25: =AK25*'Vaccine pricing'!B3 -> 7183191.5 | AM25: =IF($A25="","", LET( ctry,$A25, ctryCol,'Shipments by country'!$B$2:$B1023, vaccCol,'Shipments by country'!$C$2:$C1023, finCol,'Shipments by country'!$D$2:$D1023, doseCol,'Shipments by country'!$F$2:$F1023, price,IFERROR(VLOOKUP(vaccCol,'Vaccine pricing'!$A$2:$B1023,2,FALSE),0), totCost,SUMPRODUCT((ctryCol=ctry)*doseCol*price), gaviCost,SUMPRODUCT((ctryCol=ctry)*(finCol="Gavi")*doseCol*price), IF(totCost=0,"",gaviCost/totCost) )) -> 0.97829804 | AN25: 11 | AO25: 480481.04 | AP25: 677 | AQ25: ='Vaccine pricing'!$B$3*4/((S25/1000000)*'Vaccine efficacy curves'!$C$3) -> 85.367194 | AR25: ='Vaccine pricing'!$B$3*4/((T25/1000000)*'Vaccine efficacy curves'!$C$3) -> 24737.513 | AS25: =K25/5 -> 154586.4 | AT25: =AS25*4 -> 618345.6 | AU25: =AT25*'Vaccine pricing'!B3 -> 1848853.3 | AV25: =K25*31/60 -> 399348.2 | AW25: =M25/AV25 -> 0.23798154 | AX25: =AV25-M25 -> 304310.7 | AY25: =1-AW25 -> 0.76201846 | AZ25: =AX25*4 -> 1217242.8 | BA25: =AZ25*'Vaccine pricing'!B3 -> 3639556 | BB25: 243448.56
A26: Madagascar | B26: =SUMIFS('Shipments by country'!F:F, 'Shipments by country'!B:B, A26, 'Shipments by country'!C:C, "RTS,S", 'Shipments by country'!G:G, "Delivered") -> 0 | C26: =SUMIFS('Shipments by country'!F:F, 'Shipments by country'!B:B, A26, 'Shipments by country'!C:C, "R21", 'Shipments by country'!G:G, "Delivered") -> 0 | D26: =B26+C26 -> 0 | E26: =SUMIFS('Shipments by country'!F:F, 'Shipments by country'!B:B, A26, 'Shipments by country'!C:C, "RTS,S") -> 0 | F26: =SUMIFS('Shipments by country'!F:F, 'Shipments by country'!B:B, A26, 'Shipments by country'!C:C, "R21") -> 0 | G26: =E26+F26 -> 0 | H26: Initial self-financing | I26: 26000000 | J26: 31195932 | K26: 4588132 | L26: =K26*0.9 -> 4129318.8 | M26: =G26/4 -> 0 | N26: =M26/L26 -> 0 | O26: =L26-M26 -> 4129318.8 | P26: =1-N26 -> 1 | Q26: 6239943 | R26: 15974 | S26: =Q26*1000000/J26 -> 200024.25 | T26: =R26*1000000/J26 -> 512.05394 | U26: =IFERROR(__xludf.DUMMYFUNCTION("IFERROR( SUM( FILTER( 'Shipments by country'!$H$2:$H1023 * ( INDEX(Countries!$S$2:$S1023, MATCH('Shipments by country'!$B$2:$B1023, Countries!$A$2:$A1023, 0) ) / 1000000 ) * INDEX('Vaccine efficacy curves'!$C$2:$C1023, MATCH('Shipments by country'!$C$2:$C"&"1023, 'Vaccine efficacy curves'!$A$2:$A1023, 0) ), ('Shipments by country'!$E$2:$E1023 < NOW()) * ('Shipments by country'!$I$2:$I1023 > 0) * ('Shipments by country'!$B$2:$B1023 = $A26) ) ), 0 )"),0.0) -> 0 | V26: =SUMIF('Shipments by country'!$B:$B,$A26,'Shipments by country'!$K:$K) -> 0 | W26: =IFERROR(__xludf.DUMMYFUNCTION("IFERROR( SUM( FILTER( 'Shipments by country'!$H$2:$H1023 * ( INDEX(Countries!$T$2:$T1023, MATCH('Shipments by country'!$B$2:$B1023, Countries!$A$2:$A1023, 0) ) / 1000000 ) * INDEX('Vaccine efficacy curves'!$C$2:$C1023, MATCH('Shipments by country'!$C$2:$C"&"1023, 'Vaccine efficacy curves'!$A$2:$A1023, 0) ), ('Shipments by country'!$E$2:$E1023 < NOW()) * ('Shipments by country'!$I$2:$I1023 > 0) * ('Shipments by country'!$B$2:$B1023 = $A26) ) ), 0 )"),0.0) -> 0 | X26: =SUMIF('Shipments by country'!$B:$B,$A26,'Shipments by country'!$L:$L) -> 0 | Y26: =IFERROR(__xludf.DUMMYFUNCTION("IFERROR( SUM( FILTER( 'Shipments by country'!$H$2:$H1023 * ( INDEX(Countries!$S$2:$S1023, MATCH('Shipments by country'!$B$2:$B1023, Countries!$A$2:$A1023, 0) ) / 1000000 ) * INDEX('Vaccine efficacy curves'!$C$2:$C1023, MATCH('Shipments by country'!$C$2:$C"&"1023, 'Vaccine efficacy curves'!$A$2:$A1023, 0) ), ('Shipments by country'!$E$2:$E1023 < NOW()) * ('Shipments by country'!$I$2:$I1023 > 0.25) * ('Shipments by country'!$B$2:$B1023 = $A26) ) ), 0 )"),0.0) -> 0 | Z26: =SUMIF('Shipments by country'!$B:$B,$A26,'Shipments by country'!$M:$M) -> 0 | AA26: =IFERROR(__xludf.DUMMYFUNCTION("IFERROR( SUM( FILTER( 'Shipments by country'!$H$2:$H1023 * ( INDEX(Countries!$T$2:$T1023, MATCH('Shipments by country'!$B$2:$B1023, Countries!$A$2:$A1023, 0) ) / 1000000 ) * INDEX('Vaccine efficacy curves'!$C$2:$C1023, MATCH('Shipments by country'!$C$2:$C"&"1023, 'Vaccine efficacy curves'!$A$2:$A1023, 0) ), ('Shipments by country'!$E$2:$E1023 < NOW()) * ('Shipments by country'!$I$2:$I1023 > 0.25) * ('Shipments by country'!$B$2:$B1023 = $A26) ) ), 0 )"),0.0) -> 0 | AB26: =SUMIF('Shipments by country'!$B:$B,$A26,'Shipments by country'!$N:$N) -> 0 | AC26: =IFERROR(__xludf.DUMMYFUNCTION("IFERROR( SUM( FILTER( 'Shipments by country'!$H$2:$H1023 * ( INDEX(Countries!$S$2:$S1023, MATCH('Shipments by country'!$B$2:$B1023, Countries!$A$2:$A1023, 0) ) / 1000000 ) * 'Shipments by country'!$J$2:$J1023, ('Shipments by country'!$E$2:$E1023 < NOW()) "&"* ('Shipments by country'!$I$2:$I1023 > 0) * ('Shipments by country'!$B$2:$B1023 = $A26) ) ), 0 )"),0.0) -> 0 | AD26: =SUMIF('Shipments by country'!$B:$B,$A26,'Shipments by country'!$O:$O) -> 0 | AE26: =IFERROR(__xludf.DUMMYFUNCTION("IFERROR( SUM( FILTER( 'Shipments by country'!$H$2:$H1023 * ( INDEX(Countries!$T$2:$T1023, MATCH('Shipments by country'!$B$2:$B1023, Countries!$A$2:$A1023, 0) ) / 1000000 ) * 'Shipments by country'!$J$2:$J1023, ('Shipments by country'!$E$2:$E1023 < NOW()) "&"* ('Shipments by country'!$I$2:$I1023 > 0) * ('Shipments by country'!$B$2:$B1023 = $A26) ) ), 0 )"),0.0) -> 0 | AF26: =SUMIF('Shipments by country'!$B:$B,$A26,'Shipments by country'!$P:$P) -> 0 | AG26: =IFERROR(__xludf.DUMMYFUNCTION("IFERROR( SUM( FILTER( 'Shipments by country'!$H$2:$H1023 * INDEX(Countries!$S$2:$S1023, MATCH('Shipments by country'!$B$2:$B1023, Countries!$A$2:$A1023, 0) ) / 1000000 "&" * 'Shipments by country'!$J$2:$J1023, ( 'Shipments by country'!$E$2:$E1023 < NOW() ) * ( 'Shipments by country'!$I$2:$I1023 > 0.25 ) * ( 'Shipments by country'!$"&"B$2:$B1023 = $A26 ) ) ), 0 ) "),0.0) -> 0 | AH26: =SUMIF('Shipments by country'!$B:$B,$A26,'Shipments by country'!$Q:$Q) -> 0 | AI26: =IFERROR(__xludf.DUMMYFUNCTION("IFERROR( SUM( FILTER( 'Shipments by country'!$H$2:$H1023 * ( INDEX(Countries!$T$2:$T1023, MATCH('Shipments by country'!$B$2:$B1023, Countries!$A$2:$A1023, 0) ) / 1000000 ) * 'Shipments by country"&"'!$J$2:$J1023, ('Shipments by country'!$E$2:$E1023 < NOW()) * ('Shipments by country'!$I$2:$I1023 > 0.25) * ('Shipments by country'!$B$2:$B1023 = $A26) ) ), 0 ) "),0.0) -> 0 | AJ26: =SUMIF('Shipments by country'!$B:$B,$A26,'Shipments by country'!$R:$R) -> 0 | AK26: =O26*4 -> 16517275 | AL26: =AK26*'Vaccine pricing'!B3 -> 49386653 | AM26: =IF($A26="","", LET( ctry,$A26, ctryCol,'Shipments by country'!$B$2:$B1023, vaccCol,'Shipments by country'!$C$2:$C1023, finCol,'Shipments by country'!$D$2:$D1023, doseCol,'Shipments by country'!$F$2:$F1023, price,IFERROR(VLOOKUP(vaccCol,'Vaccine pricing'!$A$2:$B1023,2,FALSE),0), totCost,SUMPRODUCT((ctryCol=ctry)*doseCol*price), gaviCost,SUMPRODUCT((ctryCol=ctry)*(finCol="Gavi")*doseCol*price), IF(totCost=0,"",gaviCost/totCost) )) | AN26: 11 | AO26: 3303455 | AP26: 513 | AQ26: ='Vaccine pricing'!$B$3*4/((S26/1000000)*'Vaccine efficacy curves'!$C$3) -> 79.723666 | AR26: ='Vaccine pricing'!$B$3*4/((T26/1000000)*'Vaccine efficacy curves'!$C$3) -> 31142.552 | AS26: =K26/5 -> 917626.4 | AT26: =AS26*4 -> 3670505.6 | AU26: =AT26*'Vaccine pricing'!B3 -> 10974812 | AV26: =K26*31/60 -> 2370534.9 | AW26: =M26/AV26 -> 0 | AX26: =AV26-M26 -> 2370534.9 | AY26: =1-AW26 -> 1 | AZ26: =AX26*4 -> 9482139.5 | BA26: =AZ26*'Vaccine pricing'!B3 -> 28351597 | BB26: 1896427.9
A27: Malawi | B27: =SUMIFS('Shipments by country'!F:F, 'Shipments by country'!B:B, A27, 'Shipments by country'!C:C, "RTS,S", 'Shipments by country'!G:G, "Delivered") -> 2223450 | C27: =SUMIFS('Shipments by country'!F:F, 'Shipments by country'!B:B, A27, 'Shipments by country'!C:C, "R21", 'Shipments by country'!G:G, "Delivered") -> 0 | D27: =B27+C27 -> 2223450 | E27: =SUMIFS('Shipments by country'!F:F, 'Shipments by country'!B:B, A27, 'Shipments by country'!C:C, "RTS,S") -> 2250050 | F27: =SUMIFS('Shipments by country'!F:F, 'Shipments by country'!B:B, A27, 'Shipments by country'!C:C, "R21") -> 0 | G27: =E27+F27 -> 2250050 | H27: Initial self-financing | I27: 24000000 | J27: 21104482 | K27: 3079812 | L27: =K27*0.9 -> 2771830.8 | M27: =G27/4 -> 562512.5 | N27: =M27/L27 -> 0.20293897 | O27: =L27-M27 -> 2209318.3 | P27: =1-N27 -> 0.79706103 | Q27: 4810053 | R27: 7376 | S27: =Q27*1000000/J27 -> 227916.18 | T27: =R27*1000000/J27 -> 349.49922 | U27: =IFERROR(__xludf.DUMMYFUNCTION("IFERROR( SUM( FILTER( 'Shipments by country'!$H$2:$H1023 * ( INDEX(Countries!$S$2:$S1023, MATCH('Shipments by country'!$B$2:$B1023, Countries!$A$2:$A1023, 0) ) / 1000000 ) * INDEX('Vaccine efficacy curves'!$C$2:$C1023, MATCH('Shipments by country'!$C$2:$C"&"1023, 'Vaccine efficacy curves'!$A$2:$A1023, 0) ), ('Shipments by country'!$E$2:$E1023 < NOW()) * ('Shipments by country'!$I$2:$I1023 > 0) * ('Shipments by country'!$B$2:$B1023 = $A27) ) ), 0 )"),110035.06863199746) -> 110035.07 | V27: =SUMIF('Shipments by country'!$B:$B,$A27,'Shipments by country'!$K:$K) -> 2039.3262 | W27: =IFERROR(__xludf.DUMMYFUNCTION("IFERROR( SUM( FILTER( 'Shipments by country'!$H$2:$H1023 * ( INDEX(Countries!$T$2:$T1023, MATCH('Shipments by country'!$B$2:$B1023, Countries!$A$2:$A1023, 0) ) / 1000000 ) * INDEX('Vaccine efficacy curves'!$C$2:$C1023, MATCH('Shipments by country'!$C$2:$C"&"1023, 'Vaccine efficacy curves'!$A$2:$A1023, 0) ), ('Shipments by country'!$E$2:$E1023 < NOW()) * ('Shipments by country'!$I$2:$I1023 > 0) * ('Shipments by country'!$B$2:$B1023 = $A27) ) ), 0 )"),218.27604498541115) -> 218.27605 | X27: =SUMIF('Shipments by country'!$B:$B,$A27,'Shipments by country'!$L:$L) -> 63014.566 | Y27: =IFERROR(__xludf.DUMMYFUNCTION("IFERROR( SUM( FILTER( 'Shipments by country'!$H$2:$H1023 * ( INDEX(Countries!$S$2:$S1023, MATCH('Shipments by country'!$B$2:$B1023, Countries!$A$2:$A1023, 0) ) / 1000000 ) * INDEX('Vaccine efficacy curves'!$C$2:$C1023, MATCH('Shipments by country'!$C$2:$C"&"1023, 'Vaccine efficacy curves'!$A$2:$A1023, 0) ), ('Shipments by country'!$E$2:$E1023 < NOW()) * ('Shipments by country'!$I$2:$I1023 > 0.25) * ('Shipments by country'!$B$2:$B1023 = $A27) ) ), 0 )"),110035.06863199746) -> 110035.07 | Z27: =SUMIF('Shipments by country'!$B:$B,$A27,'Shipments by country'!$M:$M) -> 1465.3203 | AA27: =IFERROR(__xludf.DUMMYFUNCTION("IFERROR( SUM( FILTER( 'Shipments by country'!$H$2:$H1023 * ( INDEX(Countries!$T$2:$T1023, MATCH('Shipments by country'!$B$2:$B1023, Countries!$A$2:$A1023, 0) ) / 1000000 ) * INDEX('Vaccine efficacy curves'!$C$2:$C1023, MATCH('Shipments by country'!$C$2:$C"&"1023, 'Vaccine efficacy curves'!$A$2:$A1023, 0) ), ('Shipments by country'!$E$2:$E1023 < NOW()) * ('Shipments by country'!$I$2:$I1023 > 0.25) * ('Shipments by country'!$B$2:$B1023 = $A27) ) ), 0 )"),218.27604498541115) -> 218.27605 | AB27: =SUMIF('Shipments by country'!$B:$B,$A27,'Shipments by country'!$N:$N) -> 45277.958 | AC27: =IFERROR(__xludf.DUMMYFUNCTION("IFERROR( SUM( FILTER( 'Shipments by country'!$H$2:$H1023 * ( INDEX(Countries!$S$2:$S1023, MATCH('Shipments by country'!$B$2:$B1023, Countries!$A$2:$A1023, 0) ) / 1000000 ) * 'Shipments by country'!$J$2:$J1023, ('Shipments by country'!$E$2:$E1023 < NOW()) "&"* ('Shipments by country'!$I$2:$I1023 > 0) * ('Shipments by country'!$B$2:$B1023 = $A27) ) ), 0 )"),106859.80434981213) -> 106859.8 | AD27: =SUMIF('Shipments by country'!$B:$B,$A27,'Shipments by country'!$O:$O) -> 1984.1129 | AE27: =IFERROR(__xludf.DUMMYFUNCTION("IFERROR( SUM( FILTER( 'Shipments by country'!$H$2:$H1023 * ( INDEX(Countries!$T$2:$T1023, MATCH('Shipments by country'!$B$2:$B1023, Countries!$A$2:$A1023, 0) ) / 1000000 ) * 'Shipments by country'!$J$2:$J1023, ('Shipments by country'!$E$2:$E1023 < NOW()) "&"* ('Shipments by country'!$I$2:$I1023 > 0) * ('Shipments by country'!$B$2:$B1023 = $A27) ) ), 0 )"),211.9772882534386) -> 211.97729 | AF27: =SUMIF('Shipments by country'!$B:$B,$A27,'Shipments by country'!$P:$P) -> 61308.492 | AG27: =IFERROR(__xludf.DUMMYFUNCTION("IFERROR( SUM( FILTER( 'Shipments by country'!$H$2:$H1023 * INDEX(Countries!$S$2:$S1023, MATCH('Shipments by country'!$B$2:$B1023, Countries!$A$2:$A1023, 0) ) / 1000000 "&" * 'Shipments by country'!$J$2:$J1023, ( 'Shipments by country'!$E$2:$E1023 < NOW() ) * ( 'Shipments by country'!$I$2:$I1023 > 0.25 ) * ( 'Shipments by country'!$"&"B$2:$B1023 = $A27 ) ) ), 0 ) "),106859.80434981214) -> 106859.8 | AH27: =SUMIF('Shipments by country'!$B:$B,$A27,'Shipments by country'!$Q:$Q) -> 16927.182 | AI27: =IFERROR(__xludf.DUMMYFUNCTION("IFERROR( SUM( FILTER( 'Shipments by country'!$H$2:$H1023 * ( INDEX(Countries!$T$2:$T1023, MATCH('Shipments by country'!$B$2:$B1023, Countries!$A$2:$A1023, 0) ) / 1000000 ) * 'Shipments by country"&"'!$J$2:$J1023, ('Shipments by country'!$E$2:$E1023 < NOW()) * ('Shipments by country'!$I$2:$I1023 > 0.25) * ('Shipments by country'!$B$2:$B1023 = $A27) ) ), 0 ) "),211.9772882534386) -> 211.97729 | AJ27: =SUMIF('Shipments by country'!$B:$B,$A27,'Shipments by country'!$R:$R) -> 25.957073 | AK27: =O27*4 -> 8837273.2 | AL27: =AK27*'Vaccine pricing'!B3 -> 26423447 | AM27: =IF($A27="","", LET( ctry,$A27, ctryCol,'Shipments by country'!$B$2:$B1023, vaccCol,'Shipments by country'!$C$2:$C1023, finCol,'Shipments by country'!$D$2:$D1023, doseCol,'Shipments by country'!$F$2:$F1023, price,IFERROR(VLOOKUP(vaccCol,'Vaccine pricing'!$A$2:$B1023,2,FALSE),0), totCost,SUMPRODUCT((ctryCol=ctry)*doseCol*price), gaviCost,SUMPRODUCT((ctryCol=ctry)*(finCol="Gavi")*doseCol*price), IF(totCost=0,"",gaviCost/totCost) )) -> 0.97855603 | AN27: 11 | AO27: 1767454.6 | AP27: 637 | AQ27: ='Vaccine pricing'!$B$3*4/((S27/1000000)*'Vaccine efficacy curves'!$C$3) -> 69.967241 | AR27: ='Vaccine pricing'!$B$3*4/((T27/1000000)*'Vaccine efficacy curves'!$C$3) -> 45627.188 | AS27: =K27/5 -> 615962.4 | AT27: =AS27*4 -> 2463849.6 | AU27: =AT27*'Vaccine pricing'!B3 -> 7366910.3 | AV27: =K27*31/60 -> 1591236.2 | AW27: =M27/AV27 -> 0.3535066 | AX27: =AV27-M27 -> 1028723.7 | AY27: =1-AW27 -> 0.6464934 | AZ27: =AX27*4 -> 4114894.8 | BA27: =AZ27*'Vaccine pricing'!B3 -> 12303535 | BB27: 822978.96
A28: Mali | B28: =SUMIFS('Shipments by country'!F:F, 'Shipments by country'!B:B, A28, 'Shipments by country'!C:C, "RTS,S", 'Shipments by country'!G:G, "Delivered") -> 0 | C28: =SUMIFS('Shipments by country'!F:F, 'Shipments by country'!B:B, A28, 'Shipments by country'!C:C, "R21", 'Shipments by country'!G:G, "Delivered") -> 927800 | D28: =B28+C28 -> 927800 | E28: =SUMIFS('Shipments by country'!F:F, 'Shipments by country'!B:B, A28, 'Shipments by country'!C:C, "RTS,S") -> 0 | F28: =SUMIFS('Shipments by country'!F:F, 'Shipments by country'!B:B, A28, 'Shipments by country'!C:C, "R21") -> 975600 | G28: =E28+F28 -> 975600 | H28: Initial self-financing | I28: 25000000 | J28: 23769127 | K28: 4158173 | L28: =K28*0.9 -> 3742355.7 | M28: =G28/4 -> 243900 | N28: =M28/L28 -> 0.065172854 | O28: =L28-M28 -> 3498455.7 | P28: =1-N28 -> 0.93482715 | Q28: 8229337 | R28: 14203 | S28: =Q28*1000000/J28 -> 346219.57 | T28: =R28*1000000/J28 -> 597.53983 | U28: =IFERROR(__xludf.DUMMYFUNCTION("IFERROR( SUM( FILTER( 'Shipments by country'!$H$2:$H1023 * ( INDEX(Countries!$S$2:$S1023, MATCH('Shipments by country'!$B$2:$B1023, Countries!$A$2:$A1023, 0) ) / 1000000 ) * INDEX('Vaccine efficacy curves'!$C$2:$C1023, MATCH('Shipments by country'!$C$2:$C"&"1023, 'Vaccine efficacy curves'!$A$2:$A1023, 0) ), ('Shipments by country'!$E$2:$E1023 < NOW()) * ('Shipments by country'!$I$2:$I1023 > 0) * ('Shipments by country'!$B$2:$B1023 = $A28) ) ), 0 )"),45915.37326081866) -> 45915.373 | V28: =SUMIF('Shipments by country'!$B:$B,$A28,'Shipments by country'!$K:$K) -> 1667.2831 | W28: =IFERROR(__xludf.DUMMYFUNCTION("IFERROR( SUM( FILTER( 'Shipments by country'!$H$2:$H1023 * ( INDEX(Countries!$T$2:$T1023, MATCH('Shipments by country'!$B$2:$B1023, Countries!$A$2:$A1023, 0) ) / 1000000 ) * INDEX('Vaccine efficacy curves'!$C$2:$C1023, MATCH('Shipments by country'!$C$2:$C"&"1023, 'Vaccine efficacy curves'!$A$2:$A1023, 0) ), ('Shipments by country'!$E$2:$E1023 < NOW()) * ('Shipments by country'!$I$2:$I1023 > 0) * ('Shipments by country'!$B$2:$B1023 = $A28) ) ), 0 )"),91.08210867681507) -> 91.082109 | X28: =SUMIF('Shipments by country'!$B:$B,$A28,'Shipments by country'!$L:$L) -> 40642.544 | Y28: =IFERROR(__xludf.DUMMYFUNCTION("IFERROR( SUM( FILTER( 'Shipments by country'!$H$2:$H1023 * ( INDEX(Countries!$S$2:$S1023, MATCH('Shipments by country'!$B$2:$B1023, Countries!$A$2:$A1023, 0) ) / 1000000 ) * INDEX('Vaccine efficacy curves'!$C$2:$C1023, MATCH('Shipments by country'!$C$2:$C"&"1023, 'Vaccine efficacy curves'!$A$2:$A1023, 0) ), ('Shipments by country'!$E$2:$E1023 < NOW()) * ('Shipments by country'!$I$2:$I1023 > 0.25) * ('Shipments by country'!$B$2:$B1023 = $A28) ) ), 0 )"),45915.37326081866) -> 45915.373 | Z28: =SUMIF('Shipments by country'!$B:$B,$A28,'Shipments by country'!$M:$M) -> 1049.5858 | AA28: =IFERROR(__xludf.DUMMYFUNCTION("IFERROR( SUM( FILTER( 'Shipments by country'!$H$2:$H1023 * ( INDEX(Countries!$T$2:$T1023, MATCH('Shipments by country'!$B$2:$B1023, Countries!$A$2:$A1023, 0) ) / 1000000 ) * INDEX('Vaccine efficacy curves'!$C$2:$C1023, MATCH('Shipments by country'!$C$2:$C"&"1023, 'Vaccine efficacy curves'!$A$2:$A1023, 0) ), ('Shipments by country'!$E$2:$E1023 < NOW()) * ('Shipments by country'!$I$2:$I1023 > 0.25) * ('Shipments by country'!$B$2:$B1023 = $A28) ) ), 0 )"),91.08210867681507) -> 91.082109 | AB28: =SUMIF('Shipments by country'!$B:$B,$A28,'Shipments by country'!$N:$N) -> 25585.238 | AC28: =IFERROR(__xludf.DUMMYFUNCTION("IFERROR( SUM( FILTER( 'Shipments by country'!$H$2:$H1023 * ( INDEX(Countries!$S$2:$S1023, MATCH('Shipments by country'!$B$2:$B1023, Countries!$A$2:$A1023, 0) ) / 1000000 ) * 'Shipments by country'!$J$2:$J1023, ('Shipments by country'!$E$2:$E1023 < NOW()) "&"* ('Shipments by country'!$I$2:$I1023 > 0) * ('Shipments by country'!$B$2:$B1023 = $A28) ) ), 0 )"),61493.8034743107) -> 61493.803 | AD28: =SUMIF('Shipments by country'!$B:$B,$A28,'Shipments by country'!$O:$O) -> 1667.2831 | AE28: =IFERROR(__xludf.DUMMYFUNCTION("IFERROR( SUM( FILTER( 'Shipments by country'!$H$2:$H1023 * ( INDEX(Countries!$T$2:$T1023, MATCH('Shipments by country'!$B$2:$B1023, Countries!$A$2:$A1023, 0) ) / 1000000 ) * 'Shipments by country'!$J$2:$J1023, ('Shipments by country'!$E$2:$E1023 < NOW()) "&"* ('Shipments by country'!$I$2:$I1023 > 0) * ('Shipments by country'!$B$2:$B1023 = $A28) ) ), 0 )"),121.9849669778773) -> 121.98497 | AF28: =SUMIF('Shipments by country'!$B:$B,$A28,'Shipments by country'!$P:$P) -> 40642.544 | AG28: =IFERROR(__xludf.DUMMYFUNCTION("IFERROR( SUM( FILTER( 'Shipments by country'!$H$2:$H1023 * INDEX(Countries!$S$2:$S1023, MATCH('Shipments by country'!$B$2:$B1023, Countries!$A$2:$A1023, 0) ) / 1000000 "&" * 'Shipments by country'!$J$2:$J1023, ( 'Shipments by country'!$E$2:$E1023 < NOW() ) * ( 'Shipments by country'!$I$2:$I1023 > 0.25 ) * ( 'Shipments by country'!$"&"B$2:$B1023 = $A28 ) ) ), 0 ) "),61493.8034743107) -> 61493.803 | AH28: =SUMIF('Shipments by country'!$B:$B,$A28,'Shipments by country'!$Q:$Q) -> 15057.306 | AI28: =IFERROR(__xludf.DUMMYFUNCTION("IFERROR( SUM( FILTER( 'Shipments by country'!$H$2:$H1023 * ( INDEX(Countries!$T$2:$T1023, MATCH('Shipments by country'!$B$2:$B1023, Countries!$A$2:$A1023, 0) ) / 1000000 ) * 'Shipments by country"&"'!$J$2:$J1023, ('Shipments by country'!$E$2:$E1023 < NOW()) * ('Shipments by country'!$I$2:$I1023 > 0.25) * ('Shipments by country'!$B$2:$B1023 = $A28) ) ), 0 ) "),121.9849669778773) -> 121.98497 | AJ28: =SUMIF('Shipments by country'!$B:$B,$A28,'Shipments by country'!$R:$R) -> 25.98738 | AK28: =O28*4 -> 13993823 | AL28: =AK28*'Vaccine pricing'!B3 -> 41841530 | AM28: =IF($A28="","", LET( ctry,$A28, ctryCol,'Shipments by country'!$B$2:$B1023, vaccCol,'Shipments by country'!$C$2:$C1023, finCol,'Shipments by country'!$D$2:$D1023, doseCol,'Shipments by country'!$F$2:$F1023, price,IFERROR(VLOOKUP(vaccCol,'Vaccine pricing'!$A$2:$B1023,2,FALSE),0), totCost,SUMPRODUCT((ctryCol=ctry)*doseCol*price), gaviCost,SUMPRODUCT((ctryCol=ctry)*(finCol="Gavi")*doseCol*price), IF(totCost=0,"",gaviCost/totCost) )) -> 0.95100451 | AN28: 11 | AO28: 2798764.6 | AP28: 860 | AQ28: ='Vaccine pricing'!$B$3*4/((S28/1000000)*'Vaccine efficacy curves'!$C$3) -> 46.059402 | AR28: ='Vaccine pricing'!$B$3*4/((T28/1000000)*'Vaccine efficacy curves'!$C$3) -> 26687.203 | AS28: =K28/5 -> 831634.6 | AT28: =AS28*4 -> 3326538.4 | AU28: =AT28*'Vaccine pricing'!B3 -> 9946349.8 | AV28: =K28*31/60 -> 2148389.4 | AW28: =M28/AV28 -> 0.11352691 | AX28: =AV28-M28 -> 1904489.4 | AY28: =1-AW28 -> 0.88647309 | AZ28: =AX28*4 -> 7617957.5 | BA28: =AZ28*'Vaccine pricing'!B3 -> 22777693 | BB28: 1523591.5
A29: Mauritania | B29: =SUMIFS('Shipments by country'!F:F, 'Shipments by country'!B:B, A29, 'Shipments by country'!C:C, "RTS,S", 'Shipments by country'!G:G, "Delivered") -> 0 | C29: =SUMIFS('Shipments by country'!F:F, 'Shipments by country'!B:B, A29, 'Shipments by country'!C:C, "R21", 'Shipments by country'!G:G, "Delivered") -> 0 | D29: =B29+C29 -> 0 | E29: =SUMIFS('Shipments by country'!F:F, 'Shipments by country'!B:B, A29, 'Shipments by country'!C:C, "RTS,S") -> 0 | F29: =SUMIFS('Shipments by country'!F:F, 'Shipments by country'!B:B, A29, 'Shipments by country'!C:C, "R21") -> 0 | G29: =E29+F29 -> 0 | H29: Preparatory transition | I29: 0 | J29: 5022441 | K29: 799917 | L29: =K29*0.9 -> 719925.3 | M29: =G29/4 -> 0 | N29: =M29/L29 -> 0 | O29: =L29-M29 -> 719925.3 | P29: =1-N29 -> 1 | Q29: 192584 | R29: 493 | S29: =Q29*1000000/J29 -> 38344.701 | T29: =R29*1000000/J29 -> 98.159441 | U29: =IFERROR(__xludf.DUMMYFUNCTION("IFERROR( SUM( FILTER( 'Shipments by country'!$H$2:$H1023 * ( INDEX(Countries!$S$2:$S1023, MATCH('Shipments by country'!$B$2:$B1023, Countries!$A$2:$A1023, 0) ) / 1000000 ) * INDEX('Vaccine efficacy curves'!$C$2:$C1023, MATCH('Shipments by country'!$C$2:$C"&"1023, 'Vaccine efficacy curves'!$A$2:$A1023, 0) ), ('Shipments by country'!$E$2:$E1023 < NOW()) * ('Shipments by country'!$I$2:$I1023 > 0) * ('Shipments by country'!$B$2:$B1023 = $A29) ) ), 0 )"),0.0) -> 0 | V29: =SUMIF('Shipments by country'!$B:$B,$A29,'Shipments by country'!$K:$K) -> 0 | W29: =IFERROR(__xludf.DUMMYFUNCTION("IFERROR( SUM( FILTER( 'Shipments by country'!$H$2:$H1023 * ( INDEX(Countries!$T$2:$T1023, MATCH('Shipments by country'!$B$2:$B1023, Countries!$A$2:$A1023, 0) ) / 1000000 ) * INDEX('Vaccine efficacy curves'!$C$2:$C1023, MATCH('Shipments by country'!$C$2:$C"&"1023, 'Vaccine efficacy curves'!$A$2:$A1023, 0) ), ('Shipments by country'!$E$2:$E1023 < NOW()) * ('Shipments by country'!$I$2:$I1023 > 0) * ('Shipments by country'!$B$2:$B1023 = $A29) ) ), 0 )"),0.0) -> 0 | X29: =SUMIF('Shipments by country'!$B:$B,$A29,'Shipments by country'!$L:$L) -> 0 | Y29: =IFERROR(__xludf.DUMMYFUNCTION("IFERROR( SUM( FILTER( 'Shipments by country'!$H$2:$H1023 * ( INDEX(Countries!$S$2:$S1023, MATCH('Shipments by country'!$B$2:$B1023, Countries!$A$2:$A1023, 0) ) / 1000000 ) * INDEX('Vaccine efficacy curves'!$C$2:$C1023, MATCH('Shipments by country'!$C$2:$C"&"1023, 'Vaccine efficacy curves'!$A$2:$A1023, 0) ), ('Shipments by country'!$E$2:$E1023 < NOW()) * ('Shipments by country'!$I$2:$I1023 > 0.25) * ('Shipments by country'!$B$2:$B1023 = $A29) ) ), 0 )"),0.0) -> 0 | Z29: =SUMIF('Shipments by country'!$B:$B,$A29,'Shipments by country'!$M:$M) -> 0 | AA29: =IFERROR(__xludf.DUMMYFUNCTION("IFERROR( SUM( FILTER( 'Shipments by country'!$H$2:$H1023 * ( INDEX(Countries!$T$2:$T1023, MATCH('Shipments by country'!$B$2:$B1023, Countries!$A$2:$A1023, 0) ) / 1000000 ) * INDEX('Vaccine efficacy curves'!$C$2:$C1023, MATCH('Shipments by country'!$C$2:$C"&"1023, 'Vaccine efficacy curves'!$A$2:$A1023, 0) ), ('Shipments by country'!$E$2:$E1023 < NOW()) * ('Shipments by country'!$I$2:$I1023 > 0.25) * ('Shipments by country'!$B$2:$B1023 = $A29) ) ), 0 )"),0.0) -> 0 | AB29: =SUMIF('Shipments by country'!$B:$B,$A29,'Shipments by country'!$N:$N) -> 0 | AC29: =IFERROR(__xludf.DUMMYFUNCTION("IFERROR( SUM( FILTER( 'Shipments by country'!$H$2:$H1023 * ( INDEX(Countries!$S$2:$S1023, MATCH('Shipments by country'!$B$2:$B1023, Countries!$A$2:$A1023, 0) ) / 1000000 ) * 'Shipments by country'!$J$2:$J1023, ('Shipments by country'!$E$2:$E1023 < NOW()) "&"* ('Shipments by country'!$I$2:$I1023 > 0) * ('Shipments by country'!$B$2:$B1023 = $A29) ) ), 0 )"),0.0) -> 0 | AD29: =SUMIF('Shipments by country'!$B:$B,$A29,'Shipments by country'!$O:$O) -> 0 | AE29: =IFERROR(__xludf.DUMMYFUNCTION("IFERROR( SUM( FILTER( 'Shipments by country'!$H$2:$H1023 * ( INDEX(Countries!$T$2:$T1023, MATCH('Shipments by country'!$B$2:$B1023, Countries!$A$2:$A1023, 0) ) / 1000000 ) * 'Shipments by country'!$J$2:$J1023, ('Shipments by country'!$E$2:$E1023 < NOW()) "&"* ('Shipments by country'!$I$2:$I1023 > 0) * ('Shipments by country'!$B$2:$B1023 = $A29) ) ), 0 )"),0.0) -> 0 | AF29: =SUMIF('Shipments by country'!$B:$B,$A29,'Shipments by country'!$P:$P) -> 0 | AG29: =IFERROR(__xludf.DUMMYFUNCTION("IFERROR( SUM( FILTER( 'Shipments by country'!$H$2:$H1023 * INDEX(Countries!$S$2:$S1023, MATCH('Shipments by country'!$B$2:$B1023, Countries!$A$2:$A1023, 0) ) / 1000000 "&" * 'Shipments by country'!$J$2:$J1023, ( 'Shipments by country'!$E$2:$E1023 < NOW() ) * ( 'Shipments by country'!$I$2:$I1023 > 0.25 ) * ( 'Shipments by country'!$"&"B$2:$B1023 = $A29 ) ) ), 0 ) "),0.0) -> 0 | AH29: =SUMIF('Shipments by country'!$B:$B,$A29,'Shipments by country'!$Q:$Q) -> 0 | AI29: =IFERROR(__xludf.DUMMYFUNCTION("IFERROR( SUM( FILTER( 'Shipments by country'!$H$2:$H1023 * ( INDEX(Countries!$T$2:$T1023, MATCH('Shipments by country'!$B$2:$B1023, Countries!$A$2:$A1023, 0) ) / 1000000 ) * 'Shipments by country"&"'!$J$2:$J1023, ('Shipments by country'!$E$2:$E1023 < NOW()) * ('Shipments by country'!$I$2:$I1023 > 0.25) * ('Shipments by country'!$B$2:$B1023 = $A29) ) ), 0 ) "),0.0) -> 0 | AJ29: =SUMIF('Shipments by country'!$B:$B,$A29,'Shipments by country'!$R:$R) -> 0 | AK29: =O29*4 -> 2879701.2 | AL29: =AK29*'Vaccine pricing'!B3 -> 8610306.6 | AM29: =IF($A29="","", LET( ctry,$A29, ctryCol,'Shipments by country'!$B$2:$B1023, vaccCol,'Shipments by country'!$C$2:$C1023, finCol,'Shipments by country'!$D$2:$D1023, doseCol,'Shipments by country'!$F$2:$F1023, price,IFERROR(VLOOKUP(vaccCol,'Vaccine pricing'!$A$2:$B1023,2,FALSE),0), totCost,SUMPRODUCT((ctryCol=ctry)*doseCol*price), gaviCost,SUMPRODUCT((ctryCol=ctry)*(finCol="Gavi")*doseCol*price), IF(totCost=0,"",gaviCost/totCost) )) | AN29: 11 | AO29: 2329999.5 | AP29: 2013 | AQ29: ='Vaccine pricing'!$B$3*4/((S29/1000000)*'Vaccine efficacy curves'!$C$3) -> 415.87667 | AR29: ='Vaccine pricing'!$B$3*4/((T29/1000000)*'Vaccine efficacy curves'!$C$3) -> 162456.78 | AS29: =K29/5 -> 159983.4 | AT29: =AS29*4 -> 639933.6 | AU29: =AT29*'Vaccine pricing'!B3 -> 1913401.5 | AV29: =K29*31/60 -> 413290.45 | AW29: =M29/AV29 -> 0 | AX29: =AV29-M29 -> 413290.45 | AY29: =1-AW29 -> 1 | AZ29: =AX29*4 -> 1653161.8 | BA29: =AZ29*'Vaccine pricing'!B3 -> 4942953.8 | BB29: 1337592.3
A30: Mozambique | B30: =SUMIFS('Shipments by country'!F:F, 'Shipments by country'!B:B, A30, 'Shipments by country'!C:C, "RTS,S", 'Shipments by country'!G:G, "Delivered") -> 0 | C30: =SUMIFS('Shipments by country'!F:F, 'Shipments by country'!B:B, A30, 'Shipments by country'!C:C, "R21", 'Shipments by country'!G:G, "Delivered") -> 3730900 | D30: =B30+C30 -> 3730900 | E30: =SUMIFS('Shipments by country'!F:F, 'Shipments by country'!B:B, A30, 'Shipments by country'!C:C, "RTS,S") -> 0 | F30: =SUMIFS('Shipments by country'!F:F, 'Shipments by country'!B:B, A30, 'Shipments by country'!C:C, "R21") -> 5614900 | G30: =E30+F30 -> 5614900 | H30: Initial self-financing | I30: 29000000 | J30: 33635160 | K30: 5668611 | L30: =K30*0.9 -> 5101749.9 | M30: =G30/4 -> 1403725 | N30: =M30/L30 -> 0.27514579 | O30: =L30-M30 -> 3698024.9 | P30: =1-N30 -> 0.72485421 | Q30: 9256415 | R30: 17875 | S30: =Q30*1000000/J30 -> 275200.56 | T30: =R30*1000000/J30 -> 531.43794 | U30: =IFERROR(__xludf.DUMMYFUNCTION("IFERROR( SUM( FILTER( 'Shipments by country'!$H$2:$H1023 * ( INDEX(Countries!$S$2:$S1023, MATCH('Shipments by country'!$B$2:$B1023, Countries!$A$2:$A1023, 0) ) / 1000000 ) * INDEX('Vaccine efficacy curves'!$C$2:$C1023, MATCH('Shipments by country'!$C$2:$C"&"1023, 'Vaccine efficacy curves'!$A$2:$A1023, 0) ), ('Shipments by country'!$E$2:$E1023 < NOW()) * ('Shipments by country'!$I$2:$I1023 > 0) * ('Shipments by country'!$B$2:$B1023 = $A30) ) ), 0 )"),196251.3518033008) -> 196251.35 | V30: =SUMIF('Shipments by country'!$B:$B,$A30,'Shipments by country'!$K:$K) -> 6570.7367 | W30: =IFERROR(__xludf.DUMMYFUNCTION("IFERROR( SUM( FILTER( 'Shipments by country'!$H$2:$H1023 * ( INDEX(Countries!$T$2:$T1023, MATCH('Shipments by country'!$B$2:$B1023, Countries!$A$2:$A1023, 0) ) / 1000000 ) * INDEX('Vaccine efficacy curves'!$C$2:$C1023, MATCH('Shipments by country'!$C$2:$C"&"1023, 'Vaccine efficacy curves'!$A$2:$A1023, 0) ), ('Shipments by country'!$E$2:$E1023 < NOW()) * ('Shipments by country'!$I$2:$I1023 > 0) * ('Shipments by country'!$B$2:$B1023 = $A30) ) ), 0 )"),389.3028779572945) -> 389.30288 | X30: =SUMIF('Shipments by country'!$B:$B,$A30,'Shipments by country'!$L:$L) -> 101161.98 | Y30: =IFERROR(__xludf.DUMMYFUNCTION("IFERROR( SUM( FILTER( 'Shipments by country'!$H$2:$H1023 * ( INDEX(Countries!$S$2:$S1023, MATCH('Shipments by country'!$B$2:$B1023, Countries!$A$2:$A1023, 0) ) / 1000000 ) * INDEX('Vaccine efficacy curves'!$C$2:$C1023, MATCH('Shipments by country'!$C$2:$C"&"1023, 'Vaccine efficacy curves'!$A$2:$A1023, 0) ), ('Shipments by country'!$E$2:$E1023 < NOW()) * ('Shipments by country'!$I$2:$I1023 > 0.25) * ('Shipments by country'!$B$2:$B1023 = $A30) ) ), 0 )"),184636.4152821603) -> 184636.42 | Z30: =SUMIF('Shipments by country'!$B:$B,$A30,'Shipments by country'!$M:$M) -> 3415.6415 | AA30: =IFERROR(__xludf.DUMMYFUNCTION("IFERROR( SUM( FILTER( 'Shipments by country'!$H$2:$H1023 * ( INDEX(Countries!$T$2:$T1023, MATCH('Shipments by country'!$B$2:$B1023, Countries!$A$2:$A1023, 0) ) / 1000000 ) * INDEX('Vaccine efficacy curves'!$C$2:$C1023, MATCH('Shipments by country'!$C$2:$C"&"1023, 'Vaccine efficacy curves'!$A$2:$A1023, 0) ), ('Shipments by country'!$E$2:$E1023 < NOW()) * ('Shipments by country'!$I$2:$I1023 > 0.25) * ('Shipments by country'!$B$2:$B1023 = $A30) ) ), 0 )"),366.26238333943667) -> 366.26238 | AB30: =SUMIF('Shipments by country'!$B:$B,$A30,'Shipments by country'!$N:$N) -> 52586.656 | AC30: =IFERROR(__xludf.DUMMYFUNCTION("IFERROR( SUM( FILTER( 'Shipments by country'!$H$2:$H1023 * ( INDEX(Countries!$S$2:$S1023, MATCH('Shipments by country'!$B$2:$B1023, Countries!$A$2:$A1023, 0) ) / 1000000 ) * 'Shipments by country'!$J$2:$J1023, ('Shipments by country'!$E$2:$E1023 < NOW()) "&"* ('Shipments by country'!$I$2:$I1023 > 0) * ('Shipments by country'!$B$2:$B1023 = $A30) ) ), 0 )"),260366.58886144432) -> 260366.59 | AD30: =SUMIF('Shipments by country'!$B:$B,$A30,'Shipments by country'!$O:$O) -> 6466.6504 | AE30: =IFERROR(__xludf.DUMMYFUNCTION("IFERROR( SUM( FILTER( 'Shipments by country'!$H$2:$H1023 * ( INDEX(Countries!$T$2:$T1023, MATCH('Shipments by country'!$B$2:$B1023, Countries!$A$2:$A1023, 0) ) / 1000000 ) * 'Shipments by country'!$J$2:$J1023, ('Shipments by country'!$E$2:$E1023 < NOW()) "&"* ('Shipments by country'!$I$2:$I1023 > 0) * ('Shipments by country'!$B$2:$B1023 = $A30) ) ), 0 )"),516.4879703314183) -> 516.48797 | AF30: =SUMIF('Shipments by country'!$B:$B,$A30,'Shipments by country'!$P:$P) -> 99559.488 | AG30: =IFERROR(__xludf.DUMMYFUNCTION("IFERROR( SUM( FILTER( 'Shipments by country'!$H$2:$H1023 * INDEX(Countries!$S$2:$S1023, MATCH('Shipments by country'!$B$2:$B1023, Countries!$A$2:$A1023, 0) ) / 1000000 "&" * 'Shipments by country'!$J$2:$J1023, ( 'Shipments by country'!$E$2:$E1023 < NOW() ) * ( 'Shipments by country'!$I$2:$I1023 > 0.25 ) * ( 'Shipments by country'!$"&"B$2:$B1023 = $A30 ) ) ), 0 ) "),244810.87030634552) -> 244810.87 | AH30: =SUMIF('Shipments by country'!$B:$B,$A30,'Shipments by country'!$Q:$Q) -> 47501.124 | AI30: =IFERROR(__xludf.DUMMYFUNCTION("IFERROR( SUM( FILTER( 'Shipments by country'!$H$2:$H1023 * ( INDEX(Countries!$T$2:$T1023, MATCH('Shipments by country'!$B$2:$B1023, Countries!$A$2:$A1023, 0) ) / 1000000 ) * 'Shipments by country"&"'!$J$2:$J1023, ('Shipments by country'!$E$2:$E1023 < NOW()) * ('Shipments by country'!$I$2:$I1023 > 0.25) * ('Shipments by country'!$B$2:$B1023 = $A30) ) ), 0 ) "),485.6301650396444) -> 485.63016 | AJ30: =SUMIF('Shipments by country'!$B:$B,$A30,'Shipments by country'!$R:$R) -> 91.729097 | AK30: =O30*4 -> 14792100 | AL30: =AK30*'Vaccine pricing'!B3 -> 44228378 | AM30: =IF($A30="","", LET( ctry,$A30, ctryCol,'Shipments by country'!$B$2:$B1023, vaccCol,'Shipments by country'!$C$2:$C1023, finCol,'Shipments by country'!$D$2:$D1023, doseCol,'Shipments by country'!$F$2:$F1023, price,IFERROR(VLOOKUP(vaccCol,'Vaccine pricing'!$A$2:$B1023,2,FALSE),0), totCost,SUMPRODUCT((ctryCol=ctry)*doseCol*price), gaviCost,SUMPRODUCT((ctryCol=ctry)*(finCol="Gavi")*doseCol*price), IF(totCost=0,"",gaviCost/totCost) )) -> 0.95121908 | AN30: 11 | AO30: 2958419.9 | AP30: 503 | AQ30: ='Vaccine pricing'!$B$3*4/((S30/1000000)*'Vaccine efficacy curves'!$C$3) -> 57.945618 | AR30: ='Vaccine pricing'!$B$3*4/((T30/1000000)*'Vaccine efficacy curves'!$C$3) -> 30006.64 | AS30: =K30/5 -> 1133722.2 | AT30: =AS30*4 -> 4534888.8 | AU30: =AT30*'Vaccine pricing'!B3 -> 13559318 | AV30: =K30*31/60 -> 2928782.4 | AW30: =M30/AV30 -> 0.47928621 | AX30: =AV30-M30 -> 1525057.4 | AY30: =1-AW30 -> 0.52071379 | AZ30: =AX30*4 -> 6100229.4 | BA30: =AZ30*'Vaccine pricing'!B3 -> 18239686 | BB30: 1220045.9
